Workbook

Sheet Read Me
B2: AI Capex Spending Cut — Scenario Analysis
B3: Impact on 2026E sales and EPS growth across AI supply-chain sub-segments, with training vs. inference capex exposure
B6: HOW TO USE
B7: • Yellow cells are inputs. Edit scenario capex growth rates on 'Scenario Assumptions' and segment exposures/baselines on 'Sub-Segment Exposures'; all downstream sheets recalculate automatically.
B9: SHEET GUIDE
B10: • Scenario Assumptions — global 2025E AI capex base, training/inference split, and four 2026E scenarios (Base, Mild Cut/Digestion, Moderate Cut/ROI Reset, Severe Cut/AI Winter) with separate training and inference capex growth paths.
B11: • Sub-Segment Exposures — 14 sub-segments with: AI-capex revenue exposure (% of sales), training vs. inference capex exposure mix, EPS operating leverage, and baseline 2026E sales/EPS growth.
B12: • Sales Growth Impact — per scenario: each segment's blended AI capex growth (weighted by its training/inference mix), the change in sales growth vs. Base (pp), and the resulting scenario sales growth.
B13: • EPS Growth Impact — applies each segment's EPS leverage factor to the sales-growth delta to get scenario EPS growth.
B14: • Summary Matrix — one-page view of sales and EPS growth by segment across all four scenarios (color-scaled).
B16: METHODOLOGY
B17: 1. Each scenario specifies separate 2026E growth rates for TRAINING capex and INFERENCE capex. Cuts hit training first (frontier-model ROI scrutiny, efficiency gains such as distillation); inference is more resilient because it is tied to usage and revenue.
... B24: • First-year sensitivities only: backlogs (semicap, power) and long leases (REITs) delay — not remove — the impact; multi-year effects would differ.

Sheet Scenario Assumptions
A1: Scenario Assumptions — 2026E AI Capex
A3: Global AI capex (hyperscalers + neoclouds + enterprise)
A4: 2025E AI capex base ($bn) | B4: 475
A5: Training share of 2025E AI capex | B5: 0.55
A6: Inference share of 2025E AI capex | B6: =1-B5
A8: Scenario | B8: Training capex growth (26E y/y) | C8: Inference capex growth (26E y/y) | D8: Blended AI capex growth | E8: Implied 2026E AI capex ($bn) | F8: Δ vs Base Case ($bn) | G8: Narrative
A9: Base Case | B9: 0.2 | C9: 0.45 | D9: =$B$5*B9+$B$6*C9 | E9: =$B$4*(1+D9) | F9: =E9-$E$9 | G9: Hyperscaler capex guidance holds. Frontier training race continues; inference scales with copilot/agent adoption and token growth.
A10: Mild Cut — Digestion | B10: 0 | C10: 0.3 | D10: =$B$5*B10+$B$6*C10 | E10: =$B$4*(1+D10) | F10: =E10-$E$9 | G10: Budget digestion after three years of hypergrowth. Training efficiency gains (distillation, MoE, longer depreciation) trim frontier spend; inference growth stays intact.
A11: Moderate Cut — ROI Reset | B11: -0.2 | C11: 0.15 | D11: =$B$5*B11+$B$6*C11 | E11: =$B$4*(1+D11) | F11: =E11-$E$9 | G11: ROI scrutiny bites. Training capex declines as fewer frontier labs compete and clusters are re-used; inference growth slows on a monetization lag.
A12: Severe Cut — AI Winter | B12: -0.45 | C12: -0.1 | D12: =$B$5*B12+$B$6*C12 | E12: =$B$4*(1+D12) | F12: =E12-$E$9 | G12: Funding pullback across labs and neoclouds. Training capex cut sharply; inference also contracts while the capacity overhang is absorbed.
A14: Design principle: capex cuts hit TRAINING budgets first (frontier ROI scrutiny, model-efficiency gains), while INFERENCE capex is defended because it maps to live usage and revenue. Training-exposed segments therefore underperform in every cut scenario.

Sheet Sub-Segment Exposures
A1: Sub-Segment Exposures & Baselines
A3: Sub-segment | B3: Representative names | C3: AI capex revenue exposure (% of sales) | D3: Training capex exposure (% of AI rev) | E3: Inference capex exposure (% of AI rev) | F3: EPS leverage (x) | G3: Baseline 26E sales growth | H3: Baseline 26E EPS growth | I3: Notes
A4: AI Accelerators (GPUs) | B4: NVIDIA, AMD | C4: 0.85 | D4: 0.55 | E4: =1-D4 | F4: 1.4 | G4: 0.35 | H4: 0.38 | I4: Data center is ~85-90% of NVDA revenue. Inference share of GPU demand rising but frontier training still sets the marginal order.
A5: Custom AI ASICs (XPUs) | B5: Broadcom (AI), Marvell, Alchip | C5: 0.45 | D5: 0.45 | E5: =1-D5 | F5: 1.5 | G5: 0.32 | H5: 0.35 | I5: TPU / Trainium / MTIA programs skew to inference serving at scale; multi-year design wins add some backlog protection.
A6: HBM & AI DRAM | B6: Micron, SK Hynix, Samsung | C6: 0.4 | D6: 0.6 | E6: =1-D6 | F6: 2 | G6: 0.28 | H6: 0.45 | I6: HBM demand attaches to accelerator units (training-heavy). High fixed-cost model gives memory the largest EPS beta.
A7: AI Networking (Switching/NICs) | B7: Arista, NVIDIA Networking, Broadcom, Cisco | C7: 0.5 | D7: 0.65 | E7: =1-D7 | F7: 1.4 | G7: 0.25 | H7: 0.28 | I7: Training clusters drive east-west fabric density (higher switch/optics content per GPU than inference pods).
A8: Optical Transceivers & Interconnect | B8: Coherent, Lumentum, Fabrinet, Credo | C8: 0.55 | D8: 0.6 | E8: =1-D8 | F8: 1.8 | G8: 0.3 | H8: 0.35 | I8: 800G/1.6T ramps tied to large training fabrics; short lead times mean fast order response when capex changes.
A9: Foundry & Advanced Packaging | B9: TSMC (CoWoS/SoIC) | C9: 0.3 | D9: 0.55 | E9: =1-D9 | F9: 1.3 | G9: 0.18 | H9: 0.2 | I9: AI accelerators ~30% of revenue and rising; CoWoS capacity is the bottleneck. Long-term agreements dampen the first-year hit.
A10: Semicap Equipment (WFE) | B10: ASML, Applied Materials, Lam, KLA | C10: 0.25 | D10: 0.55 | E10: =1-D10 | F10: 1.5 | G10: 0.12 | H10: 0.15 | I10: Second-order exposure: tool orders lag chip capex by 2-4 quarters, so cuts land with a delay but persist longer.
A11: AI Servers (ODM/OEM) | B11: Supermicro, Dell ISG, HPE, Quanta, Wiwynn | C11: 0.5 | D11: 0.55 | E11: =1-D11 | F11: 1.1 | G11: 0.22 | H11: 0.18 | I11: Low-margin integration/pass-through: big revenue swings, smaller EPS leverage than component makers.
A12: Power, Cooling & Electricals | B12: Vertiv, Eaton, Schneider, Modine | C12: 0.35 | D12: 0.5 | E12: =1-D12 | F12: 1.3 | G12: 0.18 | H12: 0.22 | I12: Facility infrastructure is largely training/inference agnostic; multi-quarter backlog cushions the first year of a cut.
A13: Data Center Colo & REITs | B13: Digital Realty, Equinix, GDS | C13: 0.25 | D13: 0.45 | E13: =1-D13 | F13: 0.9 | G13: 0.12 | H13: 0.1 | I13: Long leases limit downside to in-place revenue; the hit shows up in bookings/pre-leasing and development yields.
A14: Storage (Nearline HDD/eSSD) | B14: Seagate, Western Digital | C14: 0.2 | D14: 0.3 | E14: =1-D14 | F14: 1.6 | G14: 0.15 | H14: 0.25 | I14: Skews to inference/data-lake buildouts (retention of generated data); least training-dependent hardware segment.
A15: EDA & Semi IP | B15: Synopsys, Cadence, Arm | C15: 0.2 | D15: 0.6 | E15: =1-D15 | F15: 1.1 | G15: 0.12 | H15: 0.14 | I15: Design activity for training silicon drives bookings, but ratable revenue and backlog make near-term EPS resilient.
... A17: Hyperscalers (AI Cloud Revenue) | B17: Microsoft, Alphabet, Amazon, Meta, Oracle | C17: 0.12 | D17: 0.3 | E17: =1-D17 | F17: 0.4 | G17: 0.13 | H17: 0.14 | I17: They are the spenders: a cut lowers depreciation and lifts near-term FCF/EPS, largely offsetting slower AI cloud revenue — low net EPS beta.

Sheet Sales Growth Impact
A1: Sales Growth Impact by Scenario (2026E)
B2: Base Case | E2: Mild Cut — Digestion | H2: Moderate Cut — ROI Reset | K2: Severe Cut — AI Winter
A3: Sub-segment | B3: Segment AI-linked capex growth | C3: Δ sales growth vs Base (pp) | D3: Scenario sales growth (26E) | E3: Segment AI-linked capex growth | F3: Δ sales growth vs Base (pp) | G3: Scenario sales growth (26E) | H3: Segment AI-linked capex growth | I3: Δ sales growth vs Base (pp) | J3: Scenario sales growth (26E) | K3: Segment AI-linked capex growth | L3: Δ sales growth vs Base (pp) | M3: Scenario sales growth (26E)
A4: ='Sub-Segment Exposures'!A4 | B4: ='Sub-Segment Exposures'!$D4*'Scenario Assumptions'!B$9+'Sub-Segment Exposures'!$E4*'Scenario Assumptions'!C$9 | C4: ='Sub-Segment Exposures'!$C4*(B4-$B4) | D4: ='Sub-Segment Exposures'!$G4+C4 | E4: ='Sub-Segment Exposures'!$D4*'Scenario Assumptions'!B$10+'Sub-Segment Exposures'!$E4*'Scenario Assumptions'!C$10 | F4: ='Sub-Segment Exposures'!$C4*(E4-$B4) | G4: ='Sub-Segment Exposures'!$G4+F4 | H4: ='Sub-Segment Exposures'!$D4*'Scenario Assumptions'!B$11+'Sub-Segment Exposures'!$E4*'Scenario Assumptions'!C$11 | I4: ='Sub-Segment Exposures'!$C4*(H4-$B4) | J4: ='Sub-Segment Exposures'!$G4+I4 | K4: ='Sub-Segment Exposures'!$D4*'Scenario Assumptions'!B$12+'Sub-Segment Exposures'!$E4*'Scenario Assumptions'!C$12 | L4: ='Sub-Segment Exposures'!$C4*(K4-$B4) | M4: ='Sub-Segment Exposures'!$G4+L4
A5: ='Sub-Segment Exposures'!A5 | B5: ='Sub-Segment Exposures'!$D5*'Scenario Assumptions'!B$9+'Sub-Segment Exposures'!$E5*'Scenario Assumptions'!C$9 | C5: ='Sub-Segment Exposures'!$C5*(B5-$B5) | D5: ='Sub-Segment Exposures'!$G5+C5 | E5: ='Sub-Segment Exposures'!$D5*'Scenario Assumptions'!B$10+'Sub-Segment Exposures'!$E5*'Scenario Assumptions'!C$10 | F5: ='Sub-Segment Exposures'!$C5*(E5-$B5) | G5: ='Sub-Segment Exposures'!$G5+F5 | H5: ='Sub-Segment Exposures'!$D5*'Scenario Assumptions'!B$11+'Sub-Segment Exposures'!$E5*'Scenario Assumptions'!C$11 | I5: ='Sub-Segment Exposures'!$C5*(H5-$B5) | J5: ='Sub-Segment Exposures'!$G5+I5 | K5: ='Sub-Segment Exposures'!$D5*'Scenario Assumptions'!B$12+'Sub-Segment Exposures'!$E5*'Scenario Assumptions'!C$12 | L5: ='Sub-Segment Exposures'!$C5*(K5-$B5) | M5: ='Sub-Segment Exposures'!$G5+L5
A6: ='Sub-Segment Exposures'!A6 | B6: ='Sub-Segment Exposures'!$D6*'Scenario Assumptions'!B$9+'Sub-Segment Exposures'!$E6*'Scenario Assumptions'!C$9 | C6: ='Sub-Segment Exposures'!$C6*(B6-$B6) | D6: ='Sub-Segment Exposures'!$G6+C6 | E6: ='Sub-Segment Exposures'!$D6*'Scenario Assumptions'!B$10+'Sub-Segment Exposures'!$E6*'Scenario Assumptions'!C$10 | F6: ='Sub-Segment Exposures'!$C6*(E6-$B6) | G6: ='Sub-Segment Exposures'!$G6+F6 | H6: ='Sub-Segment Exposures'!$D6*'Scenario Assumptions'!B$11+'Sub-Segment Exposures'!$E6*'Scenario Assumptions'!C$11 | I6: ='Sub-Segment Exposures'!$C6*(H6-$B6) | J6: ='Sub-Segment Exposures'!$G6+I6 | K6: ='Sub-Segment Exposures'!$D6*'Scenario Assumptions'!B$12+'Sub-Segment Exposures'!$E6*'Scenario Assumptions'!C$12 | L6: ='Sub-Segment Exposures'!$C6*(K6-$B6) | M6: ='Sub-Segment Exposures'!$G6+L6
A7: ='Sub-Segment Exposures'!A7 | B7: ='Sub-Segment Exposures'!$D7*'Scenario Assumptions'!B$9+'Sub-Segment Exposures'!$E7*'Scenario Assumptions'!C$9 | C7: ='Sub-Segment Exposures'!$C7*(B7-$B7) | D7: ='Sub-Segment Exposures'!$G7+C7 | E7: ='Sub-Segment Exposures'!$D7*'Scenario Assumptions'!B$10+'Sub-Segment Exposures'!$E7*'Scenario Assumptions'!C$10 | F7: ='Sub-Segment Exposures'!$C7*(E7-$B7) | G7: ='Sub-Segment Exposures'!$G7+F7 | H7: ='Sub-Segment Exposures'!$D7*'Scenario Assumptions'!B$11+'Sub-Segment Exposures'!$E7*'Scenario Assumptions'!C$11 | I7: ='Sub-Segment Exposures'!$C7*(H7-$B7) | J7: ='Sub-Segment Exposures'!$G7+I7 | K7: ='Sub-Segment Exposures'!$D7*'Scenario Assumptions'!B$12+'Sub-Segment Exposures'!$E7*'Scenario Assumptions'!C$12 | L7: ='Sub-Segment Exposures'!$C7*(K7-$B7) | M7: ='Sub-Segment Exposures'!$G7+L7
A8: ='Sub-Segment Exposures'!A8 | B8: ='Sub-Segment Exposures'!$D8*'Scenario Assumptions'!B$9+'Sub-Segment Exposures'!$E8*'Scenario Assumptions'!C$9 | C8: ='Sub-Segment Exposures'!$C8*(B8-$B8) | D8: ='Sub-Segment Exposures'!$G8+C8 | E8: ='Sub-Segment Exposures'!$D8*'Scenario Assumptions'!B$10+'Sub-Segment Exposures'!$E8*'Scenario Assumptions'!C$10 | F8: ='Sub-Segment Exposures'!$C8*(E8-$B8) | G8: ='Sub-Segment Exposures'!$G8+F8 | H8: ='Sub-Segment Exposures'!$D8*'Scenario Assumptions'!B$11+'Sub-Segment Exposures'!$E8*'Scenario Assumptions'!C$11 | I8: ='Sub-Segment Exposures'!$C8*(H8-$B8) | J8: ='Sub-Segment Exposures'!$G8+I8 | K8: ='Sub-Segment Exposures'!$D8*'Scenario Assumptions'!B$12+'Sub-Segment Exposures'!$E8*'Scenario Assumptions'!C$12 | L8: ='Sub-Segment Exposures'!$C8*(K8-$B8) | M8: ='Sub-Segment Exposures'!$G8+L8
A9: ='Sub-Segment Exposures'!A9 | B9: ='Sub-Segment Exposures'!$D9*'Scenario Assumptions'!B$9+'Sub-Segment Exposures'!$E9*'Scenario Assumptions'!C$9 | C9: ='Sub-Segment Exposures'!$C9*(B9-$B9) | D9: ='Sub-Segment Exposures'!$G9+C9 | E9: ='Sub-Segment Exposures'!$D9*'Scenario Assumptions'!B$10+'Sub-Segment Exposures'!$E9*'Scenario Assumptions'!C$10 | F9: ='Sub-Segment Exposures'!$C9*(E9-$B9) | G9: ='Sub-Segment Exposures'!$G9+F9 | H9: ='Sub-Segment Exposures'!$D9*'Scenario Assumptions'!B$11+'Sub-Segment Exposures'!$E9*'Scenario Assumptions'!C$11 | I9: ='Sub-Segment Exposures'!$C9*(H9-$B9) | J9: ='Sub-Segment Exposures'!$G9+I9 | K9: ='Sub-Segment Exposures'!$D9*'Scenario Assumptions'!B$12+'Sub-Segment Exposures'!$E9*'Scenario Assumptions'!C$12 | L9: ='Sub-Segment Exposures'!$C9*(K9-$B9) | M9: ='Sub-Segment Exposures'!$G9+L9
A10: ='Sub-Segment Exposures'!A10 | B10: ='Sub-Segment Exposures'!$D10*'Scenario Assumptions'!B$9+'Sub-Segment Exposures'!$E10*'Scenario Assumptions'!C$9 | C10: ='Sub-Segment Exposures'!$C10*(B10-$B10) | D10: ='Sub-Segment Exposures'!$G10+C10 | E10: ='Sub-Segment Exposures'!$D10*'Scenario Assumptions'!B$10+'Sub-Segment Exposures'!$E10*'Scenario Assumptions'!C$10 | F10: ='Sub-Segment Exposures'!$C10*(E10-$B10) | G10: ='Sub-Segment Exposures'!$G10+F10 | H10: ='Sub-Segment Exposures'!$D10*'Scenario Assumptions'!B$11+'Sub-Segment Exposures'!$E10*'Scenario Assumptions'!C$11 | I10: ='Sub-Segment Exposures'!$C10*(H10-$B10) | J10: ='Sub-Segment Exposures'!$G10+I10 | K10: ='Sub-Segment Exposures'!$D10*'Scenario Assumptions'!B$12+'Sub-Segment Exposures'!$E10*'Scenario Assumptions'!C$12 | L10: ='Sub-Segment Exposures'!$C10*(K10-$B10) | M10: ='Sub-Segment Exposures'!$G10+L10
A11: ='Sub-Segment Exposures'!A11 | B11: ='Sub-Segment Exposures'!$D11*'Scenario Assumptions'!B$9+'Sub-Segment Exposures'!$E11*'Scenario Assumptions'!C$9 | C11: ='Sub-Segment Exposures'!$C11*(B11-$B11) | D11: ='Sub-Segment Exposures'!$G11+C11 | E11: ='Sub-Segment Exposures'!$D11*'Scenario Assumptions'!B$10+'Sub-Segment Exposures'!$E11*'Scenario Assumptions'!C$10 | F11: ='Sub-Segment Exposures'!$C11*(E11-$B11) | G11: ='Sub-Segment Exposures'!$G11+F11 | H11: ='Sub-Segment Exposures'!$D11*'Scenario Assumptions'!B$11+'Sub-Segment Exposures'!$E11*'Scenario Assumptions'!C$11 | I11: ='Sub-Segment Exposures'!$C11*(H11-$B11) | J11: ='Sub-Segment Exposures'!$G11+I11 | K11: ='Sub-Segment Exposures'!$D11*'Scenario Assumptions'!B$12+'Sub-Segment Exposures'!$E11*'Scenario Assumptions'!C$12 | L11: ='Sub-Segment Exposures'!$C11*(K11-$B11) | M11: ='Sub-Segment Exposures'!$G11+L11
A12: ='Sub-Segment Exposures'!A12 | B12: ='Sub-Segment Exposures'!$D12*'Scenario Assumptions'!B$9+'Sub-Segment Exposures'!$E12*'Scenario Assumptions'!C$9 | C12: ='Sub-Segment Exposures'!$C12*(B12-$B12) | D12: ='Sub-Segment Exposures'!$G12+C12 | E12: ='Sub-Segment Exposures'!$D12*'Scenario Assumptions'!B$10+'Sub-Segment Exposures'!$E12*'Scenario Assumptions'!C$10 | F12: ='Sub-Segment Exposures'!$C12*(E12-$B12) | G12: ='Sub-Segment Exposures'!$G12+F12 | H12: ='Sub-Segment Exposures'!$D12*'Scenario Assumptions'!B$11+'Sub-Segment Exposures'!$E12*'Scenario Assumptions'!C$11 | I12: ='Sub-Segment Exposures'!$C12*(H12-$B12) | J12: ='Sub-Segment Exposures'!$G12+I12 | K12: ='Sub-Segment Exposures'!$D12*'Scenario Assumptions'!B$12+'Sub-Segment Exposures'!$E12*'Scenario Assumptions'!C$12 | L12: ='Sub-Segment Exposures'!$C12*(K12-$B12) | M12: ='Sub-Segment Exposures'!$G12+L12
A13: ='Sub-Segment Exposures'!A13 | B13: ='Sub-Segment Exposures'!$D13*'Scenario Assumptions'!B$9+'Sub-Segment Exposures'!$E13*'Scenario Assumptions'!C$9 | C13: ='Sub-Segment Exposures'!$C13*(B13-$B13) | D13: ='Sub-Segment Exposures'!$G13+C13 | E13: ='Sub-Segment Exposures'!$D13*'Scenario Assumptions'!B$10+'Sub-Segment Exposures'!$E13*'Scenario Assumptions'!C$10 | F13: ='Sub-Segment Exposures'!$C13*(E13-$B13) | G13: ='Sub-Segment Exposures'!$G13+F13 | H13: ='Sub-Segment Exposures'!$D13*'Scenario Assumptions'!B$11+'Sub-Segment Exposures'!$E13*'Scenario Assumptions'!C$11 | I13: ='Sub-Segment Exposures'!$C13*(H13-$B13) | J13: ='Sub-Segment Exposures'!$G13+I13 | K13: ='Sub-Segment Exposures'!$D13*'Scenario Assumptions'!B$12+'Sub-Segment Exposures'!$E13*'Scenario Assumptions'!C$12 | L13: ='Sub-Segment Exposures'!$C13*(K13-$B13) | M13: ='Sub-Segment Exposures'!$G13+L13
A14: ='Sub-Segment Exposures'!A14 | B14: ='Sub-Segment Exposures'!$D14*'Scenario Assumptions'!B$9+'Sub-Segment Exposures'!$E14*'Scenario Assumptions'!C$9 | C14: ='Sub-Segment Exposures'!$C14*(B14-$B14) | D14: ='Sub-Segment Exposures'!$G14+C14 | E14: ='Sub-Segment Exposures'!$D14*'Scenario Assumptions'!B$10+'Sub-Segment Exposures'!$E14*'Scenario Assumptions'!C$10 | F14: ='Sub-Segment Exposures'!$C14*(E14-$B14) | G14: ='Sub-Segment Exposures'!$G14+F14 | H14: ='Sub-Segment Exposures'!$D14*'Scenario Assumptions'!B$11+'Sub-Segment Exposures'!$E14*'Scenario Assumptions'!C$11 | I14: ='Sub-Segment Exposures'!$C14*(H14-$B14) | J14: ='Sub-Segment Exposures'!$G14+I14 | K14: ='Sub-Segment Exposures'!$D14*'Scenario Assumptions'!B$12+'Sub-Segment Exposures'!$E14*'Scenario Assumptions'!C$12 | L14: ='Sub-Segment Exposures'!$C14*(K14-$B14) | M14: ='Sub-Segment Exposures'!$G14+L14
A15: ='Sub-Segment Exposures'!A15 | B15: ='Sub-Segment Exposures'!$D15*'Scenario Assumptions'!B$9+'Sub-Segment Exposures'!$E15*'Scenario Assumptions'!C$9 | C15: ='Sub-Segment Exposures'!$C15*(B15-$B15) | D15: ='Sub-Segment Exposures'!$G15+C15 | E15: ='Sub-Segment Exposures'!$D15*'Scenario Assumptions'!B$10+'Sub-Segment Exposures'!$E15*'Scenario Assumptions'!C$10 | F15: ='Sub-Segment Exposures'!$C15*(E15-$B15) | G15: ='Sub-Segment Exposures'!$G15+F15 | H15: ='Sub-Segment Exposures'!$D15*'Scenario Assumptions'!B$11+'Sub-Segment Exposures'!$E15*'Scenario Assumptions'!C$11 | I15: ='Sub-Segment Exposures'!$C15*(H15-$B15) | J15: ='Sub-Segment Exposures'!$G15+I15 | K15: ='Sub-Segment Exposures'!$D15*'Scenario Assumptions'!B$12+'Sub-Segment Exposures'!$E15*'Scenario Assumptions'!C$12 | L15: ='Sub-Segment Exposures'!$C15*(K15-$B15) | M15: ='Sub-Segment Exposures'!$G15+L15
... A17: ='Sub-Segment Exposures'!A17 | B17: ='Sub-Segment Exposures'!$D17*'Scenario Assumptions'!B$9+'Sub-Segment Exposures'!$E17*'Scenario Assumptions'!C$9 | C17: ='Sub-Segment Exposures'!$C17*(B17-$B17) | D17: ='Sub-Segment Exposures'!$G17+C17 | E17: ='Sub-Segment Exposures'!$D17*'Scenario Assumptions'!B$10+'Sub-Segment Exposures'!$E17*'Scenario Assumptions'!C$10 | F17: ='Sub-Segment Exposures'!$C17*(E17-$B17) | G17: ='Sub-Segment Exposures'!$G17+F17 | H17: ='Sub-Segment Exposures'!$D17*'Scenario Assumptions'!B$11+'Sub-Segment Exposures'!$E17*'Scenario Assumptions'!C$11 | I17: ='Sub-Segment Exposures'!$C17*(H17-$B17) | J17: ='Sub-Segment Exposures'!$G17+I17 | K17: ='Sub-Segment Exposures'!$D17*'Scenario Assumptions'!B$12+'Sub-Segment Exposures'!$E17*'Scenario Assumptions'!C$12 | L17: ='Sub-Segment Exposures'!$C17*(K17-$B17) | M17: ='Sub-Segment Exposures'!$G17+L17

Sheet EPS Growth Impact
A1: EPS Growth Impact by Scenario (2026E)
B2: Base Case | D2: Mild Cut — Digestion | F2: Moderate Cut — ROI Reset | H2: Severe Cut — AI Winter
A3: Sub-segment | B3: Δ EPS growth vs Base (pp) | C3: Scenario EPS growth (26E) | D3: Δ EPS growth vs Base (pp) | E3: Scenario EPS growth (26E) | F3: Δ EPS growth vs Base (pp) | G3: Scenario EPS growth (26E) | H3: Δ EPS growth vs Base (pp) | I3: Scenario EPS growth (26E)
A4: ='Sub-Segment Exposures'!A4 | B4: ='Sub-Segment Exposures'!$F4*'Sales Growth Impact'!C4 | C4: ='Sub-Segment Exposures'!$H4+B4 | D4: ='Sub-Segment Exposures'!$F4*'Sales Growth Impact'!F4 | E4: ='Sub-Segment Exposures'!$H4+D4 | F4: ='Sub-Segment Exposures'!$F4*'Sales Growth Impact'!I4 | G4: ='Sub-Segment Exposures'!$H4+F4 | H4: ='Sub-Segment Exposures'!$F4*'Sales Growth Impact'!L4 | I4: ='Sub-Segment Exposures'!$H4+H4
A5: ='Sub-Segment Exposures'!A5 | B5: ='Sub-Segment Exposures'!$F5*'Sales Growth Impact'!C5 | C5: ='Sub-Segment Exposures'!$H5+B5 | D5: ='Sub-Segment Exposures'!$F5*'Sales Growth Impact'!F5 | E5: ='Sub-Segment Exposures'!$H5+D5 | F5: ='Sub-Segment Exposures'!$F5*'Sales Growth Impact'!I5 | G5: ='Sub-Segment Exposures'!$H5+F5 | H5: ='Sub-Segment Exposures'!$F5*'Sales Growth Impact'!L5 | I5: ='Sub-Segment Exposures'!$H5+H5
A6: ='Sub-Segment Exposures'!A6 | B6: ='Sub-Segment Exposures'!$F6*'Sales Growth Impact'!C6 | C6: ='Sub-Segment Exposures'!$H6+B6 | D6: ='Sub-Segment Exposures'!$F6*'Sales Growth Impact'!F6 | E6: ='Sub-Segment Exposures'!$H6+D6 | F6: ='Sub-Segment Exposures'!$F6*'Sales Growth Impact'!I6 | G6: ='Sub-Segment Exposures'!$H6+F6 | H6: ='Sub-Segment Exposures'!$F6*'Sales Growth Impact'!L6 | I6: ='Sub-Segment Exposures'!$H6+H6
A7: ='Sub-Segment Exposures'!A7 | B7: ='Sub-Segment Exposures'!$F7*'Sales Growth Impact'!C7 | C7: ='Sub-Segment Exposures'!$H7+B7 | D7: ='Sub-Segment Exposures'!$F7*'Sales Growth Impact'!F7 | E7: ='Sub-Segment Exposures'!$H7+D7 | F7: ='Sub-Segment Exposures'!$F7*'Sales Growth Impact'!I7 | G7: ='Sub-Segment Exposures'!$H7+F7 | H7: ='Sub-Segment Exposures'!$F7*'Sales Growth Impact'!L7 | I7: ='Sub-Segment Exposures'!$H7+H7
A8: ='Sub-Segment Exposures'!A8 | B8: ='Sub-Segment Exposures'!$F8*'Sales Growth Impact'!C8 | C8: ='Sub-Segment Exposures'!$H8+B8 | D8: ='Sub-Segment Exposures'!$F8*'Sales Growth Impact'!F8 | E8: ='Sub-Segment Exposures'!$H8+D8 | F8: ='Sub-Segment Exposures'!$F8*'Sales Growth Impact'!I8 | G8: ='Sub-Segment Exposures'!$H8+F8 | H8: ='Sub-Segment Exposures'!$F8*'Sales Growth Impact'!L8 | I8: ='Sub-Segment Exposures'!$H8+H8
A9: ='Sub-Segment Exposures'!A9 | B9: ='Sub-Segment Exposures'!$F9*'Sales Growth Impact'!C9 | C9: ='Sub-Segment Exposures'!$H9+B9 | D9: ='Sub-Segment Exposures'!$F9*'Sales Growth Impact'!F9 | E9: ='Sub-Segment Exposures'!$H9+D9 | F9: ='Sub-Segment Exposures'!$F9*'Sales Growth Impact'!I9 | G9: ='Sub-Segment Exposures'!$H9+F9 | H9: ='Sub-Segment Exposures'!$F9*'Sales Growth Impact'!L9 | I9: ='Sub-Segment Exposures'!$H9+H9
A10: ='Sub-Segment Exposures'!A10 | B10: ='Sub-Segment Exposures'!$F10*'Sales Growth Impact'!C10 | C10: ='Sub-Segment Exposures'!$H10+B10 | D10: ='Sub-Segment Exposures'!$F10*'Sales Growth Impact'!F10 | E10: ='Sub-Segment Exposures'!$H10+D10 | F10: ='Sub-Segment Exposures'!$F10*'Sales Growth Impact'!I10 | G10: ='Sub-Segment Exposures'!$H10+F10 | H10: ='Sub-Segment Exposures'!$F10*'Sales Growth Impact'!L10 | I10: ='Sub-Segment Exposures'!$H10+H10
A11: ='Sub-Segment Exposures'!A11 | B11: ='Sub-Segment Exposures'!$F11*'Sales Growth Impact'!C11 | C11: ='Sub-Segment Exposures'!$H11+B11 | D11: ='Sub-Segment Exposures'!$F11*'Sales Growth Impact'!F11 | E11: ='Sub-Segment Exposures'!$H11+D11 | F11: ='Sub-Segment Exposures'!$F11*'Sales Growth Impact'!I11 | G11: ='Sub-Segment Exposures'!$H11+F11 | H11: ='Sub-Segment Exposures'!$F11*'Sales Growth Impact'!L11 | I11: ='Sub-Segment Exposures'!$H11+H11
A12: ='Sub-Segment Exposures'!A12 | B12: ='Sub-Segment Exposures'!$F12*'Sales Growth Impact'!C12 | C12: ='Sub-Segment Exposures'!$H12+B12 | D12: ='Sub-Segment Exposures'!$F12*'Sales Growth Impact'!F12 | E12: ='Sub-Segment Exposures'!$H12+D12 | F12: ='Sub-Segment Exposures'!$F12*'Sales Growth Impact'!I12 | G12: ='Sub-Segment Exposures'!$H12+F12 | H12: ='Sub-Segment Exposures'!$F12*'Sales Growth Impact'!L12 | I12: ='Sub-Segment Exposures'!$H12+H12
A13: ='Sub-Segment Exposures'!A13 | B13: ='Sub-Segment Exposures'!$F13*'Sales Growth Impact'!C13 | C13: ='Sub-Segment Exposures'!$H13+B13 | D13: ='Sub-Segment Exposures'!$F13*'Sales Growth Impact'!F13 | E13: ='Sub-Segment Exposures'!$H13+D13 | F13: ='Sub-Segment Exposures'!$F13*'Sales Growth Impact'!I13 | G13: ='Sub-Segment Exposures'!$H13+F13 | H13: ='Sub-Segment Exposures'!$F13*'Sales Growth Impact'!L13 | I13: ='Sub-Segment Exposures'!$H13+H13
A14: ='Sub-Segment Exposures'!A14 | B14: ='Sub-Segment Exposures'!$F14*'Sales Growth Impact'!C14 | C14: ='Sub-Segment Exposures'!$H14+B14 | D14: ='Sub-Segment Exposures'!$F14*'Sales Growth Impact'!F14 | E14: ='Sub-Segment Exposures'!$H14+D14 | F14: ='Sub-Segment Exposures'!$F14*'Sales Growth Impact'!I14 | G14: ='Sub-Segment Exposures'!$H14+F14 | H14: ='Sub-Segment Exposures'!$F14*'Sales Growth Impact'!L14 | I14: ='Sub-Segment Exposures'!$H14+H14
A15: ='Sub-Segment Exposures'!A15 | B15: ='Sub-Segment Exposures'!$F15*'Sales Growth Impact'!C15 | C15: ='Sub-Segment Exposures'!$H15+B15 | D15: ='Sub-Segment Exposures'!$F15*'Sales Growth Impact'!F15 | E15: ='Sub-Segment Exposures'!$H15+D15 | F15: ='Sub-Segment Exposures'!$F15*'Sales Growth Impact'!I15 | G15: ='Sub-Segment Exposures'!$H15+F15 | H15: ='Sub-Segment Exposures'!$F15*'Sales Growth Impact'!L15 | I15: ='Sub-Segment Exposures'!$H15+H15
... A17: ='Sub-Segment Exposures'!A17 | B17: ='Sub-Segment Exposures'!$F17*'Sales Growth Impact'!C17 | C17: ='Sub-Segment Exposures'!$H17+B17 | D17: ='Sub-Segment Exposures'!$F17*'Sales Growth Impact'!F17 | E17: ='Sub-Segment Exposures'!$H17+D17 | F17: ='Sub-Segment Exposures'!$F17*'Sales Growth Impact'!I17 | G17: ='Sub-Segment Exposures'!$H17+F17 | H17: ='Sub-Segment Exposures'!$F17*'Sales Growth Impact'!L17 | I17: ='Sub-Segment Exposures'!$H17+H17

Sheet Summary Matrix
A1: Summary — 2026E Growth by Scenario
A3: 2026E revenue growth by scenario
A4: Sub-segment | B4: Base Case | C4: Mild Cut — Digestion | D4: Moderate Cut — ROI Reset | E4: Severe Cut — AI Winter
A5: ='Sub-Segment Exposures'!A4 | B5: ='Sales Growth Impact'!D4 | C5: ='Sales Growth Impact'!G4 | D5: ='Sales Growth Impact'!J4 | E5: ='Sales Growth Impact'!M4
A6: ='Sub-Segment Exposures'!A5 | B6: ='Sales Growth Impact'!D5 | C6: ='Sales Growth Impact'!G5 | D6: ='Sales Growth Impact'!J5 | E6: ='Sales Growth Impact'!M5
A7: ='Sub-Segment Exposures'!A6 | B7: ='Sales Growth Impact'!D6 | C7: ='Sales Growth Impact'!G6 | D7: ='Sales Growth Impact'!J6 | E7: ='Sales Growth Impact'!M6
A8: ='Sub-Segment Exposures'!A7 | B8: ='Sales Growth Impact'!D7 | C8: ='Sales Growth Impact'!G7 | D8: ='Sales Growth Impact'!J7 | E8: ='Sales Growth Impact'!M7
A9: ='Sub-Segment Exposures'!A8 | B9: ='Sales Growth Impact'!D8 | C9: ='Sales Growth Impact'!G8 | D9: ='Sales Growth Impact'!J8 | E9: ='Sales Growth Impact'!M8
A10: ='Sub-Segment Exposures'!A9 | B10: ='Sales Growth Impact'!D9 | C10: ='Sales Growth Impact'!G9 | D10: ='Sales Growth Impact'!J9 | E10: ='Sales Growth Impact'!M9
A11: ='Sub-Segment Exposures'!A10 | B11: ='Sales Growth Impact'!D10 | C11: ='Sales Growth Impact'!G10 | D11: ='Sales Growth Impact'!J10 | E11: ='Sales Growth Impact'!M10
A12: ='Sub-Segment Exposures'!A11 | B12: ='Sales Growth Impact'!D11 | C12: ='Sales Growth Impact'!G11 | D12: ='Sales Growth Impact'!J11 | E12: ='Sales Growth Impact'!M11
A13: ='Sub-Segment Exposures'!A12 | B13: ='Sales Growth Impact'!D12 | C13: ='Sales Growth Impact'!G12 | D13: ='Sales Growth Impact'!J12 | E13: ='Sales Growth Impact'!M12
A14: ='Sub-Segment Exposures'!A13 | B14: ='Sales Growth Impact'!D13 | C14: ='Sales Growth Impact'!G13 | D14: ='Sales Growth Impact'!J13 | E14: ='Sales Growth Impact'!M13
A15: ='Sub-Segment Exposures'!A14 | B15: ='Sales Growth Impact'!D14 | C15: ='Sales Growth Impact'!G14 | D15: ='Sales Growth Impact'!J14 | E15: ='Sales Growth Impact'!M14
A16: ='Sub-Segment Exposures'!A15 | B16: ='Sales Growth Impact'!D15 | C16: ='Sales Growth Impact'!G15 | D16: ='Sales Growth Impact'!J15 | E16: ='Sales Growth Impact'!M15
... A18: ='Sub-Segment Exposures'!A17 | B18: ='Sales Growth Impact'!D17 | C18: ='Sales Growth Impact'!G17 | D18: ='Sales Growth Impact'!J17 | E18: ='Sales Growth Impact'!M17
A21: 2026E EPS growth by scenario
A22: Sub-segment | B22: Base Case | C22: Mild Cut — Digestion | D22: Moderate Cut — ROI Reset | E22: Severe Cut — AI Winter
A23: ='Sub-Segment Exposures'!A4 | B23: ='EPS Growth Impact'!C4 | C23: ='EPS Growth Impact'!E4 | D23: ='EPS Growth Impact'!G4 | E23: ='EPS Growth Impact'!I4
A24: ='Sub-Segment Exposures'!A5 | B24: ='EPS Growth Impact'!C5 | C24: ='EPS Growth Impact'!E5 | D24: ='EPS Growth Impact'!G5 | E24: ='EPS Growth Impact'!I5
A25: ='Sub-Segment Exposures'!A6 | B25: ='EPS Growth Impact'!C6 | C25: ='EPS Growth Impact'!E6 | D25: ='EPS Growth Impact'!G6 | E25: ='EPS Growth Impact'!I6
A26: ='Sub-Segment Exposures'!A7 | B26: ='EPS Growth Impact'!C7 | C26: ='EPS Growth Impact'!E7 | D26: ='EPS Growth Impact'!G7 | E26: ='EPS Growth Impact'!I7
A27: ='Sub-Segment Exposures'!A8 | B27: ='EPS Growth Impact'!C8 | C27: ='EPS Growth Impact'!E8 | D27: ='EPS Growth Impact'!G8 | E27: ='EPS Growth Impact'!I8
A28: ='Sub-Segment Exposures'!A9 | B28: ='EPS Growth Impact'!C9 | C28: ='EPS Growth Impact'!E9 | D28: ='EPS Growth Impact'!G9 | E28: ='EPS Growth Impact'!I9
A29: ='Sub-Segment Exposures'!A10 | B29: ='EPS Growth Impact'!C10 | C29: ='EPS Growth Impact'!E10 | D29: ='EPS Growth Impact'!G10 | E29: ='EPS Growth Impact'!I10
A30: ='Sub-Segment Exposures'!A11 | B30: ='EPS Growth Impact'!C11 | C30: ='EPS Growth Impact'!E11 | D30: ='EPS Growth Impact'!G11 | E30: ='EPS Growth Impact'!I11
A31: ='Sub-Segment Exposures'!A12 | B31: ='EPS Growth Impact'!C12 | C31: ='EPS Growth Impact'!E12 | D31: ='EPS Growth Impact'!G12 | E31: ='EPS Growth Impact'!I12
A32: ='Sub-Segment Exposures'!A13 | B32: ='EPS Growth Impact'!C13 | C32: ='EPS Growth Impact'!E13 | D32: ='EPS Growth Impact'!G13 | E32: ='EPS Growth Impact'!I13
A33: ='Sub-Segment Exposures'!A14 | B33: ='EPS Growth Impact'!C14 | C33: ='EPS Growth Impact'!E14 | D33: ='EPS Growth Impact'!G14 | E33: ='EPS Growth Impact'!I14
A34: ='Sub-Segment Exposures'!A15 | B34: ='EPS Growth Impact'!C15 | C34: ='EPS Growth Impact'!E15 | D34: ='EPS Growth Impact'!G15 | E34: ='EPS Growth Impact'!I15
... A36: ='Sub-Segment Exposures'!A17 | B36: ='EPS Growth Impact'!C17 | C36: ='EPS Growth Impact'!E17 | D36: ='EPS Growth Impact'!G17 | E36: ='EPS Growth Impact'!I17
