Workbook

Sheet Read Me
A1: Agentic AI Offerings: Revenue & Token Usage Across Sectors
A2: Compiled: August 23, 2026. All figures are annualized USD unless noted.
A4: SHEETS
A5: Offerings - one row per agentic offering: revenue, growth trajectory, valuation, pricing model, scale and token metrics, sources.
A6: Sector Aggregates - revenue summed by sector (live SUMIFS over the Offerings sheet; memo rows excluded).
A7: Token Usage - platform- and ecosystem-level token throughput metrics relevant to agentic workloads.
A8: Sources - numbered source list; the 'Sources' column in other sheets references these numbers.
A10: DEFINITIONS
A11: ARR - annual recurring revenue as disclosed or estimated; in AI, often used interchangeably with annualized run-rate.
A12: Annualized run-rate - most recent period revenue x 12 (or x4); volatile for fast-growing companies.
A13: Tracked ARR - third-party estimate (e.g., TickerTrends) anchored to a company disclosure and extrapolated from usage signals.
A14: ACV - annual contract value (ServiceNow reports its AI portfolio this way).
... A26: 6. Run-rates in this market can double in a quarter; treat point-in-time numbers accordingly.

Sheet Offerings
A1: Sector | B1: Company | C1: Offering | D1: What it does | E1: Revenue basis | F1: Annualized revenue ($M) | G1: Revenue as-of | H1: Growth trajectory | I1: Valuation ($B) | J1: Valuation note | K1: Pricing model | L1: Scale / adoption metrics | M1: Token / usage metrics | N1: Confidence | O1: In sector aggregate? | P1: Sources (#)
A2: Coding & software development | B2: Anthropic | C2: Claude Code | D2: Agentic CLI coding agent: plans, edits, tests and iterates across a codebase | E2: Tracked ARR (3rd-party estimate) | F2: 15120 | G2: Aug 10, 2026 | H2: $1B Nov 2025 -> $2.5B Feb 2026 (company-disclosed, Series G) -> ~$8B May 2026 (Sacra) -> $15.1B Aug 2026 (TickerTrends) | I2: 380 | J2: Anthropic post-money, Feb 2026 Series G ($30B raise) | K2: Subscription (Pro/Max) + API usage | L2: ~21.9% of Anthropic tracked ARR; avg developer ~20 hrs/week in tool; ~4% of global GitHub commits (SemiAnalysis) | M2: 6.5-9.6T tokens/month routed via OpenRouter alone (app rankings snapshots) | N2: Tracked estimate (disclosed $2.5B Feb 2026) | O2: Yes | P2: 3, 4, 5, 27, 28
A3: Coding & software development | B3: OpenAI | C3: Codex | D3: Agentic coding agent (CLI/IDE/cloud) for autonomous software tasks | E3: Tracked ARR (3rd-party estimate) | F3: 8830 | G3: Aug 10, 2026 | H3: Near zero start of 2026 -> $5.9B Jul 6, 2026 -> $8.8B Aug 10, 2026; ~44% of OpenAI enterprise ARR (central case) | J3: Part of OpenAI (IPO planned) | K3: Bundled with ChatGPT plans + API usage | L3: 5M+ weekly active users (Feb 2026); 20M WAU across OpenAI coding/work products (Aug 2026) | M3: ~688B tokens/month via OpenRouter (87% on OpenAI models) | N3: Tracked estimate | O3: Yes | P3: 3, 30, 32, 28
A4: Coding & software development | B4: Anysphere (SpaceX acq. pending) | C4: Cursor | D4: AI-native code editor with agentic coding workflows | E4: ARR | F4: 4000 | G4: May-Jun 2026 | H4: $100M Jan 2025 -> $500M Jun 2025 -> $1B Nov 2025 -> $2B Feb 2026 (Bloomberg) -> $4B May/Jun 2026 (Sacra) | I4: 60 | J4: SpaceX all-stock acquisition agreed Jun 16, 2026 (close Q3 2026); last private mark $29.3B Series D Nov 2025 | K4: $20-$200/mo subscriptions + enterprise seats; ~20% margin on model API costs; ~65% enterprise (~$2.6B) | L4: 1M+ paying customers; used in 64% of Fortune 500 | N4: Company-disclosed to $2B; analyst (Sacra) at $4B | O4: Yes | P4: 1, 2, 40
A5: Coding & software development | B5: Microsoft (GitHub) | C5: GitHub Copilot | D5: AI pair programmer evolving into agentic coding (agent mode, usage-based billing) | E5: ARR (analyst estimate) | F5: 1000 | G5: Q2 FY26 (Jan 2026) | H5: Estimate range $900M-$1.1B (Axis); FT floor 'at least $550M'; Copilot revenue +60% QoQ in Q4 FY26 after usage-based billing launch | J5: Microsoft subsidiary (not separately valued) | K5: $10-$39/user/mo tiers + usage-based billing (introduced Q4 FY26) | L5: 4.7M paid subscribers (Jan 2026, +75% YoY); 50M users (Jul 2026); 90% of Fortune 100 | N5: Analyst estimate (Microsoft does not disclose) | O5: Yes | P5: 7, 36, 37
A6: Coding & software development | B6: Replit | C6: Replit Agent | D6: Cloud IDE with autonomous app-building agent | E6: ARR (analyst estimate) | F6: 525 | G6: Mid-2026 | H6: Targeting $1B ARR by end of 2026 | I6: 9 | J6: 2026 private round | K6: Effort-based agent pricing (usage) + subscriptions | N6: Analyst estimate | O6: Yes | P6: 8
A7: Coding & software development | B7: Cognition | C7: Devin + Windsurf | D7: Autonomous software engineer (Devin) + agentic IDE (Windsurf, acquired 2025) | E7: Annualized revenue (Sacra estimate) | F7: 492 | G7: May 2026 | H7: $37M (2025) -> $492M May 2026 (~13x); targeting $1B by year-end | I7: 10.2 | J7: 2026 private mark | K7: ACU (agent compute unit) credits from $20 + multi-seat enterprise licenses | N7: Analyst estimate (Sacra) | O7: Yes | P7: 8, 11
A8: Coding & software development | B8: Lovable | C8: Lovable | D8: Vibe-coding / text-to-app agent platform | E8: ARR (reported) | F8: 400 | G8: Feb 2026 | H8: $100M ARR within ~12 months of launch -> $400M Feb 2026 | K8: Subscription + usage | N8: Press-reported | O8: Yes | P8: 8, 39
A9: Customer experience & support | B9: Sierra | C9: Sierra Agents | D9: Enterprise customer-service agents across chat, voice, email (Bret Taylor / Clay Bavor) | E9: ARR (Sacra estimate) | F9: 200 | G9: May 2026 | H9: $26M end-2024 -> $100M Nov 2025 (21 months from launch) -> $150M Feb 2026 -> $200M May 2026 | I9: 15.8 | J9: May 2026 Series E ($950M) | K9: Outcome-based (~$1.50 per resolved interaction) + volume-based for routine flows | L9: Customers: SoFi, Ramp, Brex, Discord, Rivian, ADT, Cigna, SiriusXM; 50%+ of customers >$1B revenue | N9: Analyst estimate (Sacra) | O9: Yes | P9: 9, 10, 39
A10: Customer experience & support | B10: Decagon | C10: Decagon AI Agents | D10: AI customer-support agents for internet-native and consumer businesses | E10: ARR (reported) | F10: 100 | G10: 2026 (crossed $100M) | H10: ~$6M ARR late 2024 -> $100M+ 2026 | K10: Per-conversation pricing | L10: Customers: Duolingo, Notion, Webflow | N10: Press-reported | O10: Yes | P10: 9, 12, 39
A11: Customer experience & support | B11: Wonderful AI | C11: Wonderful | D11: Customer-service agents focused on non-English markets | E11: Not disclosed | H11: Revenue 'growing'; $286M raised in 13 months | I11: 2 | J11: 2026 private mark | N11: Not disclosed | O11: No (revenue n/d) | P11: 11
A12: Legal | B12: Harvey | C12: Harvey | D12: Legal AI agents: research, contract review, document analysis, drafting | E12: ARR (reported) | F12: 300 | G12: Mid-2026 | H12: $50M end-2024 -> $190M Jan 2026 (~4x YoY) -> ~$300M mid-2026 | I12: 11 | J12: Mar 2026 raise ($200M, GIC/Sequoia); up from $8B late 2025 | K12: Per-seat + enterprise contracts (7-figure ACVs) | L12: 100K+ lawyers; 1,300+ organizations | N12: Press-reported | O12: Yes | P12: 11, 12, 39
A13: Healthcare | B13: OpenEvidence | C13: OpenEvidence | D13: AI clinical decision support / evidence search for clinicians | E13: ARR (reported) | F13: 300 | G13: Jul 21, 2026 | H13: $50M 2025 -> $150M ~Dec 2025 -> $300M Jul 2026 (7.1 months to double) | I13: 12 | J13: Jan 2026 Series D ($250M) | K13: Free to clinicians; monetization via sponsors/enterprise | L13: 860K clinician users; used by ~40% of US physicians; 16.5M clinical consultations/month (2025) | N13: Press-reported | O13: Yes | P13: 14
A14: Healthcare | B14: Abridge | C14: Abridge | D14: Ambient clinical documentation (AI scribe) with deep Epic integration | E14: ARR (Sacra estimate) | F14: 100 | G14: May 2025 | H14: $60M end-2024 -> $100M May 2025; contracted ARR $117M Q1 2025 | I14: 5.3 | J14: Jun 2025 Series E ($300M, a16z) + $316M extension Apr 2026 | K14: ~$208/mo (~$2,500/clinician/yr enterprise) | L14: ~30% ambient-scribe market share; 250+ health systems (Kaiser, Mayo, Hopkins, Duke) | N14: Analyst estimate (Sacra) | O14: Yes | P14: 13, 15, 16, 38
A15: Healthcare | B15: Hippocratic AI | C15: Hippocratic Agents | D15: Patient-facing healthcare agents (pre-op, discharge, chronic-care outreach) | E15: Annual revenue (reported) | F15: 76 | G15: 2026 | H15: 115M+ patient interactions completed | I15: 3.5 | J15: Late 2025 Series C ($126M) | K15: Custom enterprise (per-agent-hour model) | L15: 50+ health-system, payor and pharma partners across 6 countries | N15: Press-reported | O15: Yes | P15: 16, 39
A16: Healthcare | B16: Ambience Healthcare | C16: Ambience | D16: Ambient documentation + coding for multi-specialty health systems | E16: ARR (analyst estimate) | F16: 30 | G16: May 2025 | H16: Unicorn ($1.25B) in 2025 | I16: 1.25 | J16: 2025 round | K16: Custom, est. $250+/clinician/mo | N16: Analyst estimate | O16: Yes | P16: 15, 16, 38
A17: Financial services | B17: Rogo | C17: Rogo (Felix) | D17: Agentic AI analyst for investment banking: models, comps, memos, pitchbooks, CIMs | E17: ARR (analyst-inferred range $50-100M; midpoint shown) | F17: 75 | G17: Mid-2026 | H17: $2M 2024 -> $15M+ 2025 (disclosed); >50% QoQ ARR growth entering mid-2026 | I17: 2 | J17: Apr 2026 Series D ($160M, Kleiner Perkins) | K17: Enterprise seats (single-tenant deployments) | L17: 35K+ professionals; 300+ institutions (Lazard, Jefferies, Moelis, Rothschild, Nomura, Baird); 50K+ queries/day | N17: Analyst-inferred (ARR not disclosed) | O17: Yes | P17: 33, 34
A18: Financial services | B18: Hebbia | C18: Hebbia Matrix | D18: Multi-document agentic analysis for finance, legal, PE diligence | E18: ARR (reported) | F18: 24.6 | G18: Late 2025 | I18: 0.7 | J18: 2024 Series B (a16z); $161M total funding | K18: Enterprise contracts | N18: Press-reported | O18: Yes | P18: 34
A19: Financial services | B19: AlphaSense | C19: AlphaSense (agentic research) | D19: Market-intelligence search adding agentic research workflows (partially agentic) | E19: ARR (reported) | F19: 200 | G19: 2026 | I19: 4 | J19: 2026 private mark | K19: Enterprise subscriptions | L19: 10,000+ content sources | N19: Press-reported; partially agentic (flagged) | O19: Yes | P19: 34
A20: Enterprise platform agents | B20: Salesforce | C20: Agentforce | D20: CRM-native agent platform (service, sales, IT) with Atlas reasoning engine | E20: ARR (company-disclosed) | F20: 1200 | G20: Q1 FY2027 (qtr ended Apr 2026) | H20: $800M Q4 FY2026 (+169% YoY) -> $1.2B Q1 FY2027 (+205% YoY); total AI+Data ARR $3.4B | J20: Public (NYSE: CRM) | K20: $2/conversation + Flex Credits ($500 per 100K credits) | L20: 18,500+ customers (9,500+ paid); 4M autonomous inquiries on Salesforce's own support in 15 months | M20: 28.6T tokens processed in Q1 FY2027 (+152% QoQ); 3.8B agentic work units delivered | N20: Company-disclosed | O20: Yes | P20: 17, 18, 19, 20
A21: Enterprise platform agents | B21: ServiceNow | C21: Now Assist / AI Agents | D21: Workflow-native agents for ITSM/ESM (Agent Fabric, AI Control Tower) | E21: ACV (reported) | F21: 1000 | G21: Mid-2026 | H21: AI portfolio anchored by Now Assist reached $1B ACV | J21: Public (NYSE: NOW) | K21: Bundled in Pro Plus / Enterprise Plus tiers (20-40% uplift at renewal) + message packs | L21: Gartner #1 for building/managing AI agents (2025) | N21: Press-reported | O21: Yes | P21: 19, 20
A22: Enterprise platform agents | B22: Microsoft | C22: M365 Copilot + Agent 365 + Copilot Studio | D22: Productivity copilot evolving to autonomous 'Autopilots'; agent governance via Agent 365 | E22: Not disclosed (excluded from aggregates) | G22: Q4 FY26 (Jun 2026) | H22: Seats: 15M Q2 -> 20M Q3 -> 30M+ Q4 FY26; at $30/user/mo list, implies up to ~$10.8B annualized before discounts (not disclosed) | J22: Public (NASDAQ: MSFT) | K22: $30-$99/user/mo seats; Copilot Studio $200/mo per 25K credits or $0.01/credit PAYG | L22: 30M+ paid M365 Copilot seats; Agent 365: ~40M registered agents within 2 months of launch | M22: Azure AI Foundry: 100K customers; customers at 1T-token annualized run-rate up 4x YoY | N22: Seats disclosed; revenue not disclosed | O22: No (revenue n/d) | P22: 36, 37, 19, 20
A23: Enterprise platform agents | B23: Glean | C23: Glean Assistant + Agents | D23: Enterprise knowledge graph powering search and agentic workflows | E23: ARR / annualized run-rate (company-disclosed) | F23: 300 | G23: May 2026 | H23: $100M Feb 2025 -> $300M May 2026 (3x in 15 months) | I23: 7.2 | J23: Jun 2025 Series F ($150M) | K23: Consumption-based + hybrid (fixed per-active-user + usage) | L23: Customers: Databricks, Reddit, Pinterest, Samsung | M23: Sells token-cost reduction: context graph cuts tokens consumed by connected AI | N23: Company-disclosed | O23: Yes | P23: 35
A24: General-purpose & consumer agents | B24: Perplexity | C24: Comet (agentic browser) + Perplexity | D24: Agentic browser and answer engine with multi-agent orchestration (company-wide figure) | E24: Annualized revenue (reported, company-wide) | F24: 500 | G24: Apr 2026 | K24: Subscriptions (Pro/Max) + enterprise | N24: Press-reported; company-wide (not agent-only) | O24: Yes | P24: 30
A25: General-purpose & consumer agents | B25: Genspark | C25: Genspark Super Agent | D25: All-in-one agentic workspace for search/productivity using multiple frontier models | E25: ARR (reported) | F25: 100 | G25: 2026 | H25: $50M ARR in first 5 months | I25: 1.6 | J25: 2026 round | K25: Subscription + credits | N25: Press-reported | O25: Yes | P25: 11, 39
A26: General-purpose & consumer agents | B26: Manus (Butterfly Effect) | C26: Manus | D26: Consumer general-purpose agent: browser control, research, integrations | E26: Annualized revenue (press estimate) | F26: 90 | G26: Aug 2025 | H26: Launched Mar 2025 | K26: Credit-based subscriptions | N26: Press estimate (dated) | O26: Yes | P26: 30
A27: General-purpose & consumer agents | B27: OpenAI | C27: ChatGPT Agent / Agents platform (memo) | D27: Deep research + computer use + AgentKit; memo row to avoid double-counting Codex | E27: Memo: agents >40% of enterprise revenue (Feb 2026); enterprise >50% of $40B run-rate (Aug 2026) implies ~$8B+ agent revenue incl. Codex | G27: Aug 2026 | H27: ChatGPT for Work: 7M+ seats (Feb 2026, +40% in 2 months); paying business users ~9M; internal forecast ~$29B agent revenue by 2029 | J27: IPO planned | K27: Seats + usage; per-task fees emerging | N27: Derived (memo only) | O27: No (memo; overlaps Codex) | P27: 31, 32
A28: Model providers (memo - not summed) | B28: OpenAI | C28: Company total | D28: Full company run-rate; agentic products (Codex, agents) are the fastest-growing segment | E28: Annualized run-rate (Bloomberg/CNBC-confirmed) | F28: 40000 | G28: Aug 2026 | H28: ~$20B end-2025 -> $40B+ Aug 2026 (+20% MoM in July); enterprise >50% of mix; ads ~$1B run-rate | J28: IPO planned | K28: Subscriptions, API usage, ads | L28: 800M+ weekly ChatGPT users; 20M WAU coding/work products | M28: API: >6B tokens/min (Oct 2025 DevDay) = ~260T tokens/month, excl. ChatGPT | N28: Confirmed by Bloomberg/CNBC | O28: No (memo) | P28: 29, 30, 31
A29: Model providers (memo - not summed) | B29: Anthropic | C29: Company total | D29: Full company run-rate; Claude Code is ~22% of tracked ARR; enterprise API 80-85% of mix | E29: Annualized run-rate (Bloomberg via internal docs) | F29: 65000 | G29: End of July 2026 | H29: $14B Feb 2026 -> $65B Jul 2026; Q2 2026 revenue $11.5B (> OpenAI's quarter, first time); first positive operating income | I29: 380 | J29: Feb 2026 Series G post-money | K29: API usage, subscriptions | L29: 34.4% of B2B market vs OpenAI 32.3% (Jul 2026) | M29: Token throughput not disclosed; Barclays sees Anthropic leading enterprise inference tokens | N29: Bloomberg-reported | O29: No (memo) | P29: 6
A30: Model providers (memo - not summed) | B30: Google | C30: Gemini (platform total) | D30: Agentic revenue not broken out; included for token-scale context | E30: Not broken out | G30: May 2026 | J30: Public (NASDAQ: GOOGL) | K30: API usage, subscriptions, ads | L30: 8.5M developers building with Gemini monthly | M30: 3.2 quadrillion tokens/month across products (May 2026); Gemini models ~22B tokens/min (~1 quadrillion/month) Q2 2026 | N30: Company-disclosed (tokens) | O30: No (memo) | P30: 21, 22, 23

Sheet Sector Aggregates
A1: Sector | B1: # offerings tracked | C1: # with revenue in aggregate | D1: Aggregate annualized revenue ($M) | E1: Share of tracked total | F1: Notes
A2: Coding & software development | B2: 7 | C2: =COUNTIFS(Offerings!A:A,A2,Offerings!O:O,"Yes",Offerings!F:F,">0") | D2: =SUMIFS(Offerings!F:F,Offerings!A:A,A2,Offerings!O:O,"Yes") | E2: =D2/D$9 | F2: Largest agentic sector by revenue; Claude Code + Codex figures are third-party tracked estimates. Cursor acquired by SpaceX for $60B (Jun 2026).
A3: Customer experience & support | B3: 3 | C3: =COUNTIFS(Offerings!A:A,A3,Offerings!O:O,"Yes",Offerings!F:F,">0") | D3: =SUMIFS(Offerings!F:F,Offerings!A:A,A3,Offerings!O:O,"Yes") | E3: =D3/D$9 | F3: Excludes Agentforce (classified under Enterprise platforms) and Wonderful AI (revenue n/d). Category commands the highest revenue multiples (~127x ARR avg).
A4: Legal | B4: 1 | C4: =COUNTIFS(Offerings!A:A,A4,Offerings!O:O,"Yes",Offerings!F:F,">0") | D4: =SUMIFS(Offerings!F:F,Offerings!A:A,A4,Offerings!O:O,"Yes") | E4: =D4/D$9 | F4: Harvey dominates; 7-figure enterprise contracts at large law firms.
A5: Healthcare | B5: 4 | C5: =COUNTIFS(Offerings!A:A,A5,Offerings!O:O,"Yes",Offerings!F:F,">0") | D5: =SUMIFS(Offerings!F:F,Offerings!A:A,A5,Offerings!O:O,"Yes") | E5: =D5/D$9 | F5: Sub-segment sizing (Information Matters, May 2026): scribes $300-500M; RCM automation $0.8-1.2B; payer prior-auth $200-400M; sector central case ~$5.5B incl. drug-discovery value.
A6: Financial services | B6: 3 | C6: =COUNTIFS(Offerings!A:A,A6,Offerings!O:O,"Yes",Offerings!F:F,">0") | D6: =SUMIFS(Offerings!F:F,Offerings!A:A,A6,Offerings!O:O,"Yes") | E6: =D6/D$9 | F6: Rogo ARR not disclosed - $75M shown is midpoint of analyst-inferred $50-100M. AlphaSense only partially agentic.
A7: Enterprise platform agents | B7: 4 | C7: =COUNTIFS(Offerings!A:A,A7,Offerings!O:O,"Yes",Offerings!F:F,">0") | D7: =SUMIFS(Offerings!F:F,Offerings!A:A,A7,Offerings!O:O,"Yes") | E7: =D7/D$9 | F7: Excludes Microsoft M365 Copilot (revenue n/d; 30M+ seats imply up to ~$10.8B at list price) - materially understated.
A8: General-purpose & consumer agents | B8: 4 | C8: =COUNTIFS(Offerings!A:A,A8,Offerings!O:O,"Yes",Offerings!F:F,">0") | D8: =SUMIFS(Offerings!F:F,Offerings!A:A,A8,Offerings!O:O,"Yes") | E8: =D8/D$9 | F8: Perplexity figure is company-wide; Manus figure dated Aug 2025. OpenAI ChatGPT Agent excluded (memo; overlaps Codex).
A9: TOTAL (tracked, ex-memo rows) | B9: =SUM(B2:B8) | C9: =SUM(C2:C8) | D9: =SUM(D2:D8) | E9: 1
A11: Memo: model-provider company totals (not summed above) | D11: =SUMIFS(Offerings!F:F,Offerings!A:A,"Model providers (memo - not summed)") | F11: OpenAI $40B (Aug 2026) + Anthropic $65B (Jul 2026) run-rates; agentic products are the top growth driver for both.

Sheet Token Usage
A1: Entity / platform | B1: Metric | C1: Value | D1: As-of | E1: Context / notes | F1: Sources (#)
A2: Industry-wide | B2: Estimated global token processing | C2: ~370 trillion/day (~135 quadrillion/yr) | D2: Mid-2026 | E2: I/O Fund estimate; already 2.4x Dell's 2028 forecast of 57 quadrillion/yr | F2: 23
A3: Google (all products) | B3: Monthly tokens processed | C3: 3.2 quadrillion/month | D3: May 2026 (I/O) | E3: vs ~480T May 2025 (~7x YoY) and 9.7T May 2024 (~330x in 2 years); includes Search, Workspace, Gemini apps | F3: 21
A4: Google Gemini Developer API | B4: API token throughput | C4: 19B tokens/min (~800T/month) | D4: May 2026 | E4: 375+ Google Cloud customers each processed >1T tokens in trailing 12 months | F4: 21, 22
A5: Google Gemini models | B5: Model token throughput | C5: 22B tokens/min (~1 quadrillion/month) | D5: Q2 2026 earnings | E5: +120% in six months | F5: 23
A6: OpenAI API | B6: API token throughput | C6: >6B tokens/min (~260T/month) | D6: Oct 2025 (DevDay) | E6: API only; excludes ChatGPT consumer traffic (800M+ weekly users) | F6: 22
A7: Anthropic | B7: Token throughput | C7: Not disclosed | D7: 2026 | E7: Barclays analysts see Anthropic leading enterprise inference tokens; 65% of Vercel AI Gateway spend on 30% of volume | F7: 22, 24
A8: Microsoft Azure AI Foundry | B8: Customers at 1T-token annualized run-rate | C8: Up 4x YoY; 100K Foundry customers | D8: Q4 FY26 (Jun 2026) | E8: Foundry revenue more than doubled YoY; 11,000+ models offered; Copilot workload throughput up 4x during FY26 | F8: 36, 37
A9: Microsoft Agent 365 | B9: Registered agents | C9: ~40M agents | D9: Q4 FY26 (2 months post-launch) | E9: Across tens of thousands of companies; agent governance layer | F9: 36, 37
A10: Salesforce Agentforce | B10: Tokens processed | C10: 28.6T in Q1 FY2027 (+152% QoQ) | D10: Qtr ended Apr 2026 | E10: 3.8B agentic work units delivered (+111%) | F10: 17, 18
A11: OpenRouter (router) | B11: Total routed tokens | C11: >20T/week (~80-90T/month) | D11: Mid-2026 | E11: State of AI study covered 100T+ tokens over ~1 year | F11: 22, 26
A12: OpenRouter (router) | B12: Agentic token multiplier | C12: ~15x tokens per request vs human chat | D12: 2026 | E12: Agentic share exploded starting Feb 2026; traffic segmented agentic/mixed/human by 7-signal composite | F12: 25
... A18: Claude Code | B18: Output footprint | C18: ~4% of all global public GitHub commits (SemiAnalysis); projected 20%+ of daily commits by end-2026 | D18: Feb 2026 | E18: Average developer ~20 hrs/week in tool | F18: 4 (via orbilontech), 5

Sheet Sources
A1: # | B1: Publisher | C1: Title / description | D1: URL
A2: 1 | B2: Axis Intelligence | C2: Cursor AI Statistics 2026: Revenue, Users, Valuation & Market Data | D2: https://axis-intelligence.com/cursor-ai-statistics/
A3: 2 | B3: Value Add VC | C3: How Does Cursor Make Money: Subscriptions, Token Pricing, Business Model | D3: https://valueaddvc.com/blog/how-does-cursor-make-money-subscriptions-token-pricing-and-the-business-model-breakdown
A4: 3 | B4: TickerTrends | C4: Claude Code Reaches $15.1B in Tracked ARR as Codex Climbs to $8.8B (Aug 10, 2026) | D4: https://blog.tickertrends.io/p/claude-code-vs-openai-codex-arr
A5: 4 | B5: Enterprise DNA | C5: Claude Code Hits $2.5B ARR in Just 13 Months (Feb 2026 Series G disclosure) | D5: https://enterprisedna.co/resources/news/claude-code-25-billion-arr-anthropic-2026/
A6: 5 | B6: FourWeekMBA | C6: Claude Code Scaled from $1B to $8B Annualized Run-Rate in Six Months (Sacra data) | D6: https://fourweekmba.com/ai-claude-code-run-rate-agentic-layer/
A7: 6 | B7: Forkast / Bloomberg | C7: Anthropic Q2 2026 Revenue ($11.5B) Overtook OpenAI; $65B run-rate end of July 2026 | D7: https://forkast.news/anthropics-q2-revenue-overtook-openai-for-the-first-time-and-reached-its-first-positive-operating-income/
A8: 7 | B8: Axis Intelligence | C8: GitHub Copilot Statistics 2026: Users, Revenue, Market Share | D8: https://axis-intelligence.com/github-copilot-statistics/
A9: 8 | B9: Value Add VC | C9: How Does Cognition Make Money: Devin Pricing, Windsurf, and $492M ARR | D9: https://valueaddvc.com/blog/how-does-cognition-make-money-devin-pricing-windsurf-enterprise-and-the-492m-arr-breakdown
A10: 9 | B10: Sacra | C10: Sierra revenue, valuation & funding ($200M ARR May 2026) | D10: https://sacra.com/c/sierra/
A11: 10 | B11: Value Add VC | C11: How Does Sierra AI Make Money: Outcome-Based Pricing ($15.8B valuation) | D11: https://valueaddvc.com/blog/how-does-sierra-ai-make-money-outcome-based-pricing-enterprise-agents-and-the-business-model-breakdown
A12: 11 | B12: AgentMarketCap | C12: Vertical Agent Revenue Ranked (Apr 2026): Harvey, Agentforce, Sierra, Genspark | D12: https://agentmarketcap.ai/blog/2026/04/05/vertical-agent-revenue-ranked-harvey-salesforce-iqvia-domain-specific-agents
A13: 12 | B13: AgentMarketCap | C13: The Verticalization Premium: Harvey and Sierra valuation multiples (Apr 2026) | D13: https://agentmarketcap.ai/blog/2026/04/07/vertical-vs-horizontal-ai-agent-valuations-2026
... A41: 40 | B41: THE DAILY BRIEF (beri.net) | C41: Why SpaceX Paid $60B for Cursor: $4B ARR (June 2026) | D41: https://www.beri.net/article/spacex-cursor-60b-acquisition-2026
