Workbook

Sheet Read Me
B2: AI Lab Compute Economics - Quarterly Time Series
B3: GW capacity, revenue, cost, and token volume for frontier and open-weight AI labs | Q1 2024 - Q3 2026 | Compiled Aug 23, 2026
B5: What's inside
B6: 1. Summary (Q2 2026) | C6: Latest-full-quarter snapshot: GW, ARR, revenue/GW, est. compute cost, cost/GW, tokens - with frontier vs open-weight subtotals.
B7: 2. GW Capacity | C7: Estimated operational AI compute capacity (owned + leased IT power, GW, end of quarter) per lab, with subtotals and chart.
B8: 3. Revenue (Quarterly) | C8: Booked revenue per calendar quarter, $B.
B9: 4. Revenue Run Rate | C9: Annualized run-rate revenue at quarter end, $B (the metric labs quote publicly).
B10: 5. Compute Cost | C10: Estimated quarterly compute cost per lab (GW x $8.5B/GW/yr TCO), industry build-capex-per-GW benchmark, and reported cost datapoints.
B11: 6. Rev & Cost per GW | C11: Derived: annualized revenue per operational GW vs annualized cost per GW, by lab and quarter.
B12: 7. Token Volume | C12: Estimated tokens processed per quarter (trillions), all surfaces, with global market anchors and chart.
B13: 8. Sources & Methodology | C13: Every disclosed anchor with source + URL, and metric-by-metric methodology and caveats.
B15: Lab coverage
B16: Frontier (closed) | C16: OpenAI, Anthropic, Google DeepMind, xAI
B17: Open-weight | C17: Meta (Llama), DeepSeek, Alibaba (Qwen), Mistral AI
B19: How to read it
B20: Red bold cells | C20: Directly disclosed figures (company statements, filings, earnings). Everything else is estimated/interpolated - see Sources & Methodology.
B21: 'Q3 2026 (part.)' | C21: Partial quarter: quarter-to-date run rates as of Aug 23, 2026, extrapolated.
B22: 'n/a' (Meta revenue) | C22: Meta gives Llama away and monetizes via ads - it has no separable model revenue, so revenue-per-GW is not meaningful for it.
B23: Error bars | C23: Capacity and token estimates for private companies carry +/-30% or wider uncertainty. Treat as order-of-magnitude, directionally reliable.
B25: Headline takeaways (Q2-Q3 2026)
B26: Revenue | C26: Anthropic leads on run rate ($65B Jul 2026) vs OpenAI ($40B Aug 2026); Google AI ~$30B+; everyone else is <$10B. Anthropic turned adjusted-operating-income positive in Q2 2026.
B27: Capacity | C27: The 8 labs run ~12 GW operational vs 40+ GW contracted. Meta has the largest fleet (~3.6 GW incl. recsys); Google ~2.8 GW; Anthropic ~1.8 GW; announced pipelines (Stargate 9+ GW, Meta 14 GW) dwarf what is energized.
B28: Tokens | C28: Google processes the most tokens (3.2 quadrillion/month May 2026). On neutral routing (OpenRouter), open-weight models flipped to a 60/40 majority by Jun 2026, led by DeepSeek (~23%).
B29: Economics | C29: ~$31B/yr revenue per GW is the break-even benchmark; Anthropic (~$26B/GW) and OpenAI (~$22B/GW) are approaching it, Google sits lower on paid revenue per GW (heavy un-monetized internal usage), and open-weight labs monetize a small fraction of their token footprint.

Sheet Summary (Q2 2026)
A1: Summary - Q2 2026 (last full quarter)
A2: Formula-linked snapshot. ARR = end-of-quarter annualized run rate. Break-even revenue/GW benchmark ~$31B/yr (YK Research).
A4: Lab | B4: Category | C4: Operational GW | D4: ARR ($B/yr) | E4: Revenue / GW ($B/yr per GW) | F4: Est. compute cost ($B/yr) | G4: Cost / GW ($B/yr per GW) | H4: Tokens Q2'26 (T) | I4: Notes
A5: OpenAI | B5: Frontier (closed) | C5: ='GW Capacity'!L5 | D5: ='Revenue Run Rate'!L5 | E5: =D5/C5 | F5: =C5*'Compute Cost'!$C$3 | G5: ='Compute Cost'!$C$3 | H5: ='Token Volume'!L5 | I5: Compute mostly leased (Microsoft Azure, Oracle, Stargate JV). Abilene ~0.3 GW live mid-2026; 9+ GW contracted through 2029.
A6: Anthropic | B6: Frontier (closed) | C6: ='GW Capacity'!L6 | D6: ='Revenue Run Rate'!L6 | E6: =D6/C6 | F6: =C6*'Compute Cost'!$C$3 | G6: ='Compute Cost'!$C$3 | H6: ='Token Volume'!L6 | I6: Compute leased from AWS (Project Rainier / New Carlisle ~1 GW live Mar 2026), Google TPU (1 GW+ landing 2026), SpaceX (300 MW). Best-documented revenue ramp.
A7: Google DeepMind | B7: Frontier (closed) | C7: ='GW Capacity'!L7 | D7: ='Revenue Run Rate'!L7 | E7: =D7/C7 | F7: =C7*'Compute Cost'!$C$3 | G7: ='Compute Cost'!$C$3 | H7: ='Token Volume'!L7 | I7: TPU fleet allocated to Gemini training + inference (subset of Alphabet's total fleet). Revenue = Gemini/Vertex/Workspace-AI attributable estimate, not an Alphabet segment.
A8: xAI | B8: Frontier (closed) | C8: ='GW Capacity'!L8 | D8: ='Revenue Run Rate'!L8 | E8: =D8/C8 | F8: =C8*'Compute Cost'!$C$3 | G8: ='Compute Cost'!$C$3 | H8: ='Token Volume'!L8 | I8: Self-built Colossus 1 (~0.3 GW, Memphis) + Colossus 2 ramping toward 2 GW. Standalone AI revenue only (excludes X ads/subscriptions).
A9: Meta (Llama) | B9: Open-weight | C9: ='GW Capacity'!L9 | D9: n/a | E9: n/a | F9: =C9*'Compute Cost'!$C$3 | G9: ='Compute Cost'!$C$3 | H9: ='Token Volume'!L9 | I9: AI accelerator fleet across all workloads (GenAI + ranking/recsys). No direct model revenue - monetized via ads; Llama licensed free. Plans 7 GW deployed during 2026, 14 GW by 2027.
A10: DeepSeek | B10: Open-weight | C10: ='GW Capacity'!L10 | D10: ='Revenue Run Rate'!L10 | E10: =D10/C10 | F10: =C10*'Compute Cost'!$C$3 | G10: ='Compute Cost'!$C$3 | H10: ='Token Volume'!L10 | I10: ~20k H100-equivalent fleet (mid-2026 disclosure); extreme efficiency focus; 1 GW Ulanqab site planned for late 2027/28. Revenue = API hosting only; open weights are free.
A11: Alibaba (Qwen) | B11: Open-weight | C11: ='GW Capacity'!L11 | D11: ='Revenue Run Rate'!L11 | E11: =D11/C11 | F11: =C11*'Compute Cost'!$C$3 | G11: ='Compute Cost'!$C$3 | H11: ='Token Volume'!L11 | I11: Revenue = Alibaba's disclosed 'AI-related product revenue' (calendar-quarter mapped). GW = estimated AI portion of Alibaba Cloud fleet. Qwen weights free (3B+ downloads).
A12: Mistral AI | B12: Open-weight | C12: ='GW Capacity'!L12 | D12: ='Revenue Run Rate'!L12 | E12: =D12/C12 | F12: =C12*'Compute Cost'!$C$3 | G12: ='Compute Cost'!$C$3 | H12: ='Token Volume'!L12 | I12: European open-weight lab. Small self + leased footprint (Eclairion France DC, Sweden DC committed). ARR $312M Dec 2025 -> ~$1B May 2026.
A13: Frontier subtotal | C13: =C5+C6+C7+C8 | D13: =D5+D6+D7+D8 | E13: =D13/C13 | F13: =F5+F6+F7+F8 | G13: ='Compute Cost'!$C$3 | H13: =H5+H6+H7+H8
A14: Open-weight subtotal | C14: =C9+C10+C11+C12 | D14: =D10+D11+D12 | E14: =D14/C14 | F14: =F9+F10+F11+F12 | G14: ='Compute Cost'!$C$3 | H14: =H9+H10+H11+H12
A15: TOTAL (all 8 labs) | C15: =C5+C6+C7+C8+C9+C10+C11+C12 | D15: =D5+D6+D7+D8+D10+D11+D12 | E15: =D15/C15 | F15: =F5+F6+F7+F8+F9+F10+F11+F12 | G15: ='Compute Cost'!$C$3 | H15: =H5+H6+H7+H8+H9+H10+H11+H12
A17: Current as of Aug 23, 2026: Anthropic ARR $65B (Jul), OpenAI $40B (Aug) - see Revenue Run Rate sheet, Q3 2026 column.

Sheet GW Capacity
A1: GW Capacity
A2: Estimated operational AI compute capacity serving each lab (owned + leased IT power, gigawatts, end of quarter). Red bold = disclosed. Contracted/announced capacity is far larger - see Sources.
A4: Lab | B4: Category | C4: Q1 2024 | D4: Q2 2024 | E4: Q3 2024 | F4: Q4 2024 | G4: Q1 2025 | H4: Q2 2025 | I4: Q3 2025 | J4: Q4 2025 | K4: Q1 2026 | L4: Q2 2026 | M4: Q3 2026 (part.)
A5: OpenAI | B5: Frontier (closed) | C5: 0.25 | D5: 0.3 | E5: 0.35 | F5: 0.45 | G5: 0.55 | H5: 0.65 | I5: 0.8 | J5: 1 | K5: 1.2 | L5: 1.4 | M5: 1.7
A6: Anthropic | B6: Frontier (closed) | C6: 0.08 | D6: 0.1 | E6: 0.12 | F6: 0.15 | G6: 0.2 | H6: 0.3 | I6: 0.45 | J6: 0.7 | K6: 1.2 | L6: 1.8 | M6: 2.2
A7: Google DeepMind | B7: Frontier (closed) | C7: 0.8 | D7: 0.9 | E7: 1 | F7: 1.2 | G7: 1.4 | H7: 1.6 | I7: 1.9 | J7: 2.2 | K7: 2.5 | L7: 2.8 | M7: 3.2
A8: xAI | B8: Frontier (closed) | C8: 0.02 | D8: 0.05 | E8: 0.15 | F8: 0.2 | G8: 0.25 | H8: 0.3 | I8: 0.4 | J8: 0.6 | K8: 0.9 | L8: 1.2 | M8: 1.4
A9: Meta (Llama) | B9: Open-weight | C9: 1 | D9: 1.15 | E9: 1.3 | F9: 1.5 | G9: 1.7 | H9: 1.95 | I9: 2.2 | J9: 2.5 | K9: 3 | L9: 3.6 | M9: 4.2
A10: DeepSeek | B10: Open-weight | C10: 0.01 | D10: 0.012 | E10: 0.014 | F10: 0.016 | G10: 0.018 | H10: 0.02 | I10: 0.022 | J10: 0.024 | K10: 0.026 | L10: 0.03 | M10: 0.035
A11: Alibaba (Qwen) | B11: Open-weight | C11: 0.25 | D11: 0.3 | E11: 0.35 | F11: 0.4 | G11: 0.5 | H11: 0.6 | I11: 0.7 | J11: 0.85 | K11: 1 | L11: 1.2 | M11: 1.4
A12: Mistral AI | B12: Open-weight | C12: 0.005 | D12: 0.006 | E12: 0.008 | F12: 0.01 | G12: 0.012 | H12: 0.015 | I12: 0.018 | J12: 0.025 | K12: 0.032 | L12: 0.04 | M12: 0.05
A13: Frontier subtotal | C13: =C5+C6+C7+C8 | D13: =D5+D6+D7+D8 | E13: =E5+E6+E7+E8 | F13: =F5+F6+F7+F8 | G13: =G5+G6+G7+G8 | H13: =H5+H6+H7+H8 | I13: =I5+I6+I7+I8 | J13: =J5+J6+J7+J8 | ... M13: =M5+M6+M7+M8
A14: Open-weight subtotal | C14: =C9+C10+C11+C12 | D14: =D9+D10+D11+D12 | E14: =E9+E10+E11+E12 | F14: =F9+F10+F11+F12 | G14: =G9+G10+G11+G12 | H14: =H9+H10+H11+H12 | I14: =I9+I10+I11+I12 | J14: =J9+J10+J11+J12 | ... M14: =M9+M10+M11+M12
A15: TOTAL (all 8 labs) | C15: =C5+C6+C7+C8+C9+C10+C11+C12 | D15: =D5+D6+D7+D8+D9+D10+D11+D12 | E15: =E5+E6+E7+E8+E9+E10+E11+E12 | F15: =F5+F6+F7+F8+F9+F10+F11+F12 | G15: =G5+G6+G7+G8+G9+G10+G11+G12 | H15: =H5+H6+H7+H8+H9+H10+H11+H12 | I15: =I5+I6+I7+I8+I9+I10+I11+I12 | J15: =J5+J6+J7+J8+J9+J10+J11+J12 | ... M15: =M5+M6+M7+M8+M9+M10+M11+M12
A17: Memo: top-10 models operational GW (jasperbernaers, 2026) | L17: 7.8

Sheet Revenue (Quarterly)
A1: Revenue (Quarterly)
A2: Booked revenue per calendar quarter, US$B. Red bold = disclosed (Anthropic Q2'25/Q2'26; Alibaba Q2'26 AI-related product revenue; xAI Q1'26 reported). Meta: no separable model revenue. OpenAI reports net of cloud-partner costs; Anthropic gross - not perfectly comparable.
A4: Lab | B4: Category | C4: Q1 2024 | D4: Q2 2024 | E4: Q3 2024 | F4: Q4 2024 | G4: Q1 2025 | H4: Q2 2025 | I4: Q3 2025 | J4: Q4 2025 | K4: Q1 2026 | L4: Q2 2026 | M4: Q3 2026 (part.)
A5: OpenAI | B5: Frontier (closed) | C5: 0.6 | D5: 0.8 | E5: 1 | F5: 1.3 | G5: 2.2 | H5: 2.9 | I5: 3.6 | J5: 4.4 | K5: 5.9 | L5: 7.2 | M5: 9.5
A6: Anthropic | B6: Frontier (closed) | C6: 0.15 | D6: 0.2 | E6: 0.28 | F6: 0.37 | G6: 0.45 | H6: 0.79 | I6: 1.3 | J6: 2 | K6: 4.8 | L6: 11.5 | M6: 16
A7: Google DeepMind | B7: Frontier (closed) | C7: 0.9 | D7: 1.1 | E7: 1.4 | F7: 1.6 | G7: 2.6 | H7: 3.3 | I7: 4.1 | J7: 5 | K7: 6.2 | L7: 7.5 | M7: 8.8
A8: xAI | B8: Frontier (closed) | C8: 0.01 | D8: 0.02 | E8: 0.03 | F8: 0.04 | G8: 0.06 | H8: 0.09 | I8: 0.11 | J8: 0.14 | K8: 0.82 | L8: 0.45 | M8: 0.5
A9: Meta (Llama) | B9: Open-weight | C9: n/a | D9: n/a | E9: n/a | F9: n/a | G9: n/a | H9: n/a | I9: n/a | J9: n/a | K9: n/a | L9: n/a | M9: n/a
A10: DeepSeek | B10: Open-weight | C10: 0.001 | D10: 0.002 | E10: 0.003 | F10: 0.004 | G10: 0.02 | H10: 0.04 | I10: 0.06 | J10: 0.08 | K10: 0.12 | L10: 0.15 | M10: 0.17
A11: Alibaba (Qwen) | B11: Open-weight | C11: 0.28 | D11: 0.35 | E11: 0.44 | F11: 0.55 | G11: 0.68 | H11: 0.85 | I11: 1.05 | J11: 1.25 | K11: 1.5 | L11: 1.82 | M11: 2.2
A12: Mistral AI | B12: Open-weight | C12: 0.004 | D12: 0.006 | E12: 0.008 | F12: 0.012 | G12: 0.02 | H12: 0.035 | I12: 0.055 | J12: 0.075 | K12: 0.11 | L12: 0.2 | M12: 0.26
A13: Frontier subtotal | C13: =C5+C6+C7+C8 | D13: =D5+D6+D7+D8 | E13: =E5+E6+E7+E8 | F13: =F5+F6+F7+F8 | G13: =G5+G6+G7+G8 | H13: =H5+H6+H7+H8 | I13: =I5+I6+I7+I8 | J13: =J5+J6+J7+J8 | ... M13: =M5+M6+M7+M8
A14: Open-weight subtotal | C14: =C10+C11+C12 | D14: =D10+D11+D12 | E14: =E10+E11+E12 | F14: =F10+F11+F12 | G14: =G10+G11+G12 | H14: =H10+H11+H12 | I14: =I10+I11+I12 | J14: =J10+J11+J12 | ... M14: =M10+M11+M12
A15: TOTAL (all 8 labs) | C15: =C5+C6+C7+C8+C10+C11+C12 | D15: =D5+D6+D7+D8+D10+D11+D12 | E15: =E5+E6+E7+E8+E10+E11+E12 | F15: =F5+F6+F7+F8+F10+F11+F12 | G15: =G5+G6+G7+G8+G10+G11+G12 | H15: =H5+H6+H7+H8+H10+H11+H12 | I15: =I5+I6+I7+I8+I10+I11+I12 | J15: =J5+J6+J7+J8+J10+J11+J12 | ... M15: =M5+M6+M7+M8+M10+M11+M12

Sheet Revenue Run Rate
A1: Revenue Run Rate
A2: Annualized revenue run rate at quarter end, US$B - the metric labs quote publicly. Red bold = disclosed (OpenAI $21.5B end-25 / $25B Q1'26 / $40B Aug'26; Anthropic $9B late-25 / $47B May'26 / $65B Jul'26; Mistral $312M Dec'25 / ~$1B May'26).
A4: Lab | B4: Category | C4: Q1 2024 | D4: Q2 2024 | E4: Q3 2024 | F4: Q4 2024 | G4: Q1 2025 | H4: Q2 2025 | I4: Q3 2025 | J4: Q4 2025 | K4: Q1 2026 | L4: Q2 2026 | M4: Q3 2026 (part.)
A5: OpenAI | B5: Frontier (closed) | C5: 2.8 | D5: 3.4 | E5: 4.4 | F5: 5.5 | G5: 9.5 | H5: 12 | I5: 16 | J5: 21.5 | K5: 25 | L5: 31 | M5: 40
A6: Anthropic | B6: Frontier (closed) | C6: 0.6 | D6: 0.85 | E6: 1.2 | F6: 1.6 | G6: 2.2 | H6: 3.1 | I6: 5.5 | J6: 9 | K6: 22 | L6: 47 | M6: 65
A7: Google DeepMind | B7: Frontier (closed) | C7: 3.8 | D7: 4.6 | E7: 5.6 | F7: 6.8 | G7: 9 | H7: 12 | I7: 15 | J7: 18 | K7: 24 | L7: 30 | M7: 34
A8: xAI | B8: Frontier (closed) | C8: 0.03 | D8: 0.06 | E8: 0.1 | F8: 0.16 | G8: 0.2 | H8: 0.3 | I8: 0.4 | J8: 0.5 | K8: 1 | L8: 1.5 | M8: 1.8
A9: Meta (Llama) | B9: Open-weight | C9: n/a | D9: n/a | E9: n/a | F9: n/a | G9: n/a | H9: n/a | I9: n/a | J9: n/a | K9: n/a | L9: n/a | M9: n/a
A10: DeepSeek | B10: Open-weight | C10: 0.004 | D10: 0.008 | E10: 0.012 | F10: 0.016 | G10: 0.08 | H10: 0.16 | I10: 0.24 | J10: 0.32 | K10: 0.5 | L10: 0.7 | M10: 0.8
A11: Alibaba (Qwen) | B11: Open-weight | C11: 1.1 | D11: 1.4 | E11: 1.8 | F11: 2.2 | G11: 2.7 | H11: 3.4 | I11: 4.2 | J11: 5 | K11: 6 | L11: 7.3 | M11: 8.8
A12: Mistral AI | B12: Open-weight | C12: 0.008 | D12: 0.012 | E12: 0.016 | F12: 0.02 | G12: 0.06 | H12: 0.12 | I12: 0.2 | J12: 0.312 | K12: 0.5 | L12: 1 | M12: 1.2
A13: Frontier subtotal | C13: =C5+C6+C7+C8 | D13: =D5+D6+D7+D8 | E13: =E5+E6+E7+E8 | F13: =F5+F6+F7+F8 | G13: =G5+G6+G7+G8 | H13: =H5+H6+H7+H8 | I13: =I5+I6+I7+I8 | J13: =J5+J6+J7+J8 | ... M13: =M5+M6+M7+M8
A14: Open-weight subtotal | C14: =C10+C11+C12 | D14: =D10+D11+D12 | E14: =E10+E11+E12 | F14: =F10+F11+F12 | G14: =G10+G11+G12 | H14: =H10+H11+H12 | I14: =I10+I11+I12 | J14: =J10+J11+J12 | ... M14: =M10+M11+M12
A15: TOTAL (all 8 labs) | C15: =C5+C6+C7+C8+C10+C11+C12 | D15: =D5+D6+D7+D8+D10+D11+D12 | E15: =E5+E6+E7+E8+E10+E11+E12 | F15: =F5+F6+F7+F8+F10+F11+F12 | G15: =G5+G6+G7+G8+G10+G11+G12 | H15: =H5+H6+H7+H8+H10+H11+H12 | I15: =I5+I6+I7+I8+I10+I11+I12 | J15: =J5+J6+J7+J8+J10+J11+J12 | ... M15: =M5+M6+M7+M8+M10+M11+M12

Sheet Compute Cost
A1: Compute Cost
A2: Estimated quarterly compute cost = operational GW x annualized TCO ($8.5B/GW/yr, Epoch AI) / 4. Formula-linked to the GW Capacity sheet. Bottom: industry build-capex-per-GW benchmark and reported lab cost datapoints.
A3: TCO assumption ($B per GW per year): | C3: 8.5
A5: Lab | B5: Category | C5: Q1 2024 | D5: Q2 2024 | E5: Q3 2024 | F5: Q4 2024 | G5: Q1 2025 | H5: Q2 2025 | I5: Q3 2025 | J5: Q4 2025 | K5: Q1 2026 | L5: Q2 2026 | M5: Q3 2026 (part.)
A6: OpenAI | B6: Frontier (closed) | C6: ='GW Capacity'!C5*$C$3/4 | D6: ='GW Capacity'!D5*$C$3/4 | E6: ='GW Capacity'!E5*$C$3/4 | F6: ='GW Capacity'!F5*$C$3/4 | G6: ='GW Capacity'!G5*$C$3/4 | H6: ='GW Capacity'!H5*$C$3/4 | I6: ='GW Capacity'!I5*$C$3/4 | J6: ='GW Capacity'!J5*$C$3/4 | ... M6: ='GW Capacity'!M5*$C$3/4
A7: Anthropic | B7: Frontier (closed) | C7: ='GW Capacity'!C6*$C$3/4 | D7: ='GW Capacity'!D6*$C$3/4 | E7: ='GW Capacity'!E6*$C$3/4 | F7: ='GW Capacity'!F6*$C$3/4 | G7: ='GW Capacity'!G6*$C$3/4 | H7: ='GW Capacity'!H6*$C$3/4 | I7: ='GW Capacity'!I6*$C$3/4 | J7: ='GW Capacity'!J6*$C$3/4 | ... M7: ='GW Capacity'!M6*$C$3/4
A8: Google DeepMind | B8: Frontier (closed) | C8: ='GW Capacity'!C7*$C$3/4 | D8: ='GW Capacity'!D7*$C$3/4 | E8: ='GW Capacity'!E7*$C$3/4 | F8: ='GW Capacity'!F7*$C$3/4 | G8: ='GW Capacity'!G7*$C$3/4 | H8: ='GW Capacity'!H7*$C$3/4 | I8: ='GW Capacity'!I7*$C$3/4 | J8: ='GW Capacity'!J7*$C$3/4 | ... M8: ='GW Capacity'!M7*$C$3/4
A9: xAI | B9: Frontier (closed) | C9: ='GW Capacity'!C8*$C$3/4 | D9: ='GW Capacity'!D8*$C$3/4 | E9: ='GW Capacity'!E8*$C$3/4 | F9: ='GW Capacity'!F8*$C$3/4 | G9: ='GW Capacity'!G8*$C$3/4 | H9: ='GW Capacity'!H8*$C$3/4 | I9: ='GW Capacity'!I8*$C$3/4 | J9: ='GW Capacity'!J8*$C$3/4 | ... M9: ='GW Capacity'!M8*$C$3/4
A10: Meta (Llama) | B10: Open-weight | C10: ='GW Capacity'!C9*$C$3/4 | D10: ='GW Capacity'!D9*$C$3/4 | E10: ='GW Capacity'!E9*$C$3/4 | F10: ='GW Capacity'!F9*$C$3/4 | G10: ='GW Capacity'!G9*$C$3/4 | H10: ='GW Capacity'!H9*$C$3/4 | I10: ='GW Capacity'!I9*$C$3/4 | J10: ='GW Capacity'!J9*$C$3/4 | ... M10: ='GW Capacity'!M9*$C$3/4
A11: DeepSeek | B11: Open-weight | C11: ='GW Capacity'!C10*$C$3/4 | D11: ='GW Capacity'!D10*$C$3/4 | E11: ='GW Capacity'!E10*$C$3/4 | F11: ='GW Capacity'!F10*$C$3/4 | G11: ='GW Capacity'!G10*$C$3/4 | H11: ='GW Capacity'!H10*$C$3/4 | I11: ='GW Capacity'!I10*$C$3/4 | J11: ='GW Capacity'!J10*$C$3/4 | ... M11: ='GW Capacity'!M10*$C$3/4
A12: Alibaba (Qwen) | B12: Open-weight | C12: ='GW Capacity'!C11*$C$3/4 | D12: ='GW Capacity'!D11*$C$3/4 | E12: ='GW Capacity'!E11*$C$3/4 | F12: ='GW Capacity'!F11*$C$3/4 | G12: ='GW Capacity'!G11*$C$3/4 | H12: ='GW Capacity'!H11*$C$3/4 | I12: ='GW Capacity'!I11*$C$3/4 | J12: ='GW Capacity'!J11*$C$3/4 | ... M12: ='GW Capacity'!M11*$C$3/4
A13: Mistral AI | B13: Open-weight | C13: ='GW Capacity'!C12*$C$3/4 | D13: ='GW Capacity'!D12*$C$3/4 | E13: ='GW Capacity'!E12*$C$3/4 | F13: ='GW Capacity'!F12*$C$3/4 | G13: ='GW Capacity'!G12*$C$3/4 | H13: ='GW Capacity'!H12*$C$3/4 | I13: ='GW Capacity'!I12*$C$3/4 | J13: ='GW Capacity'!J12*$C$3/4 | ... M13: ='GW Capacity'!M12*$C$3/4
A14: Frontier subtotal | C14: =C6+C7+C8+C9 | D14: =D6+D7+D8+D9 | E14: =E6+E7+E8+E9 | F14: =F6+F7+F8+F9 | G14: =G6+G7+G8+G9 | H14: =H6+H7+H8+H9 | I14: =I6+I7+I8+I9 | J14: =J6+J7+J8+J9 | ... M14: =M6+M7+M8+M9
A15: Open-weight subtotal | C15: =C10+C11+C12+C13 | D15: =D10+D11+D12+D13 | E15: =E10+E11+E12+E13 | F15: =F10+F11+F12+F13 | G15: =G10+G11+G12+G13 | H15: =H10+H11+H12+H13 | I15: =I10+I11+I12+I13 | J15: =J10+J11+J12+J13 | ... M15: =M10+M11+M12+M13
A16: TOTAL (all 8 labs) | C16: =C6+C7+C8+C9+C10+C11+C12+C13 | D16: =D6+D7+D8+D9+D10+D11+D12+D13 | E16: =E6+E7+E8+E9+E10+E11+E12+E13 | F16: =F6+F7+F8+F9+F10+F11+F12+F13 | G16: =G6+G7+G8+G9+G10+G11+G12+G13 | H16: =H6+H7+H8+H9+H10+H11+H12+H13 | I16: =I6+I7+I8+I9+I10+I11+I12+I13 | J16: =J6+J7+J8+J9+J10+J11+J12+J13 | ... M16: =M6+M7+M8+M9+M10+M11+M12+M13
A18: Industry build capex per GW ($B/GW, all-in, by GPU generation) | C18: 32 | D18: 32 | E18: 33 | F18: 34 | G18: 35 | H18: 36 | I18: 38 | J18: 40.5 | K18: 42 | L18: 45 | M18: 47
A20: Reported cost datapoints (calibration)
A21: - OpenAI: 2025 operating loss $20.9B on $13.07B revenue; ~$17B/yr cash burn in 2026; $1.4T+ long-term datacenter commitments.
A22: - xAI: ~$1B/month infrastructure + training burn; Q1 2026 operating loss $2.47B on $818M revenue.
A23: - Anthropic: positive ADJUSTED operating income in Q2 2026 - compute cost ran below $11.5B quarterly revenue.
A24: - Meta: 2026 company-wide capex guidance $130-145B (AI-driven); JVs (BlackRock 80/20 El Paso, Blue Owl Louisiana) keep part off balance sheet.
A25: - Alibaba: quarterly capex $9.975B (Jun 2026 quarter, +75% YoY), mostly AI infrastructure.
A26: - Benchmarks: $38B upfront capex/GW (Epoch, GB200-class) rising to ~$47B/GW (Vera Rubin, Bernstein/Foxconn); $0.9B/GW/yr opex; ~$31B/GW/yr inference revenue needed to break even (YK Research).

Sheet Rev & Cost per GW
A1: Revenue & Cost per GW
A2: Annualized run-rate revenue per operational GW vs annualized cost per GW (US$B per GW per year). Formula-linked. Break-even benchmark: ~$31B/yr revenue per GW (YK Research, base case). Cost per GW uses the flat $8.5B/GW/yr TCO benchmark.
A3: REVENUE PER GW ($B ARR / operational GW)
A4: Lab | B4: Category | C4: Q1 2024 | D4: Q2 2024 | E4: Q3 2024 | F4: Q4 2024 | G4: Q1 2025 | H4: Q2 2025 | I4: Q3 2025 | J4: Q4 2025 | K4: Q1 2026 | L4: Q2 2026 | M4: Q3 2026 (part.)
A5: OpenAI | B5: Frontier (closed) | C5: ='Revenue Run Rate'!C5/'GW Capacity'!C5 | D5: ='Revenue Run Rate'!D5/'GW Capacity'!D5 | E5: ='Revenue Run Rate'!E5/'GW Capacity'!E5 | F5: ='Revenue Run Rate'!F5/'GW Capacity'!F5 | G5: ='Revenue Run Rate'!G5/'GW Capacity'!G5 | H5: ='Revenue Run Rate'!H5/'GW Capacity'!H5 | I5: ='Revenue Run Rate'!I5/'GW Capacity'!I5 | J5: ='Revenue Run Rate'!J5/'GW Capacity'!J5 | ... M5: ='Revenue Run Rate'!M5/'GW Capacity'!M5
A6: Anthropic | B6: Frontier (closed) | C6: ='Revenue Run Rate'!C6/'GW Capacity'!C6 | D6: ='Revenue Run Rate'!D6/'GW Capacity'!D6 | E6: ='Revenue Run Rate'!E6/'GW Capacity'!E6 | F6: ='Revenue Run Rate'!F6/'GW Capacity'!F6 | G6: ='Revenue Run Rate'!G6/'GW Capacity'!G6 | H6: ='Revenue Run Rate'!H6/'GW Capacity'!H6 | I6: ='Revenue Run Rate'!I6/'GW Capacity'!I6 | J6: ='Revenue Run Rate'!J6/'GW Capacity'!J6 | ... M6: ='Revenue Run Rate'!M6/'GW Capacity'!M6
A7: Google DeepMind | B7: Frontier (closed) | C7: ='Revenue Run Rate'!C7/'GW Capacity'!C7 | D7: ='Revenue Run Rate'!D7/'GW Capacity'!D7 | E7: ='Revenue Run Rate'!E7/'GW Capacity'!E7 | F7: ='Revenue Run Rate'!F7/'GW Capacity'!F7 | G7: ='Revenue Run Rate'!G7/'GW Capacity'!G7 | H7: ='Revenue Run Rate'!H7/'GW Capacity'!H7 | I7: ='Revenue Run Rate'!I7/'GW Capacity'!I7 | J7: ='Revenue Run Rate'!J7/'GW Capacity'!J7 | ... M7: ='Revenue Run Rate'!M7/'GW Capacity'!M7
A8: xAI | B8: Frontier (closed) | C8: ='Revenue Run Rate'!C8/'GW Capacity'!C8 | D8: ='Revenue Run Rate'!D8/'GW Capacity'!D8 | E8: ='Revenue Run Rate'!E8/'GW Capacity'!E8 | F8: ='Revenue Run Rate'!F8/'GW Capacity'!F8 | G8: ='Revenue Run Rate'!G8/'GW Capacity'!G8 | H8: ='Revenue Run Rate'!H8/'GW Capacity'!H8 | I8: ='Revenue Run Rate'!I8/'GW Capacity'!I8 | J8: ='Revenue Run Rate'!J8/'GW Capacity'!J8 | ... M8: ='Revenue Run Rate'!M8/'GW Capacity'!M8
A9: Meta (Llama) | B9: Open-weight | C9: n/a | D9: n/a | E9: n/a | F9: n/a | G9: n/a | H9: n/a | I9: n/a | J9: n/a | K9: n/a | L9: n/a | M9: n/a
A10: DeepSeek | B10: Open-weight | C10: ='Revenue Run Rate'!C10/'GW Capacity'!C10 | D10: ='Revenue Run Rate'!D10/'GW Capacity'!D10 | E10: ='Revenue Run Rate'!E10/'GW Capacity'!E10 | F10: ='Revenue Run Rate'!F10/'GW Capacity'!F10 | G10: ='Revenue Run Rate'!G10/'GW Capacity'!G10 | H10: ='Revenue Run Rate'!H10/'GW Capacity'!H10 | I10: ='Revenue Run Rate'!I10/'GW Capacity'!I10 | J10: ='Revenue Run Rate'!J10/'GW Capacity'!J10 | ... M10: ='Revenue Run Rate'!M10/'GW Capacity'!M10
A11: Alibaba (Qwen) | B11: Open-weight | C11: ='Revenue Run Rate'!C11/'GW Capacity'!C11 | D11: ='Revenue Run Rate'!D11/'GW Capacity'!D11 | E11: ='Revenue Run Rate'!E11/'GW Capacity'!E11 | F11: ='Revenue Run Rate'!F11/'GW Capacity'!F11 | G11: ='Revenue Run Rate'!G11/'GW Capacity'!G11 | H11: ='Revenue Run Rate'!H11/'GW Capacity'!H11 | I11: ='Revenue Run Rate'!I11/'GW Capacity'!I11 | J11: ='Revenue Run Rate'!J11/'GW Capacity'!J11 | ... M11: ='Revenue Run Rate'!M11/'GW Capacity'!M11
A12: Mistral AI | B12: Open-weight | C12: ='Revenue Run Rate'!C12/'GW Capacity'!C12 | D12: ='Revenue Run Rate'!D12/'GW Capacity'!D12 | E12: ='Revenue Run Rate'!E12/'GW Capacity'!E12 | F12: ='Revenue Run Rate'!F12/'GW Capacity'!F12 | G12: ='Revenue Run Rate'!G12/'GW Capacity'!G12 | H12: ='Revenue Run Rate'!H12/'GW Capacity'!H12 | I12: ='Revenue Run Rate'!I12/'GW Capacity'!I12 | J12: ='Revenue Run Rate'!J12/'GW Capacity'!J12 | ... M12: ='Revenue Run Rate'!M12/'GW Capacity'!M12
A13: Break-even benchmark (YK Research) | C13: 31 | D13: 31 | E13: 31 | F13: 31 | G13: 31 | H13: 31 | I13: 31 | J13: 31 | K13: 31 | L13: 31 | M13: 31
A15: COST PER GW ($B per GW per year)
A16: Measure | B16: Scope | C16: Q1 2024 | D16: Q2 2024 | E16: Q3 2024 | F16: Q4 2024 | G16: Q1 2025 | H16: Q2 2025 | I16: Q3 2025 | J16: Q4 2025 | K16: Q1 2026 | L16: Q2 2026 | M16: Q3 2026 (part.)
A17: Annualized TCO per GW (Epoch AI) | B17: All labs | C17: ='Compute Cost'!$C$3 | D17: ='Compute Cost'!$C$3 | E17: ='Compute Cost'!$C$3 | F17: ='Compute Cost'!$C$3 | G17: ='Compute Cost'!$C$3 | H17: ='Compute Cost'!$C$3 | I17: ='Compute Cost'!$C$3 | J17: ='Compute Cost'!$C$3 | ... M17: ='Compute Cost'!$C$3
A18: Build capex per GW (industry) | B18: One-time, all-in | C18: 32 | D18: 32 | E18: 33 | F18: 34 | G18: 35 | H18: 36 | I18: 38 | J18: 40.5 | K18: 42 | L18: 45 | M18: 47
A20: Reading: labs above ~$31B/GW of run-rate revenue clear base-case data-center economics. As of Q2 2026, Anthropic (~$26B/GW) and OpenAI (~$22B/GW) approach it; Google's paid AI revenue per GW is lower because much of its fleet serves un-monetized internal surfaces; open-weight labs (Meta, DeepSeek, Qwen, Mistral) monetize only a small share of the tokens their models generate.

Sheet Token Volume
A1: Token Volume
A2: Estimated tokens processed per quarter, TRILLIONS, all surfaces (first-party apps + API + estimable self-hosted). Google derived from disclosed monthly anchors (9.7T May'24 / 480T May'25 / 3,200T May'26). Others estimated - see Methodology.
A4: Lab | B4: Category | C4: Q1 2024 | D4: Q2 2024 | E4: Q3 2024 | F4: Q4 2024 | G4: Q1 2025 | H4: Q2 2025 | I4: Q3 2025 | J4: Q4 2025 | K4: Q1 2026 | L4: Q2 2026 | M4: Q3 2026 (part.)
A5: OpenAI | B5: Frontier (closed) | C5: 80 | D5: 120 | E5: 170 | F5: 260 | G5: 400 | H5: 640 | I5: 1060 | J5: 1650 | K5: 2590 | L5: 3890 | M5: 4950
A6: Anthropic | B6: Frontier (closed) | C6: 15 | D6: 20 | E6: 28 | F6: 37 | G6: 45 | H6: 80 | I6: 130 | J6: 220 | K6: 500 | L6: 1200 | M6: 1700
A7: Google DeepMind | B7: Frontier (closed) | C7: 17 | D7: 30 | E7: 80 | F7: 210 | G7: 560 | H7: 1380 | I7: 2340 | J7: 3800 | K7: 6180 | L7: 10050 | M7: 15300
A8: xAI | B8: Frontier (closed) | C8: 1 | D8: 2 | E8: 3 | F8: 5 | G8: 8 | H8: 15 | I8: 25 | J8: 40 | K8: 60 | L8: 90 | M8: 120
A9: Meta (Llama) | B9: Open-weight | C9: 10 | D9: 20 | E9: 35 | F9: 55 | G9: 80 | H9: 120 | I9: 160 | J9: 210 | K9: 280 | L9: 360 | M9: 430
A10: DeepSeek | B10: Open-weight | C10: 1 | D10: 2 | E10: 4 | F10: 8 | G10: 40 | H10: 80 | I10: 120 | J10: 200 | K10: 350 | L10: 600 | M10: 800
A11: Alibaba (Qwen) | B11: Open-weight | C11: 2 | D11: 4 | E11: 8 | F11: 15 | G11: 30 | H11: 60 | I11: 110 | J11: 180 | K11: 300 | L11: 500 | M11: 700
A12: Mistral AI | B12: Open-weight | C12: 1 | D12: 2 | E12: 3 | F12: 5 | G12: 8 | H12: 12 | I12: 18 | J12: 25 | K12: 35 | L12: 50 | M12: 65
A13: Frontier subtotal | C13: =C5+C6+C7+C8 | D13: =D5+D6+D7+D8 | E13: =E5+E6+E7+E8 | F13: =F5+F6+F7+F8 | G13: =G5+G6+G7+G8 | H13: =H5+H6+H7+H8 | I13: =I5+I6+I7+I8 | J13: =J5+J6+J7+J8 | ... M13: =M5+M6+M7+M8
A14: Open-weight subtotal | C14: =C9+C10+C11+C12 | D14: =D9+D10+D11+D12 | E14: =E9+E10+E11+E12 | F14: =F9+F10+F11+F12 | G14: =G9+G10+G11+G12 | H14: =H9+H10+H11+H12 | I14: =I9+I10+I11+I12 | J14: =J9+J10+J11+J12 | ... M14: =M9+M10+M11+M12
A15: TOTAL (all 8 labs) | C15: =C5+C6+C7+C8+C9+C10+C11+C12 | D15: =D5+D6+D7+D8+D9+D10+D11+D12 | E15: =E5+E6+E7+E8+E9+E10+E11+E12 | F15: =F5+F6+F7+F8+F9+F10+F11+F12 | G15: =G5+G6+G7+G8+G9+G10+G11+G12 | H15: =H5+H6+H7+H8+H9+H10+H11+H12 | I15: =I5+I6+I7+I8+I9+I10+I11+I12 | J15: =J5+J6+J7+J8+J9+J10+J11+J12 | ... M15: =M5+M6+M7+M8+M9+M10+M11+M12
A17: Memo: global inference, all providers (est.) | C17: 30 | D17: 55 | E17: 140 | F17: 380 | G17: 900 | H17: 2000 | I17: 3600 | J17: 5800 | K17: 9200 | L17: 14500 | M17: 21000
A18: Memo: 8-lab share of global (%) | C18: =C15/C17 | D18: =D15/D17 | E18: =E15/E17 | F18: =F15/F17 | G18: =G15/G17 | H18: =H15/H17 | I18: =I15/I17 | J18: =J15/J17 | ... M18: =M15/M17

Sheet Sources & Methodology
A1: Sources & Methodology
A2: All disclosed anchors underpinning the series, then metric-by-metric methodology. Compiled Aug 23, 2026.
A4: Metric | B4: Lab / Scope | C4: Data point | D4: As of | E4: Source | F4: URL
A5: Revenue | B5: Anthropic | C5: Annualized run rate $65B (7x YoY); Q2 2026 revenue $11.5B prelim (14x YoY vs $787M Q2 2025); positive adjusted operating income in Q2 2026 | D5: Jul-Aug 2026 | E5: CNBC / Bloomberg | F5: https://www.cnbc.com/2026/08/17/anthropic-says-annualized-revenue-climbed-to-65-billion-in-july.html
A6: Revenue | B6: Anthropic | C6: Run rate >$47B (May 2026), ~$30B (Apr 2026), >$9B (late 2025); ~$10B revenue for all of 2025 (gross basis) | D6: 2025-2026 | E6: CNBC / Bloomberg / Yahoo Finance | F6: https://finance.yahoo.com/technology/ai/articles/anthropic-revenue-run-rate-surpasses-193745178.html
A7: Revenue | B7: OpenAI | C7: Annualized run rate >$40B (Aug 2026), ~2x from end-2025; monthly run rate +20% in July alone | D7: Aug 2026 | E7: Bloomberg | F7: https://www.bloomberg.com/news/articles/2026-08-13/openai-s-revenue-run-rate-tops-40-billion-ahead-of-ipo
A8: Revenue | B8: OpenAI | C8: 2024 revenue $3.7B; 2025 booked revenue $13.07B (audited, leaked) with $20.9B operating loss; ARR $21.5B end-2025, $25B Q1 2026 ($2B/month); enterprise >40% of revenue Apr 2026 | D8: 2024-2026 | E8: ValueAdd VC / Happycapy compilation of leaked financials | F8: https://valueaddvc.com/blog/openai-revenue-2026-20b-arr-4b-month-path-to-profitability
A9: Revenue | B9: Google DeepMind | C9: AI-attributable revenue est.: ~$5B 2024, ~$15B 2025, ~$28B ARR May 2026 (not an Alphabet reporting segment) | D9: May 2026 | E9: Presenc AI comparison table | F9: https://presenc.ai/research/ai-lab-revenue-and-valuation-2026
A10: Revenue | B10: xAI | C10: Standalone AI revenue ~$100M 2024, ~$350-500M 2025; Q1 2026 reported $818M revenue / $2.47B operating loss; mid-2026 ARR estimates $0.5B (Bloomberg/Sacra) to $1.5B (Presenc); 2026 target $2B | D10: 2024-2026 | E10: ValueAdd VC / Sacra / Presenc AI | F10: https://valueaddvc.com/blog/xai-revenue-how-grok-and-the-api-actually-make-money
A11: Revenue | B11: DeepSeek | C11: Annualized revenue approaching $500M (The Information, mid-2026); ~$700M annualized May 2026 (Presenc est.); ~$200M 2025; 70-80% gross margins at $2.19/M tokens; $52B valuation Jul 2026 | D11: mid-2026 | E11: AI Weekly / Caixin / Presenc AI | F11: https://aiweekly.co/alerts/deepseek-nears-500m-annualized-revenue-plans-2027-ipo
A12: Revenue | B12: Alibaba (Qwen) | C12: AI-related product revenue RMB 12,376M (US$1,824M) quarter ended Jun 30 2026, 12th consecutive quarter of triple-digit YoY growth; AI Cloud & Compute Services $7.1B (+45% YoY); MaaS ARR >RMB 16B | D12: Jun 2026 | E12: Alibaba Group earnings / SEC 6-K exhibit | F12: https://www.sec.gov/Archives/edgar/data/1577552/000110465926099220/tm2623667d1_ex99-1.htm
A13: Revenue | B13: Mistral AI | C13: ARR ~$16-20M end-2024, $312M Dec 2025, $400M Jan 2026, ~$1.0B May 2026; 2026 target $1.1-1.2B | D13: 2024-2026 | E13: Sacra / Klover / Presenc AI | F13: https://sacra.com/c/mistral/
A14: Revenue | B14: Other open-weight labs (context) | C14: May 2026 ARR: Moonshot AI (Kimi) ~$500M, Zhipu/Z.AI (GLM) ~$480M, Cohere ~$500M (not modeled as separate rows) | D14: May 2026 | E14: Presenc AI | F14: https://presenc.ai/research/ai-lab-revenue-and-valuation-2026
A15: GW capacity | B15: OpenAI | C15: Stargate Abilene ~0.3 GW operational mid-2026 (capped at 1.2 GW); 7 sites >9 GW planned ($400B+); 4.5 GW Oracle lease; balance of serving on Azure | D15: mid-2026 | E15: Founder OS / Momoview / TCDEV | F15: https://fos.kentlangley.com/b/ai-lab-compute/
... A36: Context | B36: Valuations | C36: OpenAI $852B (Mar 2026, $122B round); Anthropic $380B Series G (secondaries ~$1T); xAI $230B Series E (SpaceX merger ~$1.25T combined); DeepSeek $52B; Mistral ~$15B | D36: 2026 | E36: Bloomberg / Presenc AI / Caixin | F36: https://presenc.ai/research/ai-lab-revenue-and-valuation-2026
A39: Methodology
A40: GW capacity | C40: Operational IT power (owned + leased) serving each lab at quarter end, in gigawatts. Interpolated between disclosed anchors (cluster energizations, GPU counts converted at ~1.4 kW/H100e all-in). NOT the same as contracted/announced capacity, which is far larger (e.g. OpenAI 9+ GW, Anthropic 8.5+ GW, Meta 14 GW by 2027). Meta's figure covers its whole AI accelerator fleet incl. ranking/recsys, so it is not directly comparable to model-only estimates. Error bars are wide: +/-30% or more.
A41: Quarterly revenue | C41: Booked revenue per calendar quarter, $B. Anthropic Q2 2025/Q2 2026 and Alibaba Q2 2026 are disclosed; OpenAI annual totals (2024: $3.7B, 2025: $13.07B) are disclosed and split across quarters along the run-rate curve; everything else interpolated from disclosed run rates. Alibaba = 'AI-related product revenue' only (excludes broader AI Cloud & Compute). Meta has no separable model revenue (monetizes via ads). Note OpenAI reports net of cloud-partner costs while Anthropic includes gross reseller revenue - not perfectly comparable.
A42: Revenue run rate (ARR) | C42: Annualized revenue run rate at quarter end, $B, as disclosed by companies or estimated. This is the metric labs quote publicly (e.g. Anthropic $65B Jul 2026, OpenAI $40B Aug 2026). Alibaba ARR = quarterly AI-related product revenue x4.
A43: Compute cost | C43: Estimated quarterly compute cost = operational GW x $8.5B/GW/yr annualized TCO (Epoch AI benchmark: 5-yr server / 14-yr facility depreciation + opex) / 4. This proxies economic cost, not cash capex. Reported anchors for calibration: OpenAI ~$17B/yr burn, xAI ~$1B/month, Anthropic adjusted-operating-income positive in Q2 2026. Leased capacity (OpenAI, Anthropic) likely carries a rental premium above this benchmark; efficient self-builds (xAI, DeepSeek) may run below.
A44: Build capex per GW | C44: Industry all-in cost to BUILD 1 GW (facility + power + IT), $B/GW, by dominant GPU generation: Hopper ~$32-35B (2024), Blackwell ~$38-40.5B (2025), Vera Rubin ~$47B (2026). Sources: Epoch AI ($38B GB200-class), Bernstein/Foxconn ($47B Rubin), Turner & Townsend ($45-55B).
A45: Revenue per GW | C45: Annualized run-rate revenue / operational GW, $B per GW per year. Benchmark: a GW must generate ~$31B/yr of inference revenue to clear base-case economics (YK Research). Labs below that line are subsidizing growth with capital; labs near/above it have workable unit economics. Google's low figure partly reflects un-monetized internal usage (Search AI, Workspace).
A46: Cost per GW | C46: Two views: (1) annualized TCO ~$8.5B/GW/yr (same for all labs, Epoch benchmark); (2) build capex per GW time series above. Per-lab true costs vary with chip generation, lease vs own, power strategy, and utilization but are not separately disclosed.
A47: Token volume | C47: Trillions of tokens processed per quarter, all surfaces (first-party apps + API + self-hosted where estimable). Google is derived from three disclosed monthly anchors (9.7T -> 480T -> 3,200T/month) via exponential interpolation. OpenAI from disclosed API tokens/min (6B Oct 2025, 15B Q1 2026) x ~1.8 for first-party ChatGPT traffic. Anthropic/xAI/Mistral estimated from revenue and blended price per token. DeepSeek/Qwen/Meta include self-hosted open-weight usage, which no one measures directly - treat as order-of-magnitude.
A48: Lab selection | C48: Frontier (closed): OpenAI, Anthropic, Google DeepMind, xAI. Open-weight: Meta (Llama), DeepSeek, Alibaba (Qwen), Mistral AI. Other open-weight labs (Moonshot/Kimi ~$500M ARR, Zhipu/Z.AI ~$480M, MiniMax, Xiaomi MiMo ~17.5% of OpenRouter tokens) are material to token share but excluded as rows for lack of capacity/revenue disclosure; see Sources.
A49: General caveats | C49: Compiled Aug 23, 2026 from public reporting, company disclosures, and analyst estimates. Q3 2026 is partial (quarter-to-date run rates annualized/extrapolated). Private-company figures are unaudited and sometimes conflicting across sources (conflicts noted in Sources sheet, e.g. xAI ARR $0.5B vs $1.5B; Anthropic FY2025 ~$4.5B booked vs ~$9-10B gross). All dollar figures nominal USD billions.
