Workbook

Sheet Cover
B2: SpaceX × Cursor
B3: Pro-Forma Three-Statement Model
B6: Transaction: SpaceX acquires Cursor (Anysphere, Inc.) — announced 16-Jun-2026
B7: Consideration: ~US$60bn, 100% SpaceX Class A stock; expected close Q3-2026
B8: Strategic rationale: AI / developer-tools capability following the Feb-2026 xAI combination
B10: Contents:
B11: • Assumptions — all input drivers (blue cells are editable inputs)
B12: • IS SpaceX / IS Cursor — standalone operating builds
B13: • Deal & PPA — purchase price allocation, goodwill, intangibles
B14: • Schedules — PP&E, intangibles/DTL, debt & spectrum, tax/NOL
B15: • Income Statement — pro-forma combined P&L
B16: • Balance Sheet — purchase-accounting bridge + projections
... B24: estimates and reasonable assumptions; not investment advice and not company-verified.

Sheet Assumptions
A1: ASSUMPTIONS & DRIVERS (US$ millions unless noted; blue = input)
C2: 2025A | D2: 2026E | E2: 2027E | F2: 2028E | G2: 2029E | H2: 2030E
A3: SpaceX standalone (consolidated, incl. Starlink, launch, Starshield, xAI)
A4: Revenue, FY2025 actual ($M) | C4: 18674
A5: Revenue growth % | D5: 0.4 | E5: 0.35 | F5: 0.3 | G5: 0.25 | H5: 0.22
A6: COGS % of revenue (ex-D&A) | C6: 0.55 | D6: 0.535 | E6: 0.52 | F6: 0.505 | G6: 0.49 | H6: 0.48
A7: R&D % of revenue | C7: 0.22 | D7: 0.19 | E7: 0.17 | F7: 0.15 | G7: 0.135 | H7: 0.125
A8: SG&A % of revenue | C8: 0.147 | D8: 0.135 | E8: 0.125 | F8: 0.115 | G8: 0.105 | H8: 0.1
A9: Cursor / Anysphere standalone (AI coding platform)
A10: Revenue ($M) | C10: 450 | D10: 3000 | E10: 6500 | F10: 10000 | G10: 13500 | H10: 17000
A11: COGS % of revenue (inference / cloud, ex-D&A) | C11: 0.55 | D11: 0.5 | E11: 0.46 | F11: 0.43 | G11: 0.4 | H11: 0.38
A12: R&D % of revenue | C12: 0.4 | D12: 0.32 | E12: 0.28 | F12: 0.25 | G12: 0.23 | H12: 0.22
A13: Sales & marketing % of revenue | C13: 0.35 | D13: 0.3 | E13: 0.26 | F13: 0.22 | G13: 0.2 | H13: 0.18
A14: G&A % of revenue | C14: 0.15 | D14: 0.13 | E14: 0.11 | F14: 0.1 | G14: 0.09 | H14: 0.08
A15: Pro-forma adjustments (deal effects)
A16: Revenue synergies ($M) | C16: 0 | D16: 50 | E16: 200 | F16: 350 | G16: 450 | H16: 550
A17: Cost synergies ($M) [in-source inference on xAI/Starlink] | C17: 0 | D17: 100 | E17: 350 | F17: 550 | G17: 700 | H17: 850
A18: Integration & one-time deal costs ($M) | C18: 0 | D18: 500 | E18: 0 | F18: 0 | G18: 0 | H18: 0
A19: Capital, financing & other
A20: Capex % of combined revenue | C20: 0.26 | D20: 0.23 | E20: 0.21 | F20: 0.19 | G20: 0.175 | H20: 0.165
A21: Depreciation % of beginning net PP&E | C21: 0.09
A22: Stock-based comp % of revenue | C22: 0.06 | D22: 0.06 | E22: 0.055 | F22: 0.05 | G22: 0.045 | H22: 0.04
A23: Net new long-term debt ($M) | C23: 0 | D23: 2000 | E23: 2000 | F23: 1500 | G23: 1000 | H23: 1000
A24: Spectrum obligation repayment ($M) | C24: 0 | D24: -2000 | E24: -2000 | F24: -2000 | G24: -2000 | H24: -2000
A25: Primary equity issuance / IPO proceeds ($M) | C25: 0 | D25: 50000 | E25: 0 | F25: 0 | G25: 0 | H25: 0 | L25: SpaceX June-2026 IPO
A26: Interest rate on debt & spectrum obligation | C26: 0.065
A27: Interest income rate on cash | C27: 0.04
A28: Statutory tax rate | C28: 0.21
A29: Opening NOL carryforward, FY2025 ($M) | C29: 26000 | L29: SpaceX accumulated + Cursor
A30: NOL usage limit (% of taxable income) | C30: 0.8
A31: SpaceX shares pre-deal (M) | C31: 2000
A32: SpaceX share price, deal pricing ($) | C32: 450
A33: Working capital ratios (% of revenue)
A34: Accounts receivable (% of revenue) | C34: 0.1339
A35: Inventory (% of revenue) | C35: 0.1499
A36: Prepaid & other current assets (% of revenue) | C36: 0.0803
A37: Accounts payable (% of revenue) | C37: 0.1499
A38: Accrued liabilities (% of revenue) | C38: 0.091
A39: Deferred revenue, current (% of revenue) | C39: 0.1499
A40: Customer deposits & advances (% of revenue) | C40: 0.1017

Sheet IS SpaceX
A1: SPACEX STANDALONE — operating build (US$M, ex-D&A cash costs)
C2: 2025A | D2: 2026E | E2: 2027E | F2: 2028E | G2: 2029E | H2: 2030E
A3: Revenue | C3: ='Assumptions'!C4 | D3: ='IS SpaceX'!C3*(1+'Assumptions'!D5) | E3: ='IS SpaceX'!D3*(1+'Assumptions'!E5) | F3: ='IS SpaceX'!E3*(1+'Assumptions'!F5) | G3: ='IS SpaceX'!F3*(1+'Assumptions'!G5) | H3: ='IS SpaceX'!G3*(1+'Assumptions'!H5)
A4: Cost of revenue (ex-D&A) | C4: ='IS SpaceX'!C3*'Assumptions'!C6 | D4: ='IS SpaceX'!D3*'Assumptions'!D6 | E4: ='IS SpaceX'!E3*'Assumptions'!E6 | F4: ='IS SpaceX'!F3*'Assumptions'!F6 | G4: ='IS SpaceX'!G3*'Assumptions'!G6 | H4: ='IS SpaceX'!H3*'Assumptions'!H6
A5: Gross profit (cash) | C5: ='IS SpaceX'!C3-'IS SpaceX'!C4 | D5: ='IS SpaceX'!D3-'IS SpaceX'!D4 | E5: ='IS SpaceX'!E3-'IS SpaceX'!E4 | F5: ='IS SpaceX'!F3-'IS SpaceX'!F4 | G5: ='IS SpaceX'!G3-'IS SpaceX'!G4 | H5: ='IS SpaceX'!H3-'IS SpaceX'!H4
A6: Research & development | C6: ='IS SpaceX'!C3*'Assumptions'!C7 | D6: ='IS SpaceX'!D3*'Assumptions'!D7 | E6: ='IS SpaceX'!E3*'Assumptions'!E7 | F6: ='IS SpaceX'!F3*'Assumptions'!F7 | G6: ='IS SpaceX'!G3*'Assumptions'!G7 | H6: ='IS SpaceX'!H3*'Assumptions'!H7
A7: Selling, general & administrative | C7: ='IS SpaceX'!C3*'Assumptions'!C8 | D7: ='IS SpaceX'!D3*'Assumptions'!D8 | E7: ='IS SpaceX'!E3*'Assumptions'!E8 | F7: ='IS SpaceX'!F3*'Assumptions'!F8 | G7: ='IS SpaceX'!G3*'Assumptions'!G8 | H7: ='IS SpaceX'!H3*'Assumptions'!H8
A8: EBITDA (cash, ex-synergies) | C8: ='IS SpaceX'!C5-'IS SpaceX'!C6-'IS SpaceX'!C7 | D8: ='IS SpaceX'!D5-'IS SpaceX'!D6-'IS SpaceX'!D7 | E8: ='IS SpaceX'!E5-'IS SpaceX'!E6-'IS SpaceX'!E7 | F8: ='IS SpaceX'!F5-'IS SpaceX'!F6-'IS SpaceX'!F7 | G8: ='IS SpaceX'!G5-'IS SpaceX'!G6-'IS SpaceX'!G7 | H8: ='IS SpaceX'!H5-'IS SpaceX'!H6-'IS SpaceX'!H7
A9: EBITDA margin % | C9: ='IS SpaceX'!C8/'IS SpaceX'!C3 | D9: ='IS SpaceX'!D8/'IS SpaceX'!D3 | E9: ='IS SpaceX'!E8/'IS SpaceX'!E3 | F9: ='IS SpaceX'!F8/'IS SpaceX'!F3 | G9: ='IS SpaceX'!G8/'IS SpaceX'!G3 | H9: ='IS SpaceX'!H8/'IS SpaceX'!H3

Sheet IS Cursor
A1: CURSOR (ANYSPHERE) STANDALONE — operating build (US$M, ex-D&A cash costs)
C2: 2025A | D2: 2026E | E2: 2027E | F2: 2028E | G2: 2029E | H2: 2030E
A3: Revenue | C3: ='Assumptions'!C10 | D3: ='Assumptions'!D10 | E3: ='Assumptions'!E10 | F3: ='Assumptions'!F10 | G3: ='Assumptions'!G10 | H3: ='Assumptions'!H10
A4: Cost of revenue (inference/cloud, ex-D&A) | C4: ='IS Cursor'!C3*'Assumptions'!C11 | D4: ='IS Cursor'!D3*'Assumptions'!D11 | E4: ='IS Cursor'!E3*'Assumptions'!E11 | F4: ='IS Cursor'!F3*'Assumptions'!F11 | G4: ='IS Cursor'!G3*'Assumptions'!G11 | H4: ='IS Cursor'!H3*'Assumptions'!H11
A5: Gross profit (cash) | C5: ='IS Cursor'!C3-'IS Cursor'!C4 | D5: ='IS Cursor'!D3-'IS Cursor'!D4 | E5: ='IS Cursor'!E3-'IS Cursor'!E4 | F5: ='IS Cursor'!F3-'IS Cursor'!F4 | G5: ='IS Cursor'!G3-'IS Cursor'!G4 | H5: ='IS Cursor'!H3-'IS Cursor'!H4
A6: Research & development | C6: ='IS Cursor'!C3*'Assumptions'!C12 | D6: ='IS Cursor'!D3*'Assumptions'!D12 | E6: ='IS Cursor'!E3*'Assumptions'!E12 | F6: ='IS Cursor'!F3*'Assumptions'!F12 | G6: ='IS Cursor'!G3*'Assumptions'!G12 | H6: ='IS Cursor'!H3*'Assumptions'!H12
A7: Sales & marketing | C7: ='IS Cursor'!C3*'Assumptions'!C13 | D7: ='IS Cursor'!D3*'Assumptions'!D13 | E7: ='IS Cursor'!E3*'Assumptions'!E13 | F7: ='IS Cursor'!F3*'Assumptions'!F13 | G7: ='IS Cursor'!G3*'Assumptions'!G13 | H7: ='IS Cursor'!H3*'Assumptions'!H13
A8: General & administrative | C8: ='IS Cursor'!C3*'Assumptions'!C14 | D8: ='IS Cursor'!D3*'Assumptions'!D14 | E8: ='IS Cursor'!E3*'Assumptions'!E14 | F8: ='IS Cursor'!F3*'Assumptions'!F14 | G8: ='IS Cursor'!G3*'Assumptions'!G14 | H8: ='IS Cursor'!H3*'Assumptions'!H14
A9: EBITDA (cash) | C9: ='IS Cursor'!C5-'IS Cursor'!C6-'IS Cursor'!C7-'IS Cursor'!C8 | D9: ='IS Cursor'!D5-'IS Cursor'!D6-'IS Cursor'!D7-'IS Cursor'!D8 | E9: ='IS Cursor'!E5-'IS Cursor'!E6-'IS Cursor'!E7-'IS Cursor'!E8 | F9: ='IS Cursor'!F5-'IS Cursor'!F6-'IS Cursor'!F7-'IS Cursor'!F8 | G9: ='IS Cursor'!G5-'IS Cursor'!G6-'IS Cursor'!G7-'IS Cursor'!G8 | H9: ='IS Cursor'!H5-'IS Cursor'!H6-'IS Cursor'!H7-'IS Cursor'!H8
A10: EBITDA margin % | C10: ='IS Cursor'!C9/'IS Cursor'!C3 | D10: ='IS Cursor'!D9/'IS Cursor'!D3 | E10: ='IS Cursor'!E9/'IS Cursor'!E3 | F10: ='IS Cursor'!F9/'IS Cursor'!F3 | G10: ='IS Cursor'!G9/'IS Cursor'!G3 | H10: ='IS Cursor'!H9/'IS Cursor'!H3

Sheet Deal & PPA
A1: DEAL STRUCTURE & PURCHASE PRICE ALLOCATION (US$M)
A2: All-stock acquisition announced 16-Jun-2026; expected close Q3-2026. Modelled as effective 1-Jan-2026 for full-year pro-forma comparability.
A3: Consideration
A4: Equity purchase price (100% stock) | C4: 60000
A5: SpaceX share price at pricing ($) | C5: ='Assumptions'!C32
A6: New SpaceX shares issued (M) | C6: ='Deal & PPA'!C4/'Deal & PPA'!C5
A7: Fair value of identifiable net assets acquired
A8: Cash & equivalents | C8: 3000
A9: Accounts receivable | C9: 250
A10: Prepaid & other current assets | C10: 150
A11: Property & equipment | C11: 300
A12: Less: liabilities assumed | C12: -800
A13: Net tangible assets | C13: ='Deal & PPA'!C8+'Deal & PPA'!C9+'Deal & PPA'!C10+'Deal & PPA'!C11+'Deal & PPA'!C12
A14: Identifiable intangible assets
A15: Developed technology (IDE + agent models) | C15: 8000
A16: Useful life (yrs) | C16: 8
A17: Customer relationships (enterprise contracts) | C17: 5000
A18: Useful life (yrs) | C18: 10
A19: Trade name (Cursor) | C19: 2000
A20: Useful life (yrs) | C20: 15
A21: Total identifiable intangibles | C21: ='Deal & PPA'!C15+'Deal & PPA'!C17+'Deal & PPA'!C19
A22: Annual intangible amortization | C22: ='Deal & PPA'!C15/'Deal & PPA'!C16+'Deal & PPA'!C17/'Deal & PPA'!C18+'Deal & PPA'!C19/'Deal & PPA'!C20
A23: Goodwill & deferred tax
A24: Deferred tax liability on intangibles | C24: ='Assumptions'!C28*'Deal & PPA'!C21
A25: FV of identifiable net assets (incl. intangibles, net of DTL) | C25: ='Deal & PPA'!C13+'Deal & PPA'!C21-'Deal & PPA'!C24
A26: Goodwill | C26: ='Deal & PPA'!C4-'Deal & PPA'!C25

Sheet Schedules
A1: SUPPORTING SCHEDULES (US$M)
C2: 2025A | D2: 2026E | E2: 2027E | F2: 2028E | G2: 2029E | H2: 2030E
A3: Property, plant & equipment
A4: Beginning net PP&E | C4: 46000 | D4: ='Balance Sheet'!F9 | E4: ='Schedules'!D7 | F4: ='Schedules'!E7 | G4: ='Schedules'!F7 | H4: ='Schedules'!G7
A5: Capital expenditures | C5: ='Assumptions'!C20*'Income Statement'!C7 | D5: ='Assumptions'!D20*'Income Statement'!D7 | E5: ='Assumptions'!E20*'Income Statement'!E7 | F5: ='Assumptions'!F20*'Income Statement'!F7 | G5: ='Assumptions'!G20*'Income Statement'!G7 | H5: ='Assumptions'!H20*'Income Statement'!H7
A6: Depreciation | C6: ='Schedules'!C4*'Assumptions'!C21 | D6: ='Schedules'!D4*'Assumptions'!C21 | E6: ='Schedules'!E4*'Assumptions'!C21 | F6: ='Schedules'!F4*'Assumptions'!C21 | G6: ='Schedules'!G4*'Assumptions'!C21 | H6: ='Schedules'!H4*'Assumptions'!C21
A7: Ending net PP&E | C7: 46000 | D7: ='Schedules'!D4+'Schedules'!D5-'Schedules'!D6 | E7: ='Schedules'!E4+'Schedules'!E5-'Schedules'!E6 | F7: ='Schedules'!F4+'Schedules'!F5-'Schedules'!F6 | G7: ='Schedules'!G4+'Schedules'!G5-'Schedules'!G6 | H7: ='Schedules'!H4+'Schedules'!H5-'Schedules'!H6
A8: Acquired intangibles & deferred tax
A9: Beginning intangibles, net | C9: 0 | D9: ='Deal & PPA'!C21 | E9: ='Schedules'!D11 | F9: ='Schedules'!E11 | G9: ='Schedules'!F11 | H9: ='Schedules'!G11
A10: Amortization | C10: 0 | D10: =MIN('Schedules'!D9,'Deal & PPA'!C22) | E10: =MIN('Schedules'!E9,'Deal & PPA'!C22) | F10: =MIN('Schedules'!F9,'Deal & PPA'!C22) | G10: =MIN('Schedules'!G9,'Deal & PPA'!C22) | H10: =MIN('Schedules'!H9,'Deal & PPA'!C22)
A11: Ending intangibles, net | C11: 0 | D11: ='Schedules'!D9-'Schedules'!D10 | E11: ='Schedules'!E9-'Schedules'!E10 | F11: ='Schedules'!F9-'Schedules'!F10 | G11: ='Schedules'!G9-'Schedules'!G10 | H11: ='Schedules'!H9-'Schedules'!H10
A12: Beginning deferred tax liability | C12: 0 | D12: ='Deal & PPA'!C24 | E12: ='Schedules'!D14 | F12: ='Schedules'!E14 | G12: ='Schedules'!F14 | H12: ='Schedules'!G14
A13: Change in DTL (deferred tax benefit) | C13: 0 | D13: =-'Assumptions'!C28*'Schedules'!D10 | E13: =-'Assumptions'!C28*'Schedules'!E10 | F13: =-'Assumptions'!C28*'Schedules'!F10 | G13: =-'Assumptions'!C28*'Schedules'!G10 | H13: =-'Assumptions'!C28*'Schedules'!H10
A14: Ending deferred tax liability | C14: 0 | D14: ='Schedules'!D12+'Schedules'!D13 | E14: ='Schedules'!E12+'Schedules'!E13 | F14: ='Schedules'!F12+'Schedules'!F13 | G14: ='Schedules'!G12+'Schedules'!G13 | H14: ='Schedules'!H12+'Schedules'!H13
A15: Debt & spectrum obligation
A16: Beginning long-term debt | C16: 12000 | D16: ='Balance Sheet'!F21 | E16: ='Schedules'!D18 | F16: ='Schedules'!E18 | G16: ='Schedules'!F18 | H16: ='Schedules'!G18
A17: Net draws / (repayments) | C17: 0 | D17: ='Assumptions'!D23 | E17: ='Assumptions'!E23 | F17: ='Assumptions'!F23 | G17: ='Assumptions'!G23 | H17: ='Assumptions'!H23
A18: Ending long-term debt | C18: 12000 | D18: ='Schedules'!D16+'Schedules'!D17 | E18: ='Schedules'!E16+'Schedules'!E17 | F18: ='Schedules'!F16+'Schedules'!F17 | G18: ='Schedules'!G16+'Schedules'!G17 | H18: ='Schedules'!H16+'Schedules'!H17
A19: Beginning spectrum obligation | C19: 19600 | D19: ='Balance Sheet'!F22 | E19: ='Schedules'!D21 | F19: ='Schedules'!E21 | G19: ='Schedules'!F21 | H19: ='Schedules'!G21
A20: Repayments | C20: 0 | D20: ='Assumptions'!D24 | E20: ='Assumptions'!E24 | F20: ='Assumptions'!F24 | G20: ='Assumptions'!G24 | H20: ='Assumptions'!H24
A21: Ending spectrum obligation | C21: 19600 | D21: ='Schedules'!D19+'Schedules'!D20 | E21: ='Schedules'!E19+'Schedules'!E20 | F21: ='Schedules'!F19+'Schedules'!F20 | G21: ='Schedules'!G19+'Schedules'!G20 | H21: ='Schedules'!H19+'Schedules'!H20
A22: Interest expense (on beginning balances) | C22: =('Schedules'!C16+'Schedules'!C19)*'Assumptions'!C26 | D22: =('Schedules'!D16+'Schedules'!D19)*'Assumptions'!C26 | E22: =('Schedules'!E16+'Schedules'!E19)*'Assumptions'!C26 | F22: =('Schedules'!F16+'Schedules'!F19)*'Assumptions'!C26 | G22: =('Schedules'!G16+'Schedules'!G19)*'Assumptions'!C26 | H22: =('Schedules'!H16+'Schedules'!H19)*'Assumptions'!C26
A23: Tax & NOL carryforward
A24: Pre-tax income (from IS) | C24: ='Income Statement'!C22 | D24: ='Income Statement'!D22 | E24: ='Income Statement'!E22 | F24: ='Income Statement'!F22 | G24: ='Income Statement'!G22 | H24: ='Income Statement'!H22
A25: Taxable income (add back non-deductible amort) | C25: ='Schedules'!C24+'Schedules'!C10 | D25: ='Schedules'!D24+'Schedules'!D10 | E25: ='Schedules'!E24+'Schedules'!E10 | F25: ='Schedules'!F24+'Schedules'!F10 | G25: ='Schedules'!G24+'Schedules'!G10 | H25: ='Schedules'!H24+'Schedules'!H10
A26: Beginning NOL balance | C26: ='Assumptions'!C29 | D26: ='Schedules'!C29 | E26: ='Schedules'!D29 | F26: ='Schedules'!E29 | G26: ='Schedules'!F29 | H26: ='Schedules'!G29
A27: NOL utilised | C27: =MIN('Schedules'!C26,'Assumptions'!C30*MAX(0,'Schedules'!C25)) | D27: =MIN('Schedules'!D26,'Assumptions'!C30*MAX(0,'Schedules'!D25)) | E27: =MIN('Schedules'!E26,'Assumptions'!C30*MAX(0,'Schedules'!E25)) | F27: =MIN('Schedules'!F26,'Assumptions'!C30*MAX(0,'Schedules'!F25)) | G27: =MIN('Schedules'!G26,'Assumptions'!C30*MAX(0,'Schedules'!G25)) | H27: =MIN('Schedules'!H26,'Assumptions'!C30*MAX(0,'Schedules'!H25))
A28: NOL generated | C28: =MAX(0,-'Schedules'!C25) | D28: =MAX(0,-'Schedules'!D25) | E28: =MAX(0,-'Schedules'!E25) | F28: =MAX(0,-'Schedules'!F25) | G28: =MAX(0,-'Schedules'!G25) | H28: =MAX(0,-'Schedules'!H25)
A29: Ending NOL balance | C29: ='Schedules'!C26-'Schedules'!C27+'Schedules'!C28 | D29: ='Schedules'!D26-'Schedules'!D27+'Schedules'!D28 | E29: ='Schedules'!E26-'Schedules'!E27+'Schedules'!E28 | F29: ='Schedules'!F26-'Schedules'!F27+'Schedules'!F28 | G29: ='Schedules'!G26-'Schedules'!G27+'Schedules'!G28 | H29: ='Schedules'!H26-'Schedules'!H27+'Schedules'!H28
A30: Current income tax | C30: ='Assumptions'!C28*MAX(0,'Schedules'!C25-'Schedules'!C27) | D30: ='Assumptions'!C28*MAX(0,'Schedules'!D25-'Schedules'!D27) | E30: ='Assumptions'!C28*MAX(0,'Schedules'!E25-'Schedules'!E27) | F30: ='Assumptions'!C28*MAX(0,'Schedules'!F25-'Schedules'!F27) | G30: ='Assumptions'!C28*MAX(0,'Schedules'!G25-'Schedules'!G27) | H30: ='Assumptions'!C28*MAX(0,'Schedules'!H25-'Schedules'!H27)

Sheet Income Statement
A1: PRO-FORMA COMBINED INCOME STATEMENT (US$M)
A2: FY2025 shown pro-forma for comparability; deal effective 1-Jan-2026 in the model.
C3: 2025A | D3: 2026E | E3: 2027E | F3: 2028E | G3: 2029E | H3: 2030E
A4: Revenue — SpaceX | C4: ='IS SpaceX'!C3 | D4: ='IS SpaceX'!D3 | E4: ='IS SpaceX'!E3 | F4: ='IS SpaceX'!F3 | G4: ='IS SpaceX'!G3 | H4: ='IS SpaceX'!H3
A5: Revenue — Cursor | C5: ='IS Cursor'!C3 | D5: ='IS Cursor'!D3 | E5: ='IS Cursor'!E3 | F5: ='IS Cursor'!F3 | G5: ='IS Cursor'!G3 | H5: ='IS Cursor'!H3
A6: Revenue synergies | C6: ='Assumptions'!C16 | D6: ='Assumptions'!D16 | E6: ='Assumptions'!E16 | F6: ='Assumptions'!F16 | G6: ='Assumptions'!G16 | H6: ='Assumptions'!H16
A7: Total revenue | C7: ='Income Statement'!C4+'Income Statement'!C5+'Income Statement'!C6 | D7: ='Income Statement'!D4+'Income Statement'!D5+'Income Statement'!D6 | E7: ='Income Statement'!E4+'Income Statement'!E5+'Income Statement'!E6 | F7: ='Income Statement'!F4+'Income Statement'!F5+'Income Statement'!F6 | G7: ='Income Statement'!G4+'Income Statement'!G5+'Income Statement'!G6 | H7: ='Income Statement'!H4+'Income Statement'!H5+'Income Statement'!H6
A8: Cost of revenue (net of cost synergies) | C8: ='IS SpaceX'!C4+'IS Cursor'!C4-'Assumptions'!C17 | D8: ='IS SpaceX'!D4+'IS Cursor'!D4-'Assumptions'!D17 | E8: ='IS SpaceX'!E4+'IS Cursor'!E4-'Assumptions'!E17 | F8: ='IS SpaceX'!F4+'IS Cursor'!F4-'Assumptions'!F17 | G8: ='IS SpaceX'!G4+'IS Cursor'!G4-'Assumptions'!G17 | H8: ='IS SpaceX'!H4+'IS Cursor'!H4-'Assumptions'!H17
A9: Gross profit | C9: ='Income Statement'!C7-'Income Statement'!C8 | D9: ='Income Statement'!D7-'Income Statement'!D8 | E9: ='Income Statement'!E7-'Income Statement'!E8 | F9: ='Income Statement'!F7-'Income Statement'!F8 | G9: ='Income Statement'!G7-'Income Statement'!G8 | H9: ='Income Statement'!H7-'Income Statement'!H8
A10: Gross margin % | C10: ='Income Statement'!C9/'Income Statement'!C7 | D10: ='Income Statement'!D9/'Income Statement'!D7 | E10: ='Income Statement'!E9/'Income Statement'!E7 | F10: ='Income Statement'!F9/'Income Statement'!F7 | G10: ='Income Statement'!G9/'Income Statement'!G7 | H10: ='Income Statement'!H9/'Income Statement'!H7
A11: Research & development | C11: ='IS SpaceX'!C6+'IS Cursor'!C6 | D11: ='IS SpaceX'!D6+'IS Cursor'!D6 | E11: ='IS SpaceX'!E6+'IS Cursor'!E6 | F11: ='IS SpaceX'!F6+'IS Cursor'!F6 | G11: ='IS SpaceX'!G6+'IS Cursor'!G6 | H11: ='IS SpaceX'!H6+'IS Cursor'!H6
A12: Selling, general & administrative | C12: ='IS SpaceX'!C7+'IS Cursor'!C7+'IS Cursor'!C8 | D12: ='IS SpaceX'!D7+'IS Cursor'!D7+'IS Cursor'!D8 | E12: ='IS SpaceX'!E7+'IS Cursor'!E7+'IS Cursor'!E8 | F12: ='IS SpaceX'!F7+'IS Cursor'!F7+'IS Cursor'!F8 | G12: ='IS SpaceX'!G7+'IS Cursor'!G7+'IS Cursor'!G8 | H12: ='IS SpaceX'!H7+'IS Cursor'!H7+'IS Cursor'!H8
A13: Integration & one-time deal costs | C13: ='Assumptions'!C18 | D13: ='Assumptions'!D18 | E13: ='Assumptions'!E18 | F13: ='Assumptions'!F18 | G13: ='Assumptions'!G18 | H13: ='Assumptions'!H18
A14: EBITDA | C14: ='Income Statement'!C9-'Income Statement'!C11-'Income Statement'!C12-'Income Statement'!C13 | D14: ='Income Statement'!D9-'Income Statement'!D11-'Income Statement'!D12-'Income Statement'!D13 | E14: ='Income Statement'!E9-'Income Statement'!E11-'Income Statement'!E12-'Income Statement'!E13 | F14: ='Income Statement'!F9-'Income Statement'!F11-'Income Statement'!F12-'Income Statement'!F13 | G14: ='Income Statement'!G9-'Income Statement'!G11-'Income Statement'!G12-'Income Statement'!G13 | H14: ='Income Statement'!H9-'Income Statement'!H11-'Income Statement'!H12-'Income Statement'!H13
A15: EBITDA margin % | C15: ='Income Statement'!C14/'Income Statement'!C7 | D15: ='Income Statement'!D14/'Income Statement'!D7 | E15: ='Income Statement'!E14/'Income Statement'!E7 | F15: ='Income Statement'!F14/'Income Statement'!F7 | G15: ='Income Statement'!G14/'Income Statement'!G7 | H15: ='Income Statement'!H14/'Income Statement'!H7
A16: Depreciation | C16: ='Schedules'!C6 | D16: ='Schedules'!D6 | E16: ='Schedules'!E6 | F16: ='Schedules'!F6 | G16: ='Schedules'!G6 | H16: ='Schedules'!H6
A17: Amortization of acquired intangibles | C17: ='Schedules'!C10 | D17: ='Schedules'!D10 | E17: ='Schedules'!E10 | F17: ='Schedules'!F10 | G17: ='Schedules'!G10 | H17: ='Schedules'!H10
A18: EBIT (operating income) | C18: ='Income Statement'!C14-'Income Statement'!C16-'Income Statement'!C17 | D18: ='Income Statement'!D14-'Income Statement'!D16-'Income Statement'!D17 | E18: ='Income Statement'!E14-'Income Statement'!E16-'Income Statement'!E17 | F18: ='Income Statement'!F14-'Income Statement'!F16-'Income Statement'!F17 | G18: ='Income Statement'!G14-'Income Statement'!G16-'Income Statement'!G17 | H18: ='Income Statement'!H14-'Income Statement'!H16-'Income Statement'!H17
A19: Operating margin % | C19: ='Income Statement'!C18/'Income Statement'!C7 | D19: ='Income Statement'!D18/'Income Statement'!D7 | E19: ='Income Statement'!E18/'Income Statement'!E7 | F19: ='Income Statement'!F18/'Income Statement'!F7 | G19: ='Income Statement'!G18/'Income Statement'!G7 | H19: ='Income Statement'!H18/'Income Statement'!H7
A20: Interest expense | C20: =-'Schedules'!C22 | D20: =-'Schedules'!D22 | E20: =-'Schedules'!E22 | F20: =-'Schedules'!F22 | G20: =-'Schedules'!G22 | H20: =-'Schedules'!H22
A21: Interest income | C21: =12000*'Assumptions'!C27 | D21: ='Balance Sheet'!F4*'Assumptions'!C27 | E21: ='Balance Sheet'!G4*'Assumptions'!C27 | F21: ='Balance Sheet'!H4*'Assumptions'!C27 | G21: ='Balance Sheet'!I4*'Assumptions'!C27 | H21: ='Balance Sheet'!J4*'Assumptions'!C27
A22: Pre-tax income (loss) | C22: ='Income Statement'!C18+'Income Statement'!C20+'Income Statement'!C21 | D22: ='Income Statement'!D18+'Income Statement'!D20+'Income Statement'!D21 | E22: ='Income Statement'!E18+'Income Statement'!E20+'Income Statement'!E21 | F22: ='Income Statement'!F18+'Income Statement'!F20+'Income Statement'!F21 | G22: ='Income Statement'!G18+'Income Statement'!G20+'Income Statement'!G21 | H22: ='Income Statement'!H18+'Income Statement'!H20+'Income Statement'!H21
A23: Current income tax | C23: =-'Schedules'!C30 | D23: =-'Schedules'!D30 | E23: =-'Schedules'!E30 | F23: =-'Schedules'!F30 | G23: =-'Schedules'!G30 | H23: =-'Schedules'!H30
A24: Deferred income tax (benefit) | C24: =-'Schedules'!C13 | D24: =-'Schedules'!D13 | E24: =-'Schedules'!E13 | F24: =-'Schedules'!F13 | G24: =-'Schedules'!G13 | H24: =-'Schedules'!H13
A25: Net income (loss) | C25: ='Income Statement'!C22+'Income Statement'!C23+'Income Statement'!C24 | D25: ='Income Statement'!D22+'Income Statement'!D23+'Income Statement'!D24 | E25: ='Income Statement'!E22+'Income Statement'!E23+'Income Statement'!E24 | F25: ='Income Statement'!F22+'Income Statement'!F23+'Income Statement'!F24 | G25: ='Income Statement'!G22+'Income Statement'!G23+'Income Statement'!G24 | H25: ='Income Statement'!H22+'Income Statement'!H23+'Income Statement'!H24
A26: Net margin % | C26: ='Income Statement'!C25/'Income Statement'!C7 | D26: ='Income Statement'!D25/'Income Statement'!D7 | E26: ='Income Statement'!E25/'Income Statement'!E7 | F26: ='Income Statement'!F25/'Income Statement'!F7 | G26: ='Income Statement'!G25/'Income Statement'!G7 | H26: ='Income Statement'!H25/'Income Statement'!H7
A27: Diluted shares outstanding (M) | C27: ='Assumptions'!C31+'Deal & PPA'!C6 | D27: ='Assumptions'!C31+'Deal & PPA'!C6 | E27: ='Assumptions'!C31+'Deal & PPA'!C6 | F27: ='Assumptions'!C31+'Deal & PPA'!C6 | G27: ='Assumptions'!C31+'Deal & PPA'!C6 | H27: ='Assumptions'!C31+'Deal & PPA'!C6
A28: Diluted EPS ($) | C28: ='Income Statement'!C25/'Income Statement'!C27 | D28: ='Income Statement'!D25/'Income Statement'!D27 | E28: ='Income Statement'!E25/'Income Statement'!E27 | F28: ='Income Statement'!F25/'Income Statement'!F27 | G28: ='Income Statement'!G25/'Income Statement'!G27 | H28: ='Income Statement'!H25/'Income Statement'!H27

Sheet Balance Sheet
A1: PRO-FORMA COMBINED BALANCE SHEET (US$M)
C2: SpaceX 2025A | D2: + Cursor | E2: + Purch. acctg | F2: PF Open 1/1/26 | G2: 2026E | H2: 2027E | I2: 2028E | J2: 2029E | K2: 2030E
A3: ASSETS
A4: Cash, equivalents & ST investments | C4: 12000 | D4: 3000 | E4: 0 | F4: ='Balance Sheet'!C4+'Balance Sheet'!D4+'Balance Sheet'!E4 | G4: ='Cash Flow'!D29 | H4: ='Cash Flow'!E29 | I4: ='Cash Flow'!F29 | J4: ='Cash Flow'!G29 | K4: ='Cash Flow'!H29
A5: Accounts receivable | C5: 2500 | D5: 250 | E5: 0 | F5: ='Balance Sheet'!C5+'Balance Sheet'!D5+'Balance Sheet'!E5 | G5: ='Income Statement'!D7*'Assumptions'!C34 | H5: ='Income Statement'!E7*'Assumptions'!C34 | I5: ='Income Statement'!F7*'Assumptions'!C34 | J5: ='Income Statement'!G7*'Assumptions'!C34 | K5: ='Income Statement'!H7*'Assumptions'!C34
A6: Inventory | C6: 2800 | D6: 0 | E6: 0 | F6: ='Balance Sheet'!C6+'Balance Sheet'!D6+'Balance Sheet'!E6 | G6: ='Income Statement'!D7*'Assumptions'!C35 | H6: ='Income Statement'!E7*'Assumptions'!C35 | I6: ='Income Statement'!F7*'Assumptions'!C35 | J6: ='Income Statement'!G7*'Assumptions'!C35 | K6: ='Income Statement'!H7*'Assumptions'!C35
A7: Prepaid & other current assets | C7: 1500 | D7: 150 | E7: 0 | F7: ='Balance Sheet'!C7+'Balance Sheet'!D7+'Balance Sheet'!E7 | G7: ='Income Statement'!D7*'Assumptions'!C36 | H7: ='Income Statement'!E7*'Assumptions'!C36 | I7: ='Income Statement'!F7*'Assumptions'!C36 | J7: ='Income Statement'!G7*'Assumptions'!C36 | K7: ='Income Statement'!H7*'Assumptions'!C36
A8: Total current assets | C8: ='Balance Sheet'!C4+'Balance Sheet'!C5+'Balance Sheet'!C6+'Balance Sheet'!C7 | D8: ='Balance Sheet'!D4+'Balance Sheet'!D5+'Balance Sheet'!D6+'Balance Sheet'!D7 | E8: ='Balance Sheet'!E4+'Balance Sheet'!E5+'Balance Sheet'!E6+'Balance Sheet'!E7 | F8: ='Balance Sheet'!F4+'Balance Sheet'!F5+'Balance Sheet'!F6+'Balance Sheet'!F7 | G8: ='Balance Sheet'!G4+'Balance Sheet'!G5+'Balance Sheet'!G6+'Balance Sheet'!G7 | H8: ='Balance Sheet'!H4+'Balance Sheet'!H5+'Balance Sheet'!H6+'Balance Sheet'!H7 | I8: ='Balance Sheet'!I4+'Balance Sheet'!I5+'Balance Sheet'!I6+'Balance Sheet'!I7 | J8: ='Balance Sheet'!J4+'Balance Sheet'!J5+'Balance Sheet'!J6+'Balance Sheet'!J7 | K8: ='Balance Sheet'!K4+'Balance Sheet'!K5+'Balance Sheet'!K6+'Balance Sheet'!K7
A9: Property & equipment, net | C9: 46000 | D9: 300 | E9: 0 | F9: ='Balance Sheet'!C9+'Balance Sheet'!D9+'Balance Sheet'!E9 | G9: ='Schedules'!D7 | H9: ='Schedules'!E7 | I9: ='Schedules'!F7 | J9: ='Schedules'!G7 | K9: ='Schedules'!H7
A10: Acquired intangibles, net | C10: 0 | D10: 0 | E10: ='Deal & PPA'!C21 | F10: ='Balance Sheet'!C10+'Balance Sheet'!D10+'Balance Sheet'!E10 | G10: ='Schedules'!D11 | H10: ='Schedules'!E11 | I10: ='Schedules'!F11 | J10: ='Schedules'!G11 | K10: ='Schedules'!H11
A11: Goodwill | C11: 0 | D11: 0 | E11: ='Deal & PPA'!C26 | F11: ='Balance Sheet'!C11+'Balance Sheet'!D11+'Balance Sheet'!E11 | G11: ='Balance Sheet'!F11 | H11: ='Balance Sheet'!G11 | I11: ='Balance Sheet'!H11 | J11: ='Balance Sheet'!I11 | K11: ='Balance Sheet'!J11
A12: Spectrum & other intangibles | C12: 19600 | D12: 0 | E12: 0 | F12: ='Balance Sheet'!C12+'Balance Sheet'!D12+'Balance Sheet'!E12 | G12: ='Balance Sheet'!F12 | H12: ='Balance Sheet'!G12 | I12: ='Balance Sheet'!H12 | J12: ='Balance Sheet'!I12 | K12: ='Balance Sheet'!J12
A13: Other long-term assets | C13: 7700 | D13: 0 | E13: 0 | F13: ='Balance Sheet'!C13+'Balance Sheet'!D13+'Balance Sheet'!E13 | G13: ='Balance Sheet'!F13 | H13: ='Balance Sheet'!G13 | I13: ='Balance Sheet'!H13 | J13: ='Balance Sheet'!I13 | K13: ='Balance Sheet'!J13
A14: TOTAL ASSETS | C14: ='Balance Sheet'!C8+'Balance Sheet'!C9+'Balance Sheet'!C10+'Balance Sheet'!C11+'Balance Sheet'!C12+'Balance Sheet'!C13 | D14: ='Balance Sheet'!D8+'Balance Sheet'!D9+'Balance Sheet'!D10+'Balance Sheet'!D11+'Balance Sheet'!D12+'Balance Sheet'!D13 | E14: ='Balance Sheet'!E8+'Balance Sheet'!E9+'Balance Sheet'!E10+'Balance Sheet'!E11+'Balance Sheet'!E12+'Balance Sheet'!E13 | F14: ='Balance Sheet'!F8+'Balance Sheet'!F9+'Balance Sheet'!F10+'Balance Sheet'!F11+'Balance Sheet'!F12+'Balance Sheet'!F13 | G14: ='Balance Sheet'!G8+'Balance Sheet'!G9+'Balance Sheet'!G10+'Balance Sheet'!G11+'Balance Sheet'!G12+'Balance Sheet'!G13 | H14: ='Balance Sheet'!H8+'Balance Sheet'!H9+'Balance Sheet'!H10+'Balance Sheet'!H11+'Balance Sheet'!H12+'Balance Sheet'!H13 | I14: ='Balance Sheet'!I8+'Balance Sheet'!I9+'Balance Sheet'!I10+'Balance Sheet'!I11+'Balance Sheet'!I12+'Balance Sheet'!I13 | J14: ='Balance Sheet'!J8+'Balance Sheet'!J9+'Balance Sheet'!J10+'Balance Sheet'!J11+'Balance Sheet'!J12+'Balance Sheet'!J13 | K14: ='Balance Sheet'!K8+'Balance Sheet'!K9+'Balance Sheet'!K10+'Balance Sheet'!K11+'Balance Sheet'!K12+'Balance Sheet'!K13
A15: LIABILITIES
A16: Accounts payable | C16: 2800 | D16: 150 | E16: 0 | F16: ='Balance Sheet'!C16+'Balance Sheet'!D16+'Balance Sheet'!E16 | G16: ='Income Statement'!D7*'Assumptions'!C37 | H16: ='Income Statement'!E7*'Assumptions'!C37 | I16: ='Income Statement'!F7*'Assumptions'!C37 | J16: ='Income Statement'!G7*'Assumptions'!C37 | K16: ='Income Statement'!H7*'Assumptions'!C37
A17: Accrued liabilities | C17: 1700 | D17: 150 | E17: 0 | F17: ='Balance Sheet'!C17+'Balance Sheet'!D17+'Balance Sheet'!E17 | G17: ='Income Statement'!D7*'Assumptions'!C38 | H17: ='Income Statement'!E7*'Assumptions'!C38 | I17: ='Income Statement'!F7*'Assumptions'!C38 | J17: ='Income Statement'!G7*'Assumptions'!C38 | K17: ='Income Statement'!H7*'Assumptions'!C38
A18: Deferred revenue, current | C18: 2800 | D18: 300 | E18: 0 | F18: ='Balance Sheet'!C18+'Balance Sheet'!D18+'Balance Sheet'!E18 | G18: ='Income Statement'!D7*'Assumptions'!C39 | H18: ='Income Statement'!E7*'Assumptions'!C39 | I18: ='Income Statement'!F7*'Assumptions'!C39 | J18: ='Income Statement'!G7*'Assumptions'!C39 | K18: ='Income Statement'!H7*'Assumptions'!C39
A19: Customer deposits & advances | C19: 1900 | D19: 0 | E19: 0 | F19: ='Balance Sheet'!C19+'Balance Sheet'!D19+'Balance Sheet'!E19 | G19: ='Income Statement'!D7*'Assumptions'!C40 | H19: ='Income Statement'!E7*'Assumptions'!C40 | I19: ='Income Statement'!F7*'Assumptions'!C40 | J19: ='Income Statement'!G7*'Assumptions'!C40 | K19: ='Income Statement'!H7*'Assumptions'!C40
A20: Total current liabilities | C20: ='Balance Sheet'!C16+'Balance Sheet'!C17+'Balance Sheet'!C18+'Balance Sheet'!C19 | D20: ='Balance Sheet'!D16+'Balance Sheet'!D17+'Balance Sheet'!D18+'Balance Sheet'!D19 | E20: ='Balance Sheet'!E16+'Balance Sheet'!E17+'Balance Sheet'!E18+'Balance Sheet'!E19 | F20: ='Balance Sheet'!F16+'Balance Sheet'!F17+'Balance Sheet'!F18+'Balance Sheet'!F19 | G20: ='Balance Sheet'!G16+'Balance Sheet'!G17+'Balance Sheet'!G18+'Balance Sheet'!G19 | H20: ='Balance Sheet'!H16+'Balance Sheet'!H17+'Balance Sheet'!H18+'Balance Sheet'!H19 | I20: ='Balance Sheet'!I16+'Balance Sheet'!I17+'Balance Sheet'!I18+'Balance Sheet'!I19 | J20: ='Balance Sheet'!J16+'Balance Sheet'!J17+'Balance Sheet'!J18+'Balance Sheet'!J19 | K20: ='Balance Sheet'!K16+'Balance Sheet'!K17+'Balance Sheet'!K18+'Balance Sheet'!K19
A21: Long-term debt | C21: 12000 | D21: 0 | E21: 0 | F21: ='Balance Sheet'!C21+'Balance Sheet'!D21+'Balance Sheet'!E21 | G21: ='Schedules'!D18 | H21: ='Schedules'!E18 | I21: ='Schedules'!F18 | J21: ='Schedules'!G18 | K21: ='Schedules'!H18
A22: Spectrum acquisition obligation | C22: 19600 | D22: 0 | E22: 0 | F22: ='Balance Sheet'!C22+'Balance Sheet'!D22+'Balance Sheet'!E22 | G22: ='Schedules'!D21 | H22: ='Schedules'!E21 | I22: ='Schedules'!F21 | J22: ='Schedules'!G21 | K22: ='Schedules'!H21
A23: LT deferred revenue & deposits | C23: 28000 | D23: 200 | E23: 0 | F23: ='Balance Sheet'!C23+'Balance Sheet'!D23+'Balance Sheet'!E23 | G23: ='Balance Sheet'!F23 | H23: ='Balance Sheet'!G23 | I23: ='Balance Sheet'!H23 | J23: ='Balance Sheet'!I23 | K23: ='Balance Sheet'!J23
A24: Deferred tax liability | C24: 0 | D24: 0 | E24: ='Deal & PPA'!C24 | F24: ='Balance Sheet'!C24+'Balance Sheet'!D24+'Balance Sheet'!E24 | G24: ='Schedules'!D14 | H24: ='Schedules'!E14 | I24: ='Schedules'!F14 | J24: ='Schedules'!G14 | K24: ='Schedules'!H14
A25: Other long-term liabilities | C25: 20700 | D25: 0 | E25: 0 | F25: ='Balance Sheet'!C25+'Balance Sheet'!D25+'Balance Sheet'!E25 | G25: ='Balance Sheet'!F25 | H25: ='Balance Sheet'!G25 | I25: ='Balance Sheet'!H25 | J25: ='Balance Sheet'!I25 | K25: ='Balance Sheet'!J25
A26: TOTAL LIABILITIES | C26: ='Balance Sheet'!C20+'Balance Sheet'!C21+'Balance Sheet'!C22+'Balance Sheet'!C23+'Balance Sheet'!C24+'Balance Sheet'!C25 | D26: ='Balance Sheet'!D20+'Balance Sheet'!D21+'Balance Sheet'!D22+'Balance Sheet'!D23+'Balance Sheet'!D24+'Balance Sheet'!D25 | E26: ='Balance Sheet'!E20+'Balance Sheet'!E21+'Balance Sheet'!E22+'Balance Sheet'!E23+'Balance Sheet'!E24+'Balance Sheet'!E25 | F26: ='Balance Sheet'!F20+'Balance Sheet'!F21+'Balance Sheet'!F22+'Balance Sheet'!F23+'Balance Sheet'!F24+'Balance Sheet'!F25 | G26: ='Balance Sheet'!G20+'Balance Sheet'!G21+'Balance Sheet'!G22+'Balance Sheet'!G23+'Balance Sheet'!G24+'Balance Sheet'!G25 | H26: ='Balance Sheet'!H20+'Balance Sheet'!H21+'Balance Sheet'!H22+'Balance Sheet'!H23+'Balance Sheet'!H24+'Balance Sheet'!H25 | I26: ='Balance Sheet'!I20+'Balance Sheet'!I21+'Balance Sheet'!I22+'Balance Sheet'!I23+'Balance Sheet'!I24+'Balance Sheet'!I25 | J26: ='Balance Sheet'!J20+'Balance Sheet'!J21+'Balance Sheet'!J22+'Balance Sheet'!J23+'Balance Sheet'!J24+'Balance Sheet'!J25 | K26: ='Balance Sheet'!K20+'Balance Sheet'!K21+'Balance Sheet'!K22+'Balance Sheet'!K23+'Balance Sheet'!K24+'Balance Sheet'!K25
A27: EQUITY
A28: Common stock & additional paid-in capital | C28: 25000 | D28: 2900 | E28: ='Deal & PPA'!C4-'Balance Sheet'!D28 | F28: ='Balance Sheet'!C28+'Balance Sheet'!D28+'Balance Sheet'!E28 | G28: ='Balance Sheet'!F28+'Cash Flow'!D8+'Assumptions'!D25 | H28: ='Balance Sheet'!G28+'Cash Flow'!E8+'Assumptions'!E25 | I28: ='Balance Sheet'!H28+'Cash Flow'!F8+'Assumptions'!F25 | J28: ='Balance Sheet'!I28+'Cash Flow'!G8+'Assumptions'!G25 | K28: ='Balance Sheet'!J28+'Cash Flow'!H8+'Assumptions'!H25
A29: Accumulated deficit | C29: -22400 | D29: 0 | E29: 0 | F29: ='Balance Sheet'!C29+'Balance Sheet'!D29+'Balance Sheet'!E29 | G29: ='Balance Sheet'!F29+'Income Statement'!D25 | H29: ='Balance Sheet'!G29+'Income Statement'!E25 | I29: ='Balance Sheet'!H29+'Income Statement'!F25 | J29: ='Balance Sheet'!I29+'Income Statement'!G25 | K29: ='Balance Sheet'!J29+'Income Statement'!H25
A30: TOTAL EQUITY | C30: ='Balance Sheet'!C28+'Balance Sheet'!C29 | D30: ='Balance Sheet'!D28+'Balance Sheet'!D29 | E30: ='Balance Sheet'!E28+'Balance Sheet'!E29 | F30: ='Balance Sheet'!F28+'Balance Sheet'!F29 | G30: ='Balance Sheet'!G28+'Balance Sheet'!G29 | H30: ='Balance Sheet'!H28+'Balance Sheet'!H29 | I30: ='Balance Sheet'!I28+'Balance Sheet'!I29 | J30: ='Balance Sheet'!J28+'Balance Sheet'!J29 | K30: ='Balance Sheet'!K28+'Balance Sheet'!K29
A31: TOTAL LIABILITIES & EQUITY | C31: ='Balance Sheet'!C26+'Balance Sheet'!C30 | D31: ='Balance Sheet'!D26+'Balance Sheet'!D30 | E31: ='Balance Sheet'!E26+'Balance Sheet'!E30 | F31: ='Balance Sheet'!F26+'Balance Sheet'!F30 | G31: ='Balance Sheet'!G26+'Balance Sheet'!G30 | H31: ='Balance Sheet'!H26+'Balance Sheet'!H30 | I31: ='Balance Sheet'!I26+'Balance Sheet'!I30 | J31: ='Balance Sheet'!J26+'Balance Sheet'!J30 | K31: ='Balance Sheet'!K26+'Balance Sheet'!K30
A32: Balance check (assets − L&E) | C32: ='Balance Sheet'!C14-'Balance Sheet'!C31 | D32: ='Balance Sheet'!D14-'Balance Sheet'!D31 | E32: ='Balance Sheet'!E14-'Balance Sheet'!E31 | F32: ='Balance Sheet'!F14-'Balance Sheet'!F31 | G32: ='Balance Sheet'!G14-'Balance Sheet'!G31 | H32: ='Balance Sheet'!H14-'Balance Sheet'!H31 | I32: ='Balance Sheet'!I14-'Balance Sheet'!I31 | J32: ='Balance Sheet'!J14-'Balance Sheet'!J31 | K32: ='Balance Sheet'!K14-'Balance Sheet'!K31

Sheet Cash Flow
A1: PRO-FORMA COMBINED CASH FLOW STATEMENT (US$M)
A2: Post-acquisition years. The all-stock purchase is non-cash and reflected in opening balances (acquired cash included).
C3: 2025A | D3: 2026E | E3: 2027E | F3: 2028E | G3: 2029E | H3: 2030E
A4: Operating activities
A5: Net income (loss) | D5: ='Income Statement'!D25 | E5: ='Income Statement'!E25 | F5: ='Income Statement'!F25 | G5: ='Income Statement'!G25 | H5: ='Income Statement'!H25
A6: Depreciation | D6: ='Schedules'!D6 | E6: ='Schedules'!E6 | F6: ='Schedules'!F6 | G6: ='Schedules'!G6 | H6: ='Schedules'!H6
A7: Amortization of acquired intangibles | D7: ='Schedules'!D10 | E7: ='Schedules'!E10 | F7: ='Schedules'!F10 | G7: ='Schedules'!G10 | H7: ='Schedules'!H10
A8: Stock-based compensation | D8: ='Assumptions'!D22*'Income Statement'!D7 | E8: ='Assumptions'!E22*'Income Statement'!E7 | F8: ='Assumptions'!F22*'Income Statement'!F7 | G8: ='Assumptions'!G22*'Income Statement'!G7 | H8: ='Assumptions'!H22*'Income Statement'!H7
A9: Deferred income taxes | D9: ='Schedules'!D13 | E9: ='Schedules'!E13 | F9: ='Schedules'!F13 | G9: ='Schedules'!G13 | H9: ='Schedules'!H13
A10: (Increase)/decrease in receivables | D10: =-('Balance Sheet'!G5-'Balance Sheet'!F5) | E10: =-('Balance Sheet'!H5-'Balance Sheet'!G5) | F10: =-('Balance Sheet'!I5-'Balance Sheet'!H5) | G10: =-('Balance Sheet'!J5-'Balance Sheet'!I5) | H10: =-('Balance Sheet'!K5-'Balance Sheet'!J5)
A11: (Increase)/decrease in inventory | D11: =-('Balance Sheet'!G6-'Balance Sheet'!F6) | E11: =-('Balance Sheet'!H6-'Balance Sheet'!G6) | F11: =-('Balance Sheet'!I6-'Balance Sheet'!H6) | G11: =-('Balance Sheet'!J6-'Balance Sheet'!I6) | H11: =-('Balance Sheet'!K6-'Balance Sheet'!J6)
A12: (Increase)/decrease in prepaids | D12: =-('Balance Sheet'!G7-'Balance Sheet'!F7) | E12: =-('Balance Sheet'!H7-'Balance Sheet'!G7) | F12: =-('Balance Sheet'!I7-'Balance Sheet'!H7) | G12: =-('Balance Sheet'!J7-'Balance Sheet'!I7) | H12: =-('Balance Sheet'!K7-'Balance Sheet'!J7)
A13: Increase/(decrease) in payables | D13: =('Balance Sheet'!G16-'Balance Sheet'!F16) | E13: =('Balance Sheet'!H16-'Balance Sheet'!G16) | F13: =('Balance Sheet'!I16-'Balance Sheet'!H16) | G13: =('Balance Sheet'!J16-'Balance Sheet'!I16) | H13: =('Balance Sheet'!K16-'Balance Sheet'!J16)
A14: Increase/(decrease) in accrued liabilities | D14: =('Balance Sheet'!G17-'Balance Sheet'!F17) | E14: =('Balance Sheet'!H17-'Balance Sheet'!G17) | F14: =('Balance Sheet'!I17-'Balance Sheet'!H17) | G14: =('Balance Sheet'!J17-'Balance Sheet'!I17) | H14: =('Balance Sheet'!K17-'Balance Sheet'!J17)
A15: Increase/(decrease) in deferred revenue (cur.) | D15: =('Balance Sheet'!G18-'Balance Sheet'!F18) | E15: =('Balance Sheet'!H18-'Balance Sheet'!G18) | F15: =('Balance Sheet'!I18-'Balance Sheet'!H18) | G15: =('Balance Sheet'!J18-'Balance Sheet'!I18) | H15: =('Balance Sheet'!K18-'Balance Sheet'!J18)
A16: Increase/(decrease) in customer deposits | D16: =('Balance Sheet'!G19-'Balance Sheet'!F19) | E16: =('Balance Sheet'!H19-'Balance Sheet'!G19) | F16: =('Balance Sheet'!I19-'Balance Sheet'!H19) | G16: =('Balance Sheet'!J19-'Balance Sheet'!I19) | H16: =('Balance Sheet'!K19-'Balance Sheet'!J19)
A17: Increase/(decrease) in LT deferred revenue | D17: =('Balance Sheet'!G23-'Balance Sheet'!F23) | E17: =('Balance Sheet'!H23-'Balance Sheet'!G23) | F17: =('Balance Sheet'!I23-'Balance Sheet'!H23) | G17: =('Balance Sheet'!J23-'Balance Sheet'!I23) | H17: =('Balance Sheet'!K23-'Balance Sheet'!J23)
A18: Cash from operations | D18: ='Cash Flow'!D5+'Cash Flow'!D6+'Cash Flow'!D7+'Cash Flow'!D8+'Cash Flow'!D9+'Cash Flow'!D10+'Cash Flow'!D11+'Cash Flow'!D12+'Cash Flow'!D13+'Cash Flow'!D14+'Cash Flow'!D15+'Cash Flow'!D16+'Cash Flow'!D17 | E18: ='Cash Flow'!E5+'Cash Flow'!E6+'Cash Flow'!E7+'Cash Flow'!E8+'Cash Flow'!E9+'Cash Flow'!E10+'Cash Flow'!E11+'Cash Flow'!E12+'Cash Flow'!E13+'Cash Flow'!E14+'Cash Flow'!E15+'Cash Flow'!E16+'Cash Flow'!E17 | F18: ='Cash Flow'!F5+'Cash Flow'!F6+'Cash Flow'!F7+'Cash Flow'!F8+'Cash Flow'!F9+'Cash Flow'!F10+'Cash Flow'!F11+'Cash Flow'!F12+'Cash Flow'!F13+'Cash Flow'!F14+'Cash Flow'!F15+'Cash Flow'!F16+'Cash Flow'!F17 | G18: ='Cash Flow'!G5+'Cash Flow'!G6+'Cash Flow'!G7+'Cash Flow'!G8+'Cash Flow'!G9+'Cash Flow'!G10+'Cash Flow'!G11+'Cash Flow'!G12+'Cash Flow'!G13+'Cash Flow'!G14+'Cash Flow'!G15+'Cash Flow'!G16+'Cash Flow'!G17 | H18: ='Cash Flow'!H5+'Cash Flow'!H6+'Cash Flow'!H7+'Cash Flow'!H8+'Cash Flow'!H9+'Cash Flow'!H10+'Cash Flow'!H11+'Cash Flow'!H12+'Cash Flow'!H13+'Cash Flow'!H14+'Cash Flow'!H15+'Cash Flow'!H16+'Cash Flow'!H17
A19: Investing activities
A20: Capital expenditures | D20: =-'Schedules'!D5 | E20: =-'Schedules'!E5 | F20: =-'Schedules'!F5 | G20: =-'Schedules'!G5 | H20: =-'Schedules'!H5
A21: Cash from investing | D21: ='Cash Flow'!D20 | E21: ='Cash Flow'!E20 | F21: ='Cash Flow'!F20 | G21: ='Cash Flow'!G20 | H21: ='Cash Flow'!H20
A22: Financing activities
A23: Net debt draws / (repayments) | D23: ='Schedules'!D17 | E23: ='Schedules'!E17 | F23: ='Schedules'!F17 | G23: ='Schedules'!G17 | H23: ='Schedules'!H17
A24: Spectrum obligation repayments | D24: ='Schedules'!D20 | E24: ='Schedules'!E20 | F24: ='Schedules'!F20 | G24: ='Schedules'!G20 | H24: ='Schedules'!H20
A25: Primary equity issuance / IPO | D25: ='Assumptions'!D25 | E25: ='Assumptions'!E25 | F25: ='Assumptions'!F25 | G25: ='Assumptions'!G25 | H25: ='Assumptions'!H25
A26: Cash from financing | D26: ='Cash Flow'!D23+'Cash Flow'!D24+'Cash Flow'!D25 | E26: ='Cash Flow'!E23+'Cash Flow'!E24+'Cash Flow'!E25 | F26: ='Cash Flow'!F23+'Cash Flow'!F24+'Cash Flow'!F25 | G26: ='Cash Flow'!G23+'Cash Flow'!G24+'Cash Flow'!G25 | H26: ='Cash Flow'!H23+'Cash Flow'!H24+'Cash Flow'!H25
A27: Net change in cash | D27: ='Cash Flow'!D18+'Cash Flow'!D21+'Cash Flow'!D26 | E27: ='Cash Flow'!E18+'Cash Flow'!E21+'Cash Flow'!E26 | F27: ='Cash Flow'!F18+'Cash Flow'!F21+'Cash Flow'!F26 | G27: ='Cash Flow'!G18+'Cash Flow'!G21+'Cash Flow'!G26 | H27: ='Cash Flow'!H18+'Cash Flow'!H21+'Cash Flow'!H26
A28: Cash, beginning of period | D28: ='Balance Sheet'!F4 | E28: ='Cash Flow'!D29 | F28: ='Cash Flow'!E29 | G28: ='Cash Flow'!F29 | H28: ='Cash Flow'!G29
A29: Cash, end of period | D29: ='Cash Flow'!D28+'Cash Flow'!D27 | E29: ='Cash Flow'!E28+'Cash Flow'!E27 | F29: ='Cash Flow'!F28+'Cash Flow'!F27 | G29: ='Cash Flow'!G28+'Cash Flow'!G27 | H29: ='Cash Flow'!H28+'Cash Flow'!H27

Sheet Checks
A1: MODEL INTEGRITY CHECKS (should all be ~0)
C2: 2025A | D2: 2026E | E2: 2027E | F2: 2028E | G2: 2029E | H2: 2030E
A3: Balance sheet balances (A − L&E) | C3: ='Balance Sheet'!C32 | D3: ='Balance Sheet'!G32 | E3: ='Balance Sheet'!H32 | F3: ='Balance Sheet'!I32 | G3: ='Balance Sheet'!J32 | H3: ='Balance Sheet'!K32
A4: Cash flow ties to balance sheet cash | C4: n/a | D4: ='Cash Flow'!D29-'Balance Sheet'!G4 | E4: ='Cash Flow'!E29-'Balance Sheet'!H4 | F4: ='Cash Flow'!F29-'Balance Sheet'!I4 | G4: ='Cash Flow'!G29-'Balance Sheet'!J4 | H4: ='Cash Flow'!H29-'Balance Sheet'!K4
A5: PPA bridge balances (Open: A − L&E) | C5: ='Balance Sheet'!F32
