Workbook

Sheet Assumptions
A1: Assumptions & Toggles
A3: Weeks per month | B3: 4.345
A4: Input token share (blended price) | B4: 0.5
A5: Output token share (blended price) | B5: =1-B4
A7: Implied spend = tokens (trillions) x blended price ($/Mtok), which equals $ in millions.
A8: Blended price = input_share x input$ + output_share x output$. Edit B4 to re-flow every spend figure in the workbook.

Sheet Monthly_Consumption
A1: Monthly Token Consumption — GLM 5.2 vs Leading Frontier Models
A2: Source: OpenRouter public usage rankings & model pages. As of 30 Jun 2026. Token volumes in trillions (T). GLM 5.2 row highlighted.
A4: Rank (month) | B4: Model | C4: Developer | D4: Country | E4: License | F4: Monthly tokens (T) | G4: MoM growth % | H4: Latest weekly tokens (T) | I4: WoW growth % | J4: Monthly run-rate (T) | K4: Input $/Mtok | L4: Output $/Mtok | M4: Price basis | N4: Blended $/Mtok | O4: Implied monthly spend (trailing, $M) | P4: Implied monthly spend (run-rate, $M) | Q4: Notes
A5: 1 | B5: DeepSeek V4 Flash | C5: DeepSeek | D5: China | E5: Open (MIT) | F5: 10.9 | G5: 9.95 | H5: 4.72 | I5: 0.05 | J5: =H5*Assumptions!$B$3 | K5: 0.054 | L5: 0.242 | M5: realized | N5: =K5*Assumptions!$B$4+L5*Assumptions!$B$5 | O5: =F5*N5 | P5: =IF(J5="","",J5*N5) | Q5: MoE w/ DeepSeek Sparse Attention; default low-cost high-volume model
A6: 2 | B6: Hy3 Preview | C6: Tencent | D6: China | E6: Preview | F6: 10.7 | G6: 9.99 | H6: 3.46 | I6: 0.06 | J6: =H6*Assumptions!$B$3 | K6: 0.063 | M6: list | Q6: 295B MoE (21B active); launched late Apr 2026; output list price not disclosed
A7: 3 | B7: Claude Opus 4.7 | C7: Anthropic | D7: USA | E7: Closed | F7: 7.48 | G7: 1.97 | H7: 2.23 | I7: 0.09 | J7: =H7*Assumptions!$B$3 | K7: 1.65 | L7: 25 | M7: realized | N7: =K7*Assumptions!$B$4+L7*Assumptions!$B$5 | O7: =F7*N7 | P7: =IF(J7="","",J7*N7) | Q7: Highest-ranked closed model; realized input reflects prompt caching
A8: 4 | B8: Claude Sonnet 4.6 | C8: Anthropic | D8: USA | E8: Closed | F8: 7.45 | G8: 0.34 | H8: 1.54 | I8: 0.01 | J8: =H8*Assumptions!$B$3 | K8: 1.31 | L8: 15 | M8: realized | N8: =K8*Assumptions!$B$4+L8*Assumptions!$B$5 | O8: =F8*N8 | P8: =IF(J8="","",J8*N8) | Q8: Workhorse tier; realized input reflects prompt caching
A9: 5 | B9: Owl Alpha | C9: OpenRouter | D9: USA | E9: Closed | F9: 5.03 | G9: 9.99 | H9: 3.55 | I9: 0.31 | J9: =H9*Assumptions!$B$3 | M9: n/a | Q9: Platform-native routing/fallback model; pricing not published
A10: 6 | B10: Gemini 3 Flash Preview | C10: Google | D10: USA | E10: Closed | F10: 4.6 | G10: 0.03 | K10: 0.5 | L10: 3 | M10: list | N10: =K10*Assumptions!$B$4+L10*Assumptions!$B$5 | O10: =F10*N10 | P10: =IF(J10="","",J10*N10) | Q10: Latency-optimized high-frequency workhorse
A11: 7 | B11: DeepSeek V4 Pro | C11: DeepSeek | D11: China | E11: Open (MIT) | F11: 4.54 | G11: 7.39 | H11: 2.08 | I11: 0.17 | J11: =H11*Assumptions!$B$3 | K11: 0.435 | L11: 0.87 | M11: list | N11: =K11*Assumptions!$B$4+L11*Assumptions!$B$5 | O11: =F11*N11 | P11: =IF(J11="","",J11*N11) | Q11: 1.6T params (49B active); higher-capability sibling of V4 Flash
A12: 8 | B12: DeepSeek V3.2 | C12: DeepSeek | D12: China | E12: Open (MIT) | F12: 4.31 | G12: -0.14 | K12: 0.2288 | L12: 0.3432 | M12: list | N12: =K12*Assumptions!$B$4+L12*Assumptions!$B$5 | O12: =F12*N12 | P12: =IF(J12="","",J12*N12) | Q12: Prior-gen; being cannibalized by V4 family
A13: 9 | B13: Kimi K2.6 | C13: Moonshot AI | D13: China | E13: Open | F13: 3.72 | G13: 0.01 | K13: 0.55 | L13: 3.2 | M13: list | N13: =K13*Assumptions!$B$4+L13*Assumptions!$B$5 | O13: =F13*N13 | P13: =IF(J13="","",J13*N13) | Q13: Top open-weights AA Intelligence Index (54); multimodal
A14: 10 | B14: Nemotron 3 Super | C14: NVIDIA | D14: USA | E14: Open | F14: 2.65 | G14: 0.03 | K14: 0 | L14: 0 | M14: list | N14: =K14*Assumptions!$B$4+L14*Assumptions!$B$5 | O14: =F14*N14 | P14: =IF(J14="","",J14*N14) | Q14: Offered free on OpenRouter; ~300 tok/s throughput
B15: GLM 5.2 | C15: Z.ai (Zhipu AI) | D15: China | E15: Open (MIT) | H15: 2.11 | I15: 0.66 | J15: =H15*Assumptions!$B$3 | K15: 0.447 | L15: 3.31 | M15: realized | N15: =K15*Assumptions!$B$4+L15*Assumptions!$B$5 | P15: =IF(J15="","",J15*N15) | Q15: Launched Jun 13 (Coding Plan) / Jun 16 (weights+API); 744B MoE (40B active), 1M context; ranked #7 by weekly run-rate; partial-month so excluded from trailing-month top 10
B17: Platform context | F17: =SUM(F5:F15) | Q17: Top-10 trailing-month subtotal (GLM 5.2 excluded; partial month). OpenRouter platform-wide volume ~46T tokens/week (Jun 2026).

Sheet GLM5.2_RunRate
A1: GLM 5.2 — Adoption Run-Rate
A2: Launched 13 Jun 2026 (GLM Coding Plan) and 16 Jun 2026 (MIT open weights + API). 744B MoE, 40B active, 1M-token context. Excluded from the trailing-month top 10 because of its partial first month; run-rate is the cleaner read.
A4: Week ending | B4: Weekly tokens (T) | C4: WoW growth % | D4: Data quality | E4: Source / note
A5: 21 Jun 2026 | B5: 1.27 | D5: derived | E5: Implied from +66% WoW into week ending 28 Jun
A6: 28 Jun 2026 | B6: 2.11 | C6: 0.66 | D6: reported | E6: thestack.technology / OpenRouter ranking (#7)
A8: Latest weekly (T) | B8: =B6
A9: Monthly run-rate (T) | B9: =B6*Assumptions!$B$3
A10: Realized blended price ($/Mtok) | B10: =0.447*Assumptions!$B$4+3.31*Assumptions!$B$5
A11: Implied monthly inference spend ($M) | B11: =B9*B10
A13: Interpretation: at the latest weekly run-rate GLM 5.2 annualizes to a monthly-equivalent volume that would place it among the top 3-5 models, despite not appearing in the trailing-month top 10.

Sheet Sources
A1: Sources & Methodology
A3: Token-consumption deliverable focused on GLM 5.2 vs leading frontier models, as of 30 Jun 2026.
A5: Token volumes:
A6: - OpenRouter LLM Rankings (live monthly/weekly token usage): https://openrouter.ai/rankings
A7: - 'These Are The Most Popular AI Models On OpenRouter [June 2026]', officechai (monthly top 10).
A8: - 'OpenRouter Monthly Token Usage Ranking 2026', aicost.org (cross-check).
A9: - GLM 5.2 weekly figure: thestack.technology 'Opus-killer GLM-5.2... astonishing demand' (#7 ranking, 2.11T week ending 28 Jun, +66% WoW).
A10: - OpenRouter blog 'The Open Weight Models that Matter: June 2026' (GLM 5.2 realized pricing $0.447/$3.31).
A12: Pricing (per 1M tokens, list and prompt-cache realized where shown):
A13: - OpenRouter model pages: z-ai/glm-5.2, deepseek-v4-flash, deepseek-v4-pro, deepseek-v3.2,
A14: anthropic/claude-opus-4.7, anthropic/claude-sonnet-4.6, moonshotai/kimi-k2.6.
A15: - Gemini 3 Flash Preview list pricing $0.50/$3.00 (OpenRouter).
... A29: - Growth figures capped in source reporting (e.g. '+>999%') are entered at 999%.
