Workbook

Sheet Summary
B2: AI model labs: gross vs. net ARR - frontier (closed-weight) vs. open-weight
B3: USD billions, latest reported run rates as of 15-Oct-2026. Gross = end-customer billings incl. partner channel; Net = retained by the lab after partner revenue share. Figures are run rates from different months and are not audited.
B5: Segment | C5: # labs included | D5: Gross ARR ($B) | E5: Net ARR ($B) | F5: Gross-to-net haircut | G5: Share of total net
B6: Frontier (closed-weight) labs | C6: =Frontier!D10 | D6: =Frontier!K10 | E6: =Frontier!L10 | F6: =IF(D6=0,0,1-E6/D6) | G6: =IF($E$8=0,0,E6/$E$8)
B7: Open-weight labs | C7: =Open_Weight!D15 | D7: =Open_Weight!K15 | E7: =Open_Weight!L15 | F7: =IF(D7=0,0,1-E7/D7) | G7: =IF($E$8=0,0,E7/$E$8)
B8: Total | C8: =C6+C7 | D8: =D6+D7 | E8: =E6+E7 | F8: =IF(D8=0,0,1-E8/D8) | G8: =G6+G7
B10: Open-weight net ARR as % of frontier net ARR | C10: =IF(E6=0,0,E7/E6)
B11: Open-weight gross ARR as % of frontier gross ARR | C11: =IF(D6=0,0,D7/D6)
B12: OpenAI + Anthropic share of total net ARR | C12: =IF(E8=0,0,(Frontier!L5+Frontier!L6)/E8)
B14: By lab (included rows only)
B15: Lab | C15: Segment | D15: Gross ARR ($B) | E15: Net ARR ($B) | F15: Haircut | G15: As of
B16: =Frontier!A5 | C16: Frontier | D16: =IF(Frontier!D5="Y",Frontier!K5,0) | E16: =IF(Frontier!D5="Y",Frontier!L5,0) | F16: =Frontier!M5 | G16: =Frontier!E5
B17: =Frontier!A6 | C17: Frontier | D17: =IF(Frontier!D6="Y",Frontier!K6,0) | E17: =IF(Frontier!D6="Y",Frontier!L6,0) | F17: =Frontier!M6 | G17: =Frontier!E6
B18: =Frontier!A7 | C18: Frontier | D18: =IF(Frontier!D7="Y",Frontier!K7,0) | E18: =IF(Frontier!D7="Y",Frontier!L7,0) | F18: =Frontier!M7 | G18: =Frontier!E7
B19: =Frontier!A8 | C19: Frontier | D19: =IF(Frontier!D8="Y",Frontier!K8,0) | E19: =IF(Frontier!D8="Y",Frontier!L8,0) | F19: =Frontier!M8 | G19: =Frontier!E8
B20: =Frontier!A9 | C20: Frontier | D20: =IF(Frontier!D9="Y",Frontier!K9,0) | E20: =IF(Frontier!D9="Y",Frontier!L9,0) | F20: =Frontier!M9 | G20: =Frontier!E9
B21: =Open_Weight!A5 | C21: Open-weight | D21: =IF(Open_Weight!D5="Y",Open_Weight!K5,0) | E21: =IF(Open_Weight!D5="Y",Open_Weight!L5,0) | F21: =Open_Weight!M5 | G21: =Open_Weight!E5
B22: =Open_Weight!A6 | C22: Open-weight | D22: =IF(Open_Weight!D6="Y",Open_Weight!K6,0) | E22: =IF(Open_Weight!D6="Y",Open_Weight!L6,0) | F22: =Open_Weight!M6 | G22: =Open_Weight!E6
B23: =Open_Weight!A7 | C23: Open-weight | D23: =IF(Open_Weight!D7="Y",Open_Weight!K7,0) | E23: =IF(Open_Weight!D7="Y",Open_Weight!L7,0) | F23: =Open_Weight!M7 | G23: =Open_Weight!E7
B24: =Open_Weight!A8 | C24: Open-weight | D24: =IF(Open_Weight!D8="Y",Open_Weight!K8,0) | E24: =IF(Open_Weight!D8="Y",Open_Weight!L8,0) | F24: =Open_Weight!M8 | G24: =Open_Weight!E8
B25: =Open_Weight!A9 | C25: Open-weight | D25: =IF(Open_Weight!D9="Y",Open_Weight!K9,0) | E25: =IF(Open_Weight!D9="Y",Open_Weight!L9,0) | F25: =Open_Weight!M9 | G25: =Open_Weight!E9
B26: =Open_Weight!A10 | C26: Open-weight | D26: =IF(Open_Weight!D10="Y",Open_Weight!K10,0) | E26: =IF(Open_Weight!D10="Y",Open_Weight!L10,0) | F26: =Open_Weight!M10 | G26: =Open_Weight!E10
B27: =Open_Weight!A11 | C27: Open-weight | D27: =IF(Open_Weight!D11="Y",Open_Weight!K11,0) | E27: =IF(Open_Weight!D11="Y",Open_Weight!L11,0) | F27: =Open_Weight!M11 | G27: =Open_Weight!E11
B28: =Open_Weight!A12 | C28: Open-weight | D28: =IF(Open_Weight!D12="Y",Open_Weight!K12,0) | E28: =IF(Open_Weight!D12="Y",Open_Weight!L12,0) | F28: =Open_Weight!M12 | G28: =Open_Weight!E12
B29: =Open_Weight!A13 | C29: Open-weight | D29: =IF(Open_Weight!D13="Y",Open_Weight!K13,0) | E29: =IF(Open_Weight!D13="Y",Open_Weight!L13,0) | F29: =Open_Weight!M13 | G29: =Open_Weight!E13
B30: =Open_Weight!A14 | C30: Open-weight | D30: =IF(Open_Weight!D14="Y",Open_Weight!K14,0) | E30: =IF(Open_Weight!D14="Y",Open_Weight!L14,0) | F30: =Open_Weight!M14 | G30: =Open_Weight!E14
B31: Check: sum of per-lab net = segment total | E31: =SUM(E16:E30)-E8
B33: Reading the numbers
B34: 1. The gross/net gap is concentrated in the two leaders: OpenAI reports net of Microsoft's ~20% share (the $68B 'gross' figure was an investor gross-up), while Anthropic books cloud-marketplace sales gross and expenses the partner cut.
B35: 2. Google, xAI and the Chinese labs sell predominantly first-party, so gross = net for them in this model; their uncertainty is in the reported figure itself (yellow = estimate).
B36: 3. Open-weight labs capture only part of the spend on their models: third-party hosts (Fireworks, Together, Baseten, fal) and clouds serve most tokens. DeepSeek is estimated to receive ~8% of OpenRouter spend on DeepSeek models. See memo on the Open_Weight sheet.
B37: 4. ByteDance (~$4B MaaS) is excluded by default because its flagship Doubao models are closed and the figure includes third-party models; flip Open_Weight!D14 to 'Y' to include.
B38: 5. Run rates are month-of-record figures and are not comparable across labs without the 'As of' date; Anthropic's Q3-2026 quarterly revenue ($16.8B) annualizes to $67.2B and YE-2026 targets are ~$110B (Anthropic) and >=$70B net (OpenAI).

Sheet Frontier
A1: Frontier (closed-weight) model labs: gross vs. net ARR
A2: Gross ARR = annualized end-customer billings incl. cloud-marketplace / partner channel sales at full value. Net ARR = retained by the lab after partner revenue share. Blue = input; yellow fill = estimate or assumption. $B.
A3: As of 15-Oct-2026. Run rates are from different months; see 'As of' column. Toggle column D to include/exclude a row from totals.
A4: Company | B4: Flagship model(s) | C4: Weights | D4: Include in totals? (Y/N) | E4: As of | F4: Reported ARR ($B) | G4: Reported basis | H4: Channel share of billings | I4: Partner take rate | J4: Gross override ($B) | K4: Gross ARR ($B) | L4: Net ARR ($B) | M4: Gross-to-net haircut | N4: Confidence | O4: Source(s) | P4: Notes
A5: OpenAI | B5: GPT-5.6 family / ChatGPT | C5: Closed | D5: Y | E5: Sep-2026 | F5: 50 | G5: Net | H5: =Assumptions!$C$7 | I5: =Assumptions!$C$6 | J5: =Assumptions!$C$8 | K5: =IF(J5<>"",J5,IF(G5="Gross",F5,F5/(1-H5*I5))) | L5: =IF(G5="Net",F5,K5*(1-H5*I5)) | M5: =IF(K5=0,0,1-L5/K5) | N5: High | O5: Reuters, CNBC, Axios, Bloomberg (8-Oct-2026) | P5: OpenAI reports NET of the ~20% Microsoft revenue share. $50B is the Sep-2026 run rate told to investors; the $68B figure circulated in Sep-2026 was a gross-up to Anthropic's methodology and is used as the gross override. Model-based gross at 20% share would be $62.5B (cross-check). Guided to >=$70B (net) by YE-2026. Q3 run-rate growth +77%; enterprise +107%. MSFT rev share continues to 2030 at the same % subject to a cap (Apr-2026 amended agreement).
A6: Anthropic | B6: Claude (Fable 5 / Opus / Sonnet) | C6: Closed | D6: Y | E6: Jul-2026 | F6: 65 | G6: Gross | H6: =Assumptions!$C$12 | I6: =Assumptions!$C$13 | K6: =IF(J6<>"",J6,IF(G6="Gross",F6,F6/(1-H6*I6))) | L6: =IF(G6="Net",F6,K6*(1-H6*I6)) | M6: =IF(K6=0,0,1-L6/K6) | N6: High | O6: Reuters, Bloomberg (17-Aug-2026); Reuters on IPO prospectus; CNBC (15-Oct-2026) | P6: Anthropic reports GROSS: marketplace (AWS Bedrock, Google Vertex) sales booked at full value with the partner cut expensed in S&M. Prospectus: 2025 revenue ~$4.6B, 47% via marketplaces ($2.16B), distribution fees ~$351M (~16% take). Q3-2026 revenue $16.8B (x4 = $67.2B). Analysts see ~$110B run rate by YE-2026. BofA (Mar-2026) est. up to $6.4B of 2026 hyperscaler payouts - see sensitivity.
A7: Google DeepMind | B7: Gemini 3 (Pro / Flash) | C7: Closed | D7: Y | E7: Q2-2026 | F7: 12 | G7: Gross | H7: 0 | I7: 0 | K7: =IF(J7<>"",J7,IF(G7="Gross",F7,F7/(1-H7*I7))) | L7: =IF(G7="Net",F7,K7*(1-H7*I7)) | M7: =IF(K7=0,0,1-L7/K7) | N7: Low | O7: SemiAnalysis Tokenomics (Gemini ARR est.); The Compute Chain ($7-10B est.) | P7: ESTIMATE. Alphabet does not disclose Gemini revenue. SemiAnalysis est. $12B 1P Gemini ARR in 2Q26; The Compute Chain est. $7-10B now / $10-14B by YE. First-party sales, so gross = net. Excludes GCP infrastructure and 3P model resale (Claude on Vertex). Broader 'Google AI' bundle incl. Workspace add-ons est. ~$28B (Presenc, May-2026) - not used.
A8: xAI (SpaceX AI segment) | B8: Grok 4 / SuperGrok | C8: Closed | D8: Y | E8: Mid-2026 | F8: 0.5 | G8: Gross | H8: 0 | I8: 0 | K8: =IF(J8<>"",J8,IF(G8="Gross",F8,F8/(1-H8*I8))) | L8: =IF(G8="Net",F8,K8*(1-H8*I8)) | M8: =IF(K8=0,0,1-L8/K8) | N8: Medium | O8: Bloomberg via Sacra; SpaceX 10-Q (Q2-2026 AI segment) | P8: Standalone Grok ARR (subscriptions + API, ex-X advertising). SpaceX AI segment did $2.56B in Q2-2026 (~$10.2B annualized) but that includes X ads ($367M/qtr), compute-rental / AI infrastructure (~$1.6B/qtr) and data licensing, so it is not a model-revenue figure. Company 2026 target ~$2B.
A9: Meta (Superintelligence Labs) | B9: Muse Spark 1.x (closed since Apr-2026) | C9: Closed | D9: Y | E9: Oct-2026 | F9: 0.13 | G9: Gross | H9: 0 | I9: 0 | K9: =IF(J9<>"",J9,IF(G9="Gross",F9,F9/(1-H9*I9))) | L9: =IF(G9="Net",F9,K9*(1-H9*I9)) | M9: =IF(K9=0,0,1-L9/K9) | N9: Low | O9: Vantage OpenRouter provider economics (13-Oct-2026); Bloomberg/CNBC on Meta Model API launch | P9: FLOOR ESTIMATE. Meta Model API launched Jul-2026 ($1.25/$4.25 per M tokens). Only OpenRouter-attributable billings are observable (~$131M annualized); direct API and Muse Code subscriptions not disclosed. Meta's open-weight Llama line is shown on the Open-Weight sheet at $0 licensing revenue.
A10: Total (included rows) | D10: =COUNTIF(D5:D9,"Y") | K10: =SUMIF($D$5:$D$9,"Y",K5:K9) | L10: =SUMIF($D$5:$D$9,"Y",L5:L9) | M10: =IF(K10=0,0,1-L10/K10)

Sheet Open_Weight
A1: Open-weight model labs: gross vs. net ARR
A2: Gross ARR = annualized end-customer billings incl. cloud-marketplace / partner channel sales at full value. Net ARR = retained by the lab after partner revenue share. Blue = input; yellow fill = estimate or assumption. $B.
A3: As of 15-Oct-2026. Run rates are from different months; see 'As of' column. Toggle column D to include/exclude a row from totals.
A4: Company | B4: Flagship model(s) | C4: Weights | D4: Include in totals? (Y/N) | E4: As of | F4: Reported ARR ($B) | G4: Reported basis | H4: Channel share of billings | I4: Partner take rate | J4: Gross override ($B) | K4: Gross ARR ($B) | L4: Net ARR ($B) | M4: Gross-to-net haircut | N4: Confidence | O4: Source(s) | P4: Notes
A5: Mistral AI | B5: Mistral Large 3 / Medium (Apache 2.0) | C5: Open (Apache 2.0) + some closed | D5: Y | E5: Sep-2026 | F5: 1 | G5: Gross | H5: =Assumptions!$C$17 | I5: =Assumptions!$C$18 | K5: =IF(J5<>"",J5,IF(G5="Gross",F5,F5/(1-H5*I5))) | L5: =IF(G5="Net",F5,K5*(1-H5*I5)) | M5: =IF(K5=0,0,1-L5/K5) | N5: High | O5: WSJ, Reuters (8-Sep-2026, CFO); CNBC Disruptor 50 | P5: CFO: ARR 'slightly above $1B' at the Samsung-led EUR3B round. Was >$400M in Jan-2026, ~$20M a year earlier. ~60% of revenue in Europe; sells direct plus via Azure/AWS/GCP marketplaces (split not disclosed - generic channel assumption applied).
A6: DeepSeek | B6: DeepSeek V4 Pro / Flash (MIT) | C6: Open (MIT) | D6: Y | E6: Sep-2026 | F6: 1 | G6: Gross | H6: 0 | I6: 0 | K6: =IF(J6<>"",J6,IF(G6="Gross",F6,F6/(1-H6*I6))) | L6: =IF(G6="Net",F6,K6*(1-H6*I6)) | M6: =IF(K6=0,0,1-L6/K6) | N6: Medium | O6: Epoch AI 'How do Chinese AI companies make money?' (Oct-2026); Reuters Breakingviews (Jul-2026) | P6: Epoch est. ~$1B run rate, mostly first-party API (Reuters had $400-500M in Jul-2026). Est. API gross margin 70-80%. Only ~8% of OpenRouter spend on DeepSeek models flows to DeepSeek -> implied total ecosystem spend on the model family ~$12B+ (memo). Third-party hosts pay DeepSeek nothing.
A7: Alibaba (Qwen) | B7: Qwen3.x (small/mid open; Qwen3.7-Max proprietary) | C7: Mixed (open small tiers; closed flagship) | D7: Y | E7: Aug-2026 | F7: 2.4 | G7: Gross | H7: 0 | I7: 0 | K7: =IF(J7<>"",J7,IF(G7="Gross",F7,F7/(1-H7*I7))) | L7: =IF(G7="Net",F7,K7*(1-H7*I7)) | M7: =IF(K7=0,0,1-L7/K7) | N7: Medium | O7: Epoch AI (Model Studio / MaaS annualized); Alibaba Q2-FY27 results | P7: Model-and-application-services (MaaS) run rate; includes third-party model hosting on Model Studio (Bailian), so overstates Qwen-only revenue. Alibaba AI Cloud & Compute revenue was $7.1B in the Jun-2026 quarter (not model revenue). First-party cloud sale -> gross = net.
A8: Z.ai (Zhipu) | B8: GLM-5 / GLM-5.2 (MIT) | C8: Open (MIT) | D8: Y | E8: Sep-2026 | F8: 1.8 | G8: Gross | H8: 0 | I8: 0 | K8: =IF(J8<>"",J8,IF(G8="Gross",F8,F8/(1-H8*I8))) | L8: =IF(G8="Net",F8,K8*(1-H8*I8)) | M8: =IF(K8=0,0,1-L8/K8) | N8: Low | O8: Epoch AI (management ARR); Zhipu H1-2026 interim report (HKEX) | P8: Management-cited $1.8B ARR conflicts with reported H1-2026 revenue of RMB954M (~$142M); Epoch's interim-based 2026 estimate is ~$0.87B (API $805M + enterprise $60M). API gross margin 24.6% in H1-2026. ~25% of GLM-5 tokens served via Z.ai's own API (rest via third-party hosts).
A9: Moonshot AI (Kimi) | B9: Kimi K3 (Modified MIT) | C9: Open (Modified MIT) | D9: Y | E9: Aug-2026 | F9: 1 | G9: Gross | H9: 0 | I9: 0 | K9: =IF(J9<>"",J9,IF(G9="Gross",F9,F9/(1-H9*I9))) | L9: =IF(G9="Net",F9,K9*(1-H9*I9)) | M9: =IF(K9=0,0,1-L9/K9) | N9: Medium | O9: Epoch AI; Reuters on K3 hosting revenue-share talks | P9: ~70% of revenue from model access (Jun-2026). ARR was >$200M in Apr and ~$300M in Jun-2026 before the K3 step-up. Seeking up to 30% revenue share on K3 hosted by Azure/AWS/GCP - would create a net-basis stream (Moonshot receives 30% of partner gross).
A10: MiniMax | B10: MiniMax M3 (open weights, non-commercial) | C10: Open (non-commercial) | D10: Y | E10: Aug-2026 | F10: 0.8 | G10: Gross | H10: 0 | I10: 0 | K10: =IF(J10<>"",J10,IF(G10="Gross",F10,F10/(1-H10*I10))) | L10: =IF(G10="Net",F10,K10*(1-H10*I10)) | M10: =IF(K10=0,0,1-L10/K10) | N10: Low | O10: Epoch AI (annualized from H1-2026 interim report); MiniMax HKEX filings | P10: H1-2026 revenue $116.6M (+283% YoY). Consumer app (Talkie) gross margin ~5% vs ~69% for enterprise services. Management run rate used; interim-based estimate ~$0.3B.
A11: Cohere | B11: Command A (open weights, CC-BY-NC) | C11: Open (non-commercial) | D11: Y | E11: May-2026 | F11: 0.5 | G11: Gross | H11: =Assumptions!$C$17 | I11: =Assumptions!$C$18 | K11: =IF(J11<>"",J11,IF(G11="Gross",F11,F11/(1-H11*I11))) | L11: =IF(G11="Net",F11,K11*(1-H11*I11)) | M11: =IF(K11=0,0,1-L11/K11) | N11: Low | O11: CNBC (13-Feb-2026 investor memo: $240M ARR FY2025); Presenc AI est. May-2026 | P11: Disclosed $240M ARR for 2025 (beat $200M target; ~70% gross margin). $500M is a third-party May-2026 estimate. Sells direct and via Oracle/Azure/AWS marketplaces - generic channel assumption applied.
A12: AI21 Labs | B12: Jamba (open weights) | C12: Open | D12: Y | E12: 2026E | F12: 0.35 | G12: Gross | H12: =Assumptions!$C$17 | I12: =Assumptions!$C$18 | K12: =IF(J12<>"",J12,IF(G12="Gross",F12,F12/(1-H12*I12))) | L12: =IF(G12="Net",F12,K12*(1-H12*I12)) | M12: =IF(K12=0,0,1-L12/K12) | N12: Low | O12: Presenc AI / Clink third-party estimates | P12: ESTIMATE - AI21 has never disclosed revenue. Generic channel assumption applied.
A13: Meta (Llama) | B13: Llama 4 (community license) | C13: Open (community license, 700M MAU cap) | D13: Y | E13: 2026 | F13: 0 | G13: Gross | H13: 0 | I13: 0 | K13: =IF(J13<>"",J13,IF(G13="Gross",F13,F13/(1-H13*I13))) | L13: =IF(G13="Net",F13,K13*(1-H13*I13)) | M13: =IF(K13=0,0,1-L13/K13) | N13: High | O13: Meta Llama Community License; Licenseware | P13: Royalty-free: $0 direct licensing ARR. Meta has undisclosed revenue-share arrangements with some Llama hosts. Shown so open-weight totals reflect the largest US open-weight line. Meta's paid Muse Spark API is on the Frontier sheet.
A14: ByteDance (Doubao / Seed) | B14: Doubao (closed) / Seed-OSS (open) | C14: Mixed (flagship closed) | D14: N | E14: Jul-2026 | F14: 4 | G14: Gross | H14: 0 | I14: 0 | K14: =IF(J14<>"",J14,IF(G14="Gross",F14,F14/(1-H14*I14))) | L14: =IF(G14="Net",F14,K14*(1-H14*I14)) | M14: =IF(K14=0,0,1-L14/K14) | N14: Low | O14: Epoch AI (Volcano Engine MaaS ARR); IDC | P14: EXCLUDED from totals by default: flagship Doubao models are closed and the ~$4B Volcano Engine MaaS run rate includes third-party models (DeepSeek, Kimi, GLM). 2025 MaaS revenue was only ~$221M. Flip column D to 'Y' to include.
A15: Total (included rows) | D15: =COUNTIF(D5:D14,"Y") | K15: =SUMIF($D$5:$D$14,"Y",K5:K14) | L15: =SUMIF($D$5:$D$14,"Y",L5:L14) | M15: =IF(K15=0,0,1-L15/K15)
A18: Memo: open-weight inference hosts (where third-party spend on open models accrues; NOT model-lab ARR, excluded from totals)
A19: Provider | B19: Annualized ($B) | C19: Metric | D19: As of | E19: Note
A20: Fireworks AI | B20: 1 | C20: Annualized run rate | D20: Jul-2026 | E20: Company disclosed (>$1B; >40T tokens/day)
A21: Together AI | B21: 1 | C21: Annualized revenue (est.) | D21: Feb-2026 | E21: Sacra estimate; company cites >$1.15B annual bookings (Q2-2026)
A22: Baseten | B22: 0.6 | C22: Annualized revenue (est.) | D22: 2026 | E22: Third-party estimate
A23: fal | B23: 0.4 | C23: Annualized revenue (est.) | D23: 2026 | E23: Third-party estimate
A24: Total hosts (memo) | B24: =SUM(B20:B23)
A26: Memo: DeepSeek ecosystem spend implied by its ~8% capture of OpenRouter spend on its models ($B) | K26: =Open_Weight!F6/0.08 | L26: (Epoch AI; illustrative)

Sheet Assumptions
B2: Assumptions & inputs
B3: Blue = hard-coded input (editable). All $ in billions. As of 15-Oct-2026.
B5: OpenAI (reports NET)
B6: Microsoft revenue share on OpenAI revenue | C6: 0.2 | D6: Widely reported ~20% of ChatGPT + API revenue; OpenAI reports net of this. Continues to 2030 subject to a cap.
B7: Share of OpenAI billings subject to the MSFT share | C7: 1 | D7: Set to 100%: the share applies to OpenAI's total revenue, not just Azure channel sales.
B8: OpenAI gross ARR per investor gross-up ($B) | C8: 68 | D8: Sep-2026 figure shared with investors on Anthropic's gross methodology (CNBC/FT). Blank this cell to fall back to the model-based gross-up (= Net / (1 - share x rate)).
B9: OpenAI model-based gross ARR ($B) - cross-check | C9: =Frontier!F5/(1-C7*C6) | D9: Formula: reported net / (1 - channel share x take rate).
B11: Anthropic (reports GROSS)
B12: Channel share of billings via cloud marketplaces | C12: 0.47 | D12: 2025 actual from IPO prospectus ($2.16B of ~$4.6B). Trend: 11% (2023) -> 32% (2024) -> 47% (2025); likely higher in 2026.
B13: Blended partner take rate on marketplace sales | C13: 0.16 | D13: 2025 realized: ~$351M fees / $2.16B marketplace sales. SemiAnalysis puts Anthropic's Bedrock share at ~75% (25% take) on newer deals.
B14: Implied gross-to-net haircut | C14: =C12*C13 | D14: Channel share x take rate.
B16: Generic open-weight lab channel assumption (Mistral, Cohere, AI21)
B17: Assumed channel share of billings via marketplaces | C17: 0.25 | D17: ASSUMPTION - none of these labs disclose the marketplace share of sales. Set to 0% to treat as fully direct.
B18: Assumed partner take rate | C18: 0.2 | D18: ASSUMPTION - typical hyperscaler marketplace resale cut is 20-30%; Anthropic realized ~16% in 2025.
B19: Implied gross-to-net haircut | C19: =C17*C18
B21: Memo: BofA estimate of Anthropic hyperscaler payouts ($B)
B22: 2025E payouts | C22: 1.9 | D22: BofA, Mar-2026. Note: broader than the $351M of distribution fees disclosed in the prospectus (likely includes other cost-sharing).
B23: 2026E payouts | C23: 6.4 | D23: BofA, Mar-2026 ('up to').
B24: 2026E payouts as % of YE-2026 $110B run rate | C24: =C23/110 | D24: Alternative haircut lens; compare with C14.

Sheet Anthropic_Sensitivity
B2: Anthropic net ARR sensitivity ($B)
B3: Net ARR = Gross ARR x (1 - channel share x partner take rate). Gross ARR links to the Frontier sheet.
B5: Gross ARR ($B) | C5: =Frontier!K6
B7: Channel share \ Partner take rate | C7: 0.12 | D7: 0.16 | E7: 0.2 | F7: 0.25 | G7: 0.3
B8: 0.35 | C8: =$C$5*(1-$B8*C$7) | D8: =$C$5*(1-$B8*D$7) | E8: =$C$5*(1-$B8*E$7) | F8: =$C$5*(1-$B8*F$7) | G8: =$C$5*(1-$B8*G$7)
B9: 0.47 | C9: =$C$5*(1-$B9*C$7) | D9: =$C$5*(1-$B9*D$7) | E9: =$C$5*(1-$B9*E$7) | F9: =$C$5*(1-$B9*F$7) | G9: =$C$5*(1-$B9*G$7)
B10: 0.55 | C10: =$C$5*(1-$B10*C$7) | D10: =$C$5*(1-$B10*D$7) | E10: =$C$5*(1-$B10*E$7) | F10: =$C$5*(1-$B10*F$7) | G10: =$C$5*(1-$B10*G$7)
B11: 0.6 | C11: =$C$5*(1-$B11*C$7) | D11: =$C$5*(1-$B11*D$7) | E11: =$C$5*(1-$B11*E$7) | F11: =$C$5*(1-$B11*F$7) | G11: =$C$5*(1-$B11*G$7)
B12: 0.7 | C12: =$C$5*(1-$B12*C$7) | D12: =$C$5*(1-$B12*D$7) | E12: =$C$5*(1-$B12*E$7) | F12: =$C$5*(1-$B12*F$7) | G12: =$C$5*(1-$B12*G$7)
B14: Haircut (1 - Net/Gross)
B15: Channel share \ Partner take rate | C15: 0.12 | D15: 0.16 | E15: 0.2 | F15: 0.25 | G15: 0.3
B16: 0.35 | C16: =$B16*C$15 | D16: =$B16*D$15 | E16: =$B16*E$15 | F16: =$B16*F$15 | G16: =$B16*G$15
B17: 0.47 | C17: =$B17*C$15 | D17: =$B17*D$15 | E17: =$B17*E$15 | F17: =$B17*F$15 | G17: =$B17*G$15
B18: 0.55 | C18: =$B18*C$15 | D18: =$B18*D$15 | E18: =$B18*E$15 | F18: =$B18*F$15 | G18: =$B18*G$15
B19: 0.6 | C19: =$B19*C$15 | D19: =$B19*D$15 | E19: =$B19*E$15 | F19: =$B19*F$15 | G19: =$B19*G$15
B20: 0.7 | C20: =$B20*C$15 | D20: =$B20*D$15 | E20: =$B20*E$15 | F20: =$B20*F$15 | G20: =$B20*G$15
B23: Reference points
B24: Base case (prospectus 2025: 47% share x 16% take) | C24: =Frontier!L6
B25: Share of 2025 billings via marketplaces | C25: =Assumptions!C12
B26: 2025 realized take rate | C26: =Assumptions!C13
B27: BofA 2026E payouts / $110B YE run rate | C27: =Assumptions!C24
B28: OpenAI implied haircut (1 - 50/68) for comparison | C28: =Frontier!M5

Sheet Methodology
B2: Methodology & definitions
B4: Definitions
B5: ARR / annualized run rate: the most recent month's (or quarter's) revenue extrapolated to a year. Labs disclose these to investors or the press; none are audited annual revenue. Where only quarterly revenue exists, x4 is shown in the notes, not in the ARR column.
B6: Gross ARR: annualized value of end-customer billings for the lab's models, including sales that clear through cloud marketplaces (AWS Bedrock, Google Vertex / Gemini Enterprise Agent Platform, Azure Foundry) or other distribution partners at full value. This is Anthropic's GAAP presentation (lab is the principal; partner fee is an S&M expense).
B7: Net ARR: annualized revenue retained by the lab after the distribution partner's revenue share. This is OpenAI's GAAP presentation (reports net of the ~20% Microsoft share).
B8: Gross-to-net haircut: 1 - Net / Gross = channel share of billings x partner take rate.
B10: Calculation logic (Frontier and Open_Weight sheets)
B11: Gross ARR = Gross override if provided; otherwise the reported figure if the basis is 'Gross'; otherwise reported net / (1 - channel share x take rate).
B12: Net ARR = reported figure if the basis is 'Net'; otherwise Gross ARR x (1 - channel share x take rate).
B13: Rows with 'N' in the Include column are excluded from totals and the Summary via SUMIF. Totals are not adjusted for differing 'As of' dates.
B15: Classification
B16: Frontier (closed-weight): labs whose flagship models are API/subscription-only - OpenAI, Anthropic, Google DeepMind, xAI, Meta (Muse Spark, closed since Apr-2026).
... B29: Generic 25% channel / 20% take assumption for Mistral, Cohere and AI21 is a placeholder; set Assumptions!C17 to 0% to treat them as fully direct.

Sheet Sources
B2: Sources
B3: Accessed 15-Oct-2026.
B5: Data point | C5: Outlet | D5: URL
B6: OpenAI $50B net ARR; $68-70B gross-up | C6: Reuters via Investing.com | D6: https://www.investing.com/news/stock-market-news/openais-annualized-revenue-20-billion-less-than-previously-signaled-ft-reports-4939854
B7: OpenAI $50B vs $68B gross partner revenue | C7: CNBC | D7: https://www.cnbc.com/2026/10/08/open-ai-revenue-nvidia-oracle-coreweave.html
B8: OpenAI / Anthropic revenue accounting difference | C8: Axios | D8: https://www.axios.com/2026/10/08/openai-50-billion-arr-anthropic-revenue-accounting
B9: OpenAI expects >=$70B ARR by YE-2026 | C9: Bloomberg via Yahoo Finance | D9: https://finance.yahoo.com/technology/ai/articles/openai-expects-70-billion-annualized-014338719.html
B10: OpenAI 20% Microsoft revenue share; net reporting | C10: TechCrunch | D10: https://techcrunch.com/2025/11/14/leaked-documents-shed-light-into-how-much-openai-pays-microsoft/
B11: OpenAI-Microsoft amended agreement (rev share to 2030, capped) | C11: OpenAI | D11: https://openai.com/index/next-phase-of-microsoft-partnership/
B12: Net vs gross reporting conventions; BofA $6.4B 2026 payout est. | C12: Forbes | D12: https://www.forbes.com/sites/josipamajic/2026/03/25/openai-and-anthropic-count-revenue-differently-and-investors-are-looking-into-it/
B13: Anthropic $65B run rate (end-Jul-2026) | C13: Reuters | D13: https://www.reuters.com/technology/anthropic-revenue-run-rate-tops-65-billion-source-says-2026-08-17/
B14: Anthropic Q2-2026 revenue $11.5B | C14: Axios | D14: https://www.axios.com/2026/08/17/anthropic-revenue-run-rate-ipo-openai
B15: Anthropic Q3-2026 revenue $16.8B; $110B YE target | C15: CNBC | D15: https://www.cnbc.com/2026/10/15/anthropics-third-quarter-revenue-hits-16point8-billion-ipo.html
B16: Anthropic prospectus: 47% via marketplaces, $351M fees | C16: Reuters via Investing.com | D16: https://www.investing.com/news/stock-market-news/exclusiveanthropic-ipo-prospectus-lays-bare-deep-dependence-on-big-tech-partners-4923585
... B35: Together AI $1B annualized est. | C35: Sacra | D35: https://sacra.com/c/together-ai/
