Workbook

Sheet Cover
A1: Anthropic, PBC – Three-Statement Financial Model
A2: Revenue, training vs. inference compute, income statement, balance sheet and cash flow | FY2023A–FY2030E | USD millions
A4: Purpose
A5: Integrated 3-statement model for Anthropic built off the Form S-1 (filed 26 Oct 2026, Nasdaq: ANT) and subsequent investor disclosures. The core analytical question is how revenue scales against the compute bill, split between inference (serving customers) and training/research.
A7: Structure
A8: 1. Summary – key outputs, charts and a valuation snapshot (fiscal-year view).
A9: 2. Assumptions – all forecast drivers. Scenario switch (cell C4): 1 = Base, 2 = Bull, 3 = Bear. Blue cells are inputs.
A10: 3. Revenue Build – total revenue (Q4'26 off the disclosed Q3'26 run-rate, then annual growth), consumption vs. subscription mix, marketplace vs. direct.
A11: 4. Compute Build – inference compute (paid, free-tier, internal) vs. training & research compute, with a take-or-pay floor from contracted minimums.
A12: 5. Opex Build – personnel (headcount × cash comp + SBC), channel-partner fees, marketing, other opex, D&A, and the functional (CoR / R&D / S&M / G&A) allocation.
A13: 6. Income Statement – GAAP functional presentation, memo by nature of expense, non-GAAP adjusted operating income / EBITDA.
A14: 7. Balance Sheet – rolls from the Jun-26A filed balance sheet; convertible notes and preferred stock convert to common at the IPO (H2'26E).
... A36: This model is for research and illustration. Forecasts are the author's assumptions, not company guidance.

Sheet Summary
A1: Summary – key outputs (fiscal-year view)
A2: Active scenario shown below (switch it on Assumptions!C4). Charts update with the Assumptions sheet.
A4: Active scenario | C4: ='Assumptions'!$C$4 | D4: =CHOOSE('Assumptions'!$C$4,"Base","Bull","Bear")
A6: $M unless noted in label | B6: FY2023A | C6: FY2024A | D6: FY2025A | E6: FY2026E | F6: FY2027E | G6: FY2028E | H6: FY2029E | I6: FY2030E
A8: Growth
A9: Revenue | B9: ='Income Statement'!C8 | C9: ='Income Statement'!D8 | D9: ='Income Statement'!E8 | E9: ='Income Statement'!H8 | F9: ='Income Statement'!I8 | G9: ='Income Statement'!J8 | H9: ='Income Statement'!K8 | I9: ='Income Statement'!L8
A10: YoY growth (%) | C10: =C9/B9-1 | D10: =D9/C9-1 | E10: =E9/D9-1 | F10: =F9/E9-1 | G10: =G9/F9-1 | H10: =H9/G9-1 | I10: =I9/H9-1
A11: Year-end headcount (FTE) | B11: ='Opex Build'!C8 | C11: ='Opex Build'!D8 | D11: ='Opex Build'!E8 | E11: ='Opex Build'!H8 | F11: ='Opex Build'!I8 | G11: ='Opex Build'!J8 | H11: ='Opex Build'!K8 | I11: ='Opex Build'!L8
A13: Compute – training vs. inference
A14: Inference compute (paid + free-tier + internal) | B14: ='Compute Build'!C13 | C14: ='Compute Build'!D13 | D14: ='Compute Build'!E13 | E14: ='Compute Build'!H13 | F14: ='Compute Build'!I13 | G14: ='Compute Build'!J13 | H14: ='Compute Build'!K13 | I14: ='Compute Build'!L13
A15: Training & research compute (incl. take-or-pay shortfall) | B15: ='Income Statement'!C33 | C15: ='Income Statement'!D33 | D15: ='Income Statement'!E33 | E15: ='Income Statement'!H33 | F15: ='Income Statement'!I33 | G15: ='Income Statement'!J33 | H15: ='Income Statement'!K33 | I15: ='Income Statement'!L33
A16: Total compute & infrastructure | B16: ='Compute Build'!C26 | C16: ='Compute Build'!D26 | D16: ='Compute Build'!E26 | E16: ='Compute Build'!H26 | F16: ='Compute Build'!I26 | G16: ='Compute Build'!J26 | H16: ='Compute Build'!K26 | I16: ='Compute Build'!L26
A17: Compute as % of revenue | B17: ='Compute Build'!C29 | C17: ='Compute Build'!D29 | D17: ='Compute Build'!E29 | E17: ='Compute Build'!H29 | F17: ='Compute Build'!I29 | G17: ='Compute Build'!J29 | H17: ='Compute Build'!K29 | I17: ='Compute Build'!L29
A18: Training & research share of compute (%) | B18: ='Compute Build'!C32 | C18: ='Compute Build'!D32 | D18: ='Compute Build'!E32 | E18: ='Compute Build'!H32 | F18: ='Compute Build'!I32 | G18: ='Compute Build'!J32 | H18: ='Compute Build'!K32 | I18: ='Compute Build'!L32
A19: Revenue per $1 of compute (x) | B19: ='Compute Build'!C30 | C19: ='Compute Build'!D30 | D19: ='Compute Build'!E30 | E19: ='Compute Build'!H30 | F19: ='Compute Build'!I30 | G19: ='Compute Build'!J30 | H19: ='Compute Build'!K30 | I19: ='Compute Build'!L30
A21: Profitability
A22: Gross margin (functional, %) | B22: ='Income Statement'!C12 | C22: ='Income Statement'!D12 | D22: ='Income Statement'!E12 | E22: ='Income Statement'!H12 | F22: ='Income Statement'!I12 | G22: ='Income Statement'!J12 | H22: ='Income Statement'!K12 | I22: ='Income Statement'!L12
A23: Operating income (loss) – GAAP | B23: ='Income Statement'!C18 | C23: ='Income Statement'!D18 | D23: ='Income Statement'!E18 | E23: ='Income Statement'!H18 | F23: ='Income Statement'!I18 | G23: ='Income Statement'!J18 | H23: ='Income Statement'!K18 | I23: ='Income Statement'!L18
A24: GAAP operating margin (%) | B24: ='Income Statement'!C19 | C24: ='Income Statement'!D19 | D24: ='Income Statement'!E19 | E24: ='Income Statement'!H19 | F24: ='Income Statement'!I19 | G24: ='Income Statement'!J19 | H24: ='Income Statement'!K19 | I24: ='Income Statement'!L19
A25: Adjusted operating income (ex-SBC, donation matching, Bartz) | B25: ='Income Statement'!C44 | C25: ='Income Statement'!D44 | D25: ='Income Statement'!E44 | E25: ='Income Statement'!H44 | F25: ='Income Statement'!I44 | G25: ='Income Statement'!J44 | H25: ='Income Statement'!K44 | I25: ='Income Statement'!L44
A26: Adjusted operating margin (%) | B26: ='Income Statement'!C45 | C26: ='Income Statement'!D45 | D26: ='Income Statement'!E45 | E26: ='Income Statement'!H45 | F26: ='Income Statement'!I45 | G26: ='Income Statement'!J45 | H26: ='Income Statement'!K45 | I26: ='Income Statement'!L45
A27: Net income (loss) – GAAP | B27: ='Income Statement'!C26 | C27: ='Income Statement'!D26 | D27: ='Income Statement'!E26 | E27: ='Income Statement'!H26 | F27: ='Income Statement'!I26 | G27: ='Income Statement'!J26 | H27: ='Income Statement'!K26 | I27: ='Income Statement'!L26
A28: Adjusted net income | B28: ='Income Statement'!C48 | C28: ='Income Statement'!D48 | D28: ='Income Statement'!E48 | E28: ='Income Statement'!H48 | F28: ='Income Statement'!I48 | G28: ='Income Statement'!J48 | H28: ='Income Statement'!K48 | I28: ='Income Statement'!L48
A30: Cash flow & balance sheet
A31: Operating cash flow | B31: ='Cash Flow'!C19 | C31: ='Cash Flow'!D19 | D31: ='Cash Flow'!E19 | E31: ='Cash Flow'!H19 | F31: ='Cash Flow'!I19 | G31: ='Cash Flow'!J19 | H31: ='Cash Flow'!K19 | I31: ='Cash Flow'!L19
A32: Free cash flow | B32: ='Cash Flow'!C45 | C32: ='Cash Flow'!D45 | D32: ='Cash Flow'!E45 | E32: ='Cash Flow'!H45 | F32: ='Cash Flow'!I45 | G32: ='Cash Flow'!J45 | H32: ='Cash Flow'!K45 | I32: ='Cash Flow'!L45
A33: FCF margin (%) | B33: ='Cash Flow'!C46 | C33: ='Cash Flow'!D46 | D33: ='Cash Flow'!E46 | E33: ='Cash Flow'!H46 | F33: ='Cash Flow'!I46 | G33: ='Cash Flow'!J46 | H33: ='Cash Flow'!K46 | I33: ='Cash Flow'!L46
A34: Cash & short-term investments (year-end) | B34: ='Balance Sheet'!C8 | C34: ='Balance Sheet'!D8 | D34: ='Balance Sheet'!E8 | E34: ='Balance Sheet'!H8 | F34: ='Balance Sheet'!I8 | G34: ='Balance Sheet'!J8 | H34: ='Balance Sheet'!K8 | I34: ='Balance Sheet'!L8
A35: Total equity incl. preferred (year-end) | B35: ='Balance Sheet'!C33 | C35: ='Balance Sheet'!D33 | D35: ='Balance Sheet'!E33 | E35: ='Balance Sheet'!H33 | F35: ='Balance Sheet'!I33 | G35: ='Balance Sheet'!J33 | H35: ='Balance Sheet'!K33 | I35: ='Balance Sheet'!L33
A37: Valuation snapshot (illustrative)
A38: Assumed equity value at IPO ($M) – input | B38: 1500000 | M38: Press reports: $1.5–2.0T discussed; the S-1 price range is blank.
A39: Implied enterprise value (equity value – Dec-26E cash & STI + debt) | B39: =B38-'Balance Sheet'!G8+'Balance Sheet'!G24
A40: EV / revenue (x) | E40: =IF('Income Statement'!H8>0,$B$39/'Income Statement'!H8,"n.m.") | F40: =IF('Income Statement'!I8>0,$B$39/'Income Statement'!I8,"n.m.") | G40: =IF('Income Statement'!J8>0,$B$39/'Income Statement'!J8,"n.m.") | H40: =IF('Income Statement'!K8>0,$B$39/'Income Statement'!K8,"n.m.") | I40: =IF('Income Statement'!L8>0,$B$39/'Income Statement'!L8,"n.m.")
A41: EV / adjusted operating income (x) | E41: =IF('Income Statement'!H44>0,$B$39/'Income Statement'!H44,"n.m.") | F41: =IF('Income Statement'!I44>0,$B$39/'Income Statement'!I44,"n.m.") | G41: =IF('Income Statement'!J44>0,$B$39/'Income Statement'!J44,"n.m.") | H41: =IF('Income Statement'!K44>0,$B$39/'Income Statement'!K44,"n.m.") | I41: =IF('Income Statement'!L44>0,$B$39/'Income Statement'!L44,"n.m.")
A42: Equity value / free cash flow (x) | E42: =IF('Cash Flow'!H45>0,$B$38/'Cash Flow'!H45,"n.m.") | F42: =IF('Cash Flow'!I45>0,$B$38/'Cash Flow'!I45,"n.m.") | G42: =IF('Cash Flow'!J45>0,$B$38/'Cash Flow'!J45,"n.m.") | H42: =IF('Cash Flow'!K45>0,$B$38/'Cash Flow'!K45,"n.m.") | I42: =IF('Cash Flow'!L45>0,$B$38/'Cash Flow'!L45,"n.m.")

Sheet Assumptions
A1: Assumptions & Drivers
A2: Blue = input. Yellow rows are the live scenario-selected drivers used by the model.
A4: Scenario switch (1 = Base, 2 = Bull, 3 = Bear) | C4: 1 | D4: =CHOOSE(C4,"Base","Bull","Bear") | M4: Change this cell to flip every scenario-driven input in the model.
A6: $M unless noted | B6: Unit | C6: FY2023A | D6: FY2024A | E6: FY2025A | F6: H1'26A | G6: H2'26E | H6: FY2026E | I6: FY2027E | J6: FY2028E | K6: FY2029E | L6: FY2030E | M6: Notes / source
C7: Actual | D7: Actual | E7: Actual | F7: Actual | G7: Forecast | H7: H1A + H2E | I7: Forecast | J7: Forecast | K7: Forecast | L7: Forecast
A9: Period
A10: Period length (fraction of a year) | B10: yrs | C10: 1 | D10: 1 | E10: 1 | F10: 0.5 | G10: 0.5 | H10: 1 | I10: 1 | J10: 1 | K10: 1 | L10: 1 | M10: Used to annualise stub-period flows for balance-sheet ratios, interest and personnel cost.
A12: Revenue
A13: Q4'26 revenue growth vs. Q3'26 (QoQ) – Base | B13: % | G13: 0.15
A14: Q4'26 revenue growth vs. Q3'26 (QoQ) – Bull | B14: % | G14: 0.25
A15: Q4'26 revenue growth vs. Q3'26 (QoQ) – Bear | B15: % | G15: 0.05
A16: Q4'26 revenue growth vs. Q3'26 (QoQ) – LIVE (selected scenario) | B16: % | G16: =CHOOSE($C$4,G13,G14,G15) | M16: Q3'26 revenue $16.8B (+45% QoQ) disclosed 14 Oct 2026. Run-rate ~$70–74B (Oct) implies Q4 ≈ $18–19B.
A17: Total revenue growth (YoY) – Base | B17: % | I17: 0.95 | J17: 0.5 | K17: 0.32 | L17: 0.22
A18: Total revenue growth (YoY) – Bull | B18: % | I18: 1.3 | J18: 0.65 | K18: 0.4 | L18: 0.28
A19: Total revenue growth (YoY) – Bear | B19: % | I19: 0.55 | J19: 0.28 | K19: 0.18 | L19: 0.12
A20: Total revenue growth (YoY) – LIVE (selected scenario) | B20: % | I20: =CHOOSE($C$4,I17,I18,I19) | J20: =CHOOSE($C$4,J17,J18,J19) | K20: =CHOOSE($C$4,K17,K18,K19) | L20: =CHOOSE($C$4,L17,L18,L19) | M20: Growth decelerates from +1,088% (FY25) as the base scales; S-1 warns growth will not continue at comparable rates.
A21: Subscription revenue as % of total | B21: % | G21: 0.2 | I21: 0.2 | J21: 0.21 | K21: 0.22 | L21: 0.22 | M21: H1'26: 20% subscription / 80% consumption (filed). Consumer & team plans (Pro, Max, Team, Enterprise seats).
A22: Revenue via cloud marketplaces (AWS / GCP / Azure) as % of total | B22: % | G22: 0.48 | I22: 0.47 | J22: 0.45 | K22: 0.43 | L22: 0.41 | M22: H1'26: 48% (filed). Recognised gross; channel-partner fees sit in S&M.
A24: Compute – inference (serving)
A25: Paid inference compute as % of consumption revenue – Base | B25: % | G25: 0.1 | I25: 0.105 | J25: 0.1 | K25: 0.095 | L25: 0.09
A26: Paid inference compute as % of consumption revenue – Bull | B26: % | G26: 0.095 | I26: 0.095 | J26: 0.09 | K26: 0.085 | L26: 0.08
A27: Paid inference compute as % of consumption revenue – Bear | B27: % | G27: 0.11 | I27: 0.125 | J27: 0.125 | K27: 0.12 | L27: 0.115
A28: Paid inference compute as % of consumption revenue – LIVE (selected scenario) | B28: % | G28: =CHOOSE($C$4,G25,G26,G27) | I28: =CHOOSE($C$4,I25,I26,I27) | J28: =CHOOSE($C$4,J25,J26,J27) | K28: =CHOOSE($C$4,K25,K26,K27) | L28: =CHOOSE($C$4,L25,L26,L27) | M28: ≈ 1 – API serving gross margin. H1'26 implied ~10% (CoR $2.38B 'substantially all' serving compute). S-1 flags near-term compression from higher-cost short-term capacity when demand exceeds contracted supply.
A29: Paid inference compute as % of subscription revenue – Base | B29: % | G29: 0.3 | I29: 0.29 | J29: 0.28 | K29: 0.27 | L29: 0.26
A30: Paid inference compute as % of subscription revenue – Bull | B30: % | G30: 0.28 | I30: 0.26 | J30: 0.24 | K30: 0.22 | L30: 0.2
A31: Paid inference compute as % of subscription revenue – Bear | B31: % | G31: 0.32 | I31: 0.33 | J31: 0.33 | K31: 0.32 | L31: 0.31
A32: Paid inference compute as % of subscription revenue – LIVE (selected scenario) | B32: % | G32: =CHOOSE($C$4,G29,G30,G31) | I32: =CHOOSE($C$4,I29,I30,I31) | J32: =CHOOSE($C$4,J29,J30,J31) | K32: =CHOOSE($C$4,K29,K30,K31) | L32: =CHOOSE($C$4,L29,L30,L31) | M32: Subscriptions are the less efficient slice of the inference pool (flat fee vs. heavy usage). SemiAnalysis est. ~50% compute margin on subs.
A33: Free-tier + internal-use inference as % of paid inference compute | B33: % | G33: 0.25 | I33: 0.25 | J33: 0.25 | K33: 0.25 | L33: 0.25 | M33: Not disclosed; S-1 puts free-tier serving compute in S&M and internal Claude usage in R&D.
A34: of which free-tier (S&M) share; remainder is internal usage (R&D) | B34: % | C34: 0.4
A36: Compute – training & research
A37: Frontier training runs completed in period | B37: runs | G37: 1 | I37: 2 | J37: 2 | K37: 2 | L37: 2 | M37: Roughly two frontier-model generations per year.
A38: Compute cost per frontier training run – Base | B38: $M | G38: 5500 | I38: 7000 | J38: 10000 | K38: 13000 | L38: 16000
A39: Compute cost per frontier training run – Bull | B39: $M | G39: 6000 | I39: 8500 | J39: 12500 | K39: 16500 | L39: 20000
A40: Compute cost per frontier training run – Bear | B40: $M | G40: 5000 | I40: 6000 | J40: 8000 | K40: 10000 | L40: 12000
A41: Compute cost per frontier training run – LIVE (selected scenario) | B41: $M | G41: =CHOOSE($C$4,G38,G39,G40) | I41: =CHOOSE($C$4,I38,I39,I40) | J41: =CHOOSE($C$4,J38,J39,J40) | K41: =CHOOSE($C$4,K38,K39,K40) | L41: =CHOOSE($C$4,L38,L39,L40) | M41: Calibrated so H2'26E total compute ≈ $21B (Q3'26 at $1.70 revenue/$ compute ≈ $9.9B, Q4 higher as new capacity lands).
A42: Research, experimentation & post-training compute (multiple of frontier-run cost) | B42: x | G42: 1.7 | I42: 1.6 | J42: 1.5 | K42: 1.4 | L42: 1.3 | M42: Experiments, ablations, RL / post-training and safety research typically exceed the final pre-training run.
A43: Floor compute expense at non-cancellable contracted minimums (1 = on, 0 = off) | B43: flag | C43: 1 | M43: Take-or-pay: if contracted non-cancellable capacity exceeds modelled demand, the shortfall is expensed (shown in R&D as idle/research capacity).
A45: Personnel
A46: Year-end headcount | B46: FTE | D46: 940 | E46: 2700 | F46: 4300 | G46: 6000 | H46: =G46 | I46: 9000 | J46: 12000 | K46: 14500 | L46: 17000 | M46: Filed: ~940 (Dec-24), ~5,300 (Sep-26). Dec-25 and Jun-26 are estimates.
A47: Average cash compensation per employee (salary, bonus, benefits, payroll tax) | B47: $K/yr | G47: 550 | I47: 550 | J47: 566 | K47: 583 | L47: 601 | M47: H1'26 implied ≈ $550K annualised ((personnel $3,152M – SBC $2,185M) / avg. headcount).
A48: Stock-based compensation – ongoing | B48: $M | G48: 2600 | I48: 9000 | J48: 10000 | K48: 11000 | L48: 12000 | M48: H1'26 SBC $2,185M. Unrecognised RSU expense $26.6B at Jun-26 (performance condition met at IPO) plus new grants.
A49: Stock-based compensation – IPO RSU catch-up (one-off) | B49: $M | G49: 8000 | I49: 0 | J49: 0 | K49: 0 | L49: 0 | M49: Cumulative catch-up on RSUs whose liquidity-event condition is satisfied on IPO effectiveness.
A50: Personnel allocation – cost of revenue | B50: % | C50: 0.03
A51: Personnel allocation – R&D | B51: % | C51: 0.73
A52: Personnel allocation – S&M | B52: % | C52: 0.12
A53: Personnel allocation – G&A | B53: % | C53: 0.12 | M53: Allocations must sum to 100%. Majority of staff are research/engineering (S-1).
A55: Channel partners, marketing & other operating costs
A56: Channel-partner & partnership costs as % of marketplace revenue – Base | B56: % | G56: 0.34 | I56: 0.33 | J56: 0.32 | K56: 0.31 | L56: 0.3
A57: Channel-partner & partnership costs as % of marketplace revenue – Bull | B57: % | G57: 0.34 | I57: 0.32 | J57: 0.3 | K57: 0.28 | L57: 0.26
A58: Channel-partner & partnership costs as % of marketplace revenue – Bear | B58: % | G58: 0.36 | I58: 0.36 | J58: 0.36 | K58: 0.36 | L58: 0.36
A59: Channel-partner & partnership costs as % of marketplace revenue – LIVE (selected scenario) | B59: % | G59: =CHOOSE($C$4,G56,G57,G58) | I59: =CHOOSE($C$4,I56,I57,I58) | J59: =CHOOSE($C$4,J56,J57,J58) | K59: =CHOOSE($C$4,K56,K57,K58) | L59: =CHOOSE($C$4,L56,L57,L58) | M59: H1'26 'sales, marketing & partnerships' $3,168M = 19.5% of revenue; net of ~2% advertising, implies ~36% of marketplace revenue. Reuters: ~16c per marketplace $ in 2025, so partnership costs broadened in 2026.
A60: Advertising & marketing as % of revenue | B60: % | G60: 0.02 | I60: 0.02 | J60: 0.02 | K60: 0.02 | L60: 0.02 | M60: FY25 advertising $147M (3.2% of revenue); brand spend scaling with consumer push.
A61: Other operating & administrative as % of revenue (ex-donation matching, ex-D&A) | B61: % | G61: 0.08 | I61: 0.065 | J61: 0.055 | K61: 0.05 | L61: 0.045 | M61: H1'26: $1,588M ex-donation = 9.8% of revenue (data vendors, IT/cloud software, payment processing, facilities, legal, non-income taxes).
A62: Donation-matching programme expense (non-cash, settled in Class N shares) | B62: $M | G62: 2000 | I62: 1500 | J62: 1500 | K62: 1500 | L62: 1500 | M62: Q3'26: $2.0B recognised (S-1 subsequent events). FY25: $541M; Q1'26: $126M.
A63: Other opex allocation – cost of revenue | B63: % | C63: 0.05
A64: Other opex allocation – R&D (data / eval vendors) | B64: % | C64: 0.5
A65: Other opex allocation – S&M | B65: % | C65: 0.05
A66: Other opex allocation – G&A | B66: % | C66: 0.4 | M66: Allocations must sum to 100%.
A68: Capex & D&A (owned assets)
A69: Capital expenditure as % of revenue | B69: % | G69: 0.03 | I69: 0.03 | J69: 0.025 | K69: 0.025 | L69: 0.025 | M69: H1'26 capex $482M = 3.0% of revenue. Most compute is rented, so owned PP&E is small.
A70: D&A as % of (opening PP&E + ½ capex) | B70: % | C70: 0.35 | M70: 3–5 year useful lives; includes amortisation of acquired intangibles.
A72: Working capital (balance as % of annualised period flow)
A73: Accounts receivable as % of annualised revenue | B73: % | G73: 0.16 | I73: 0.14 | J73: 0.13 | K73: 0.125 | L73: 0.12 | M73: Jun-26: $5,833M = 17.9% of annualised H1 revenue (inflated by in-period growth; ~46 days of Q2 revenue). Trends to ~45 DSO.
A74: Prepaid expenses & other current assets as % of annualised compute expense | B74: % | G74: 0.05 | I74: 0.05 | J74: 0.05 | K74: 0.05 | L74: 0.05 | M74: Largely prepaid cloud capacity. Jun-26: $496M; Dec-25: $2,560M (lumpy).
A75: Accounts payable & accrued as % of annualised cash operating costs | B75: % | G75: 0.15 | I75: 0.15 | J75: 0.15 | K75: 0.15 | L75: 0.15 | M75: Jun-26: $5,422M ≈ 18% of annualised H1 cash opex. Includes $1.2B Bartz settlement payable (instalments to Sep-27).
A76: Deferred revenue as % of annualised subscription revenue | B76: % | G76: 0.25 | I76: 0.25 | J76: 0.25 | K76: 0.25 | L76: 0.25 | M76: Jun-26: $1,650M = 25.6% of annualised H1 subscription revenue (prepaid annual plans).
A78: Financing, interest & tax
A79: IPO primary proceeds, net of fees | B79: $M | G79: 60000 | I79: 0 | J79: 0 | K79: 0 | L79: 0 | M79: Press reports: raise could exceed $100B including secondary; primary portion assumed $60B. S-1 share count / price are blank.
A80: Fair-value charge on convertible notes & other instruments before conversion | B80: $M | G80: 50000 | I80: 0 | J80: 0 | K80: 0 | L80: 0 | M80: Amazon notes ($6.2B principal) carried at $108.6B at Jun-26 on a $965B mark; a ~$1.5T IPO mark implies a further non-cash charge. Notes convert to Class N common at IPO, after which the charge stops.
A81: Proceeds from option exercises / ESPP | B81: $M | G81: 150 | I81: 300 | J81: 300 | K81: 300 | L81: 300
A82: Debt / supplier-financing drawdown (repayment) | B82: $M | G82: 0 | I82: 0 | J82: 0 | K82: 0 | L82: 0 | M82: Broadcom offered up to $42B of 9% PIK convertible notes to fund TPU rent – not drawn in the base case.
A83: Interest rate on debt | B83: % | C83: 0.09
A84: Yield on cash & short-term investments | B84: % | G84: 0.035 | I84: 0.0325 | J84: 0.03 | K84: 0.03 | L84: 0.03 | M84: Applied to opening cash & STI balance (avoids circularity). H1'26 interest income $1,111M.
A85: Blended statutory tax rate (federal + state) | B85: % | C85: 0.23
A86: Net operating loss carryforward at Jun-26A (estimate) | B86: $M | C86: 12000 | M86: Cumulative GAAP operating losses FY21–H1'26 ≈ $12B; fair-value charges are not deductible. 80% limitation ignored.
A87: Other / minimum taxes as % of revenue | B87: % | C87: 0.001

Sheet Revenue Build
A1: Revenue Build
A2: Q4'26 is grown off the disclosed Q3'26; FY2027E+ use annual growth rates. Mix splits feed the compute and channel-cost builds.
A4: $M unless noted | B4: Unit | C4: FY2023A | D4: FY2024A | E4: FY2025A | F4: H1'26A | G4: H2'26E | H4: FY2026E | I4: FY2027E | J4: FY2028E | K4: FY2029E | L4: FY2030E | M4: Notes / source
C5: Actual | D5: Actual | E5: Actual | F5: Actual | G5: Forecast | H5: H1A + H2E | I5: Forecast | J5: Forecast | K5: Forecast | L5: Forecast
A7: Quarterly bridge for the H2'26E stub
A8: Q3'26A revenue (disclosed) | B8: $M | G8: ='Historical Data'!J83 | M8: Reuters / FT / CNBC, 14 Oct 2026.
A9: Q4'26E revenue | B9: $M | G9: =G8*(1+'Assumptions'!G16)
A10: Implied Q4'26E exit run-rate (Q4 × 4) | B10: $M | G10: =G9*4 | M10: Compare: ~$65B at end-July 2026; third-party estimates ~$70–74B for October.
A12: Total revenue
A13: Total revenue | B13: $M | C13: ='Historical Data'!C8 | D13: ='Historical Data'!D8 | E13: ='Historical Data'!E8 | F13: ='Historical Data'!F8 | G13: =G8+G9 | H13: =F13+G13 | I13: =H13*(1+'Assumptions'!I20) | J13: =I13*(1+'Assumptions'!J20) | K13: =J13*(1+'Assumptions'!K20) | L13: =K13*(1+'Assumptions'!L20)
A14: YoY growth | B14: % | D14: =D13/C13-1 | E14: =E13/D13-1 | G14: =G13/('Historical Data'!E8-'Historical Data'!$C$88)-1 | H14: =H13/E13-1 | I14: =I13/H13-1 | J14: =J13/I13-1 | K14: =K13/J13-1 | L14: =L13/K13-1 | M14: H2'26E growth is vs. H2'25A (FY25 less H1'25 = $3,422M).
A15: Sequential growth (H2 vs. H1) | B15: % | G15: =G13/F13-1
A17: Mix – consumption vs. subscription
A18: Consumption-based revenue (API, Claude Code, agents) | B18: $M | C18: ='Historical Data'!C9 | D18: ='Historical Data'!D9 | E18: ='Historical Data'!E9 | F18: ='Historical Data'!F9 | G18: =G13*(1-'Assumptions'!G21) | H18: =F18+G18 | I18: =I13*(1-'Assumptions'!I21) | J18: =J13*(1-'Assumptions'!J21) | K18: =K13*(1-'Assumptions'!K21) | L18: =L13*(1-'Assumptions'!L21)
A19: Subscription-based revenue (Pro, Max, Team, Enterprise seats) | B19: $M | C19: ='Historical Data'!C10 | D19: ='Historical Data'!D10 | E19: ='Historical Data'!E10 | F19: ='Historical Data'!F10 | G19: =G13*'Assumptions'!G21 | H19: =F19+G19 | I19: =I13*'Assumptions'!I21 | J19: =J13*'Assumptions'!J21 | K19: =K13*'Assumptions'!K21 | L19: =L13*'Assumptions'!L21
A20: Subscription share of revenue | B20: % | C20: =C19/C13 | D20: =D19/D13 | E20: =E19/E13 | F20: =F19/F13 | G20: =G19/G13 | H20: =H19/H13 | I20: =I19/I13 | J20: =J19/J13 | ... L20: =L19/L13
A21: Consumption revenue growth (YoY) | B21: % | D21: =D18/C18-1 | E21: =E18/D18-1 | H21: =H18/E18-1 | I21: =I18/H18-1 | J21: =J18/I18-1 | K21: =K18/J18-1 | L21: =L18/K18-1
A22: Subscription revenue growth (YoY) | B22: % | D22: =D19/C19-1 | E22: =E19/D19-1 | H22: =H19/E19-1 | I22: =I19/H19-1 | J22: =J19/I19-1 | K22: =K19/J19-1 | L22: =L19/K19-1
A24: Mix – channel
A25: Revenue through cloud marketplaces (AWS Bedrock, Vertex AI, Azure Foundry) | B25: $M | F25: =F13*0.48 | G25: =G13*'Assumptions'!G22 | H25: =F25+G25 | I25: =I13*'Assumptions'!I22 | J25: =J13*'Assumptions'!J22 | K25: =K13*'Assumptions'!K22 | L25: =L13*'Assumptions'!L22 | M25: H1'26: 48% of revenue (filed). Recognised gross; partner fees in S&M.
A26: Direct revenue (first-party API, apps, subscriptions) | B26: $M | F26: =F13-F25 | G26: =G13-G25 | H26: =F26+G26 | I26: =I13-I25 | J26: =J13-J25 | K26: =K13-K25 | L26: =L13-L25
A28: Memo
A29: Revenue per average employee (annualised) | B29: $M/FTE | E29: =E13/AVERAGE('Assumptions'!D46,'Assumptions'!E46) | F29: =F13/'Assumptions'!F10/AVERAGE('Assumptions'!E46,'Assumptions'!F46) | G29: =G13/'Assumptions'!G10/AVERAGE('Assumptions'!F46,'Assumptions'!G46) | H29: =H13/AVERAGE('Assumptions'!E46,'Assumptions'!H46) | I29: =I13/'Assumptions'!I10/AVERAGE('Assumptions'!H46,'Assumptions'!I46) | J29: =J13/'Assumptions'!J10/AVERAGE('Assumptions'!I46,'Assumptions'!J46) | K29: =K13/'Assumptions'!K10/AVERAGE('Assumptions'!J46,'Assumptions'!K46) | L29: =L13/'Assumptions'!L10/AVERAGE('Assumptions'!K46,'Assumptions'!L46) | M29: S-1: TTM revenue per employee > $6.6M at Sep-26.

Sheet Compute Build
A1: Compute Build – Inference vs. Training
A2: Inference is driven by revenue × cost ratios; training & research by frontier runs × cost per run × research multiple. Historical split is an estimate anchored to filed cost of revenue (S-1 discloses only total compute).
A4: $M unless noted | B4: Unit | C4: FY2023A | D4: FY2024A | E4: FY2025A | F4: H1'26A | G4: H2'26E | H4: FY2026E | I4: FY2027E | J4: FY2028E | K4: FY2029E | L4: FY2030E | M4: Notes / source
C5: Actual | D5: Actual | E5: Actual | F5: Actual | G5: Forecast | H5: H1A + H2E | I5: Forecast | J5: Forecast | K5: Forecast | L5: Forecast
A7: Inference compute – customer-serving (cost of revenue)
A8: Paid inference – consumption revenue | B8: $M | G8: ='Revenue Build'!G18*'Assumptions'!G28 | H8: =F8+G8 | I8: ='Revenue Build'!I18*'Assumptions'!I28 | J8: ='Revenue Build'!J18*'Assumptions'!J28 | K8: ='Revenue Build'!K18*'Assumptions'!K28 | L8: ='Revenue Build'!L18*'Assumptions'!L28
A9: Paid inference – subscription revenue | B9: $M | G9: ='Revenue Build'!G19*'Assumptions'!G32 | H9: =F9+G9 | I9: ='Revenue Build'!I19*'Assumptions'!I32 | J9: ='Revenue Build'!J19*'Assumptions'!J32 | K9: ='Revenue Build'!K19*'Assumptions'!K32 | L9: ='Revenue Build'!L19*'Assumptions'!L32
A10: Total paid inference compute (in cost of revenue) | B10: $M | C10: ='Historical Data'!C26-'Assumptions'!$C$50*'Historical Data'!C12-'Assumptions'!$C$63*'Historical Data'!C15 | D10: ='Historical Data'!D26-'Assumptions'!$C$50*'Historical Data'!D12-'Assumptions'!$C$63*'Historical Data'!D15 | E10: ='Historical Data'!E26-'Assumptions'!$C$50*'Historical Data'!E12-'Assumptions'!$C$63*'Historical Data'!E15 | F10: ='Historical Data'!F26-'Assumptions'!$C$50*'Historical Data'!F12-'Assumptions'!$C$63*'Historical Data'!F15 | G10: =G8+G9 | H10: =F10+G10 | I10: =I8+I9 | J10: =J8+J9 | K10: =K8+K9 | L10: =L8+L9 | M10: Historical: cost of revenue less allocated personnel/other ('substantially all' CoR is serving compute).
A11: Free-tier inference (S&M) | B11: $M | C11: =C10*'Assumptions'!G33*'Assumptions'!$C$34 | D11: =D10*'Assumptions'!G33*'Assumptions'!$C$34 | E11: =E10*'Assumptions'!G33*'Assumptions'!$C$34 | F11: =F10*'Assumptions'!G33*'Assumptions'!$C$34 | G11: =G10*'Assumptions'!G33*'Assumptions'!$C$34 | H11: =F11+G11 | I11: =I10*'Assumptions'!I33*'Assumptions'!$C$34 | J11: =J10*'Assumptions'!J33*'Assumptions'!$C$34 | K11: =K10*'Assumptions'!K33*'Assumptions'!$C$34 | L11: =L10*'Assumptions'!L33*'Assumptions'!$C$34 | M11: Historical uses the H2'26E ratio – estimate.
A12: Internal-usage inference (R&D) | B12: $M | C12: =C10*'Assumptions'!G33*(1-'Assumptions'!$C$34) | D12: =D10*'Assumptions'!G33*(1-'Assumptions'!$C$34) | E12: =E10*'Assumptions'!G33*(1-'Assumptions'!$C$34) | F12: =F10*'Assumptions'!G33*(1-'Assumptions'!$C$34) | G12: =G10*'Assumptions'!G33*(1-'Assumptions'!$C$34) | H12: =F12+G12 | I12: =I10*'Assumptions'!I33*(1-'Assumptions'!$C$34) | J12: =J10*'Assumptions'!J33*(1-'Assumptions'!$C$34) | K12: =K10*'Assumptions'!K33*(1-'Assumptions'!$C$34) | L12: =L10*'Assumptions'!L33*(1-'Assumptions'!$C$34)
A13: Total inference compute | B13: $M | C13: =C10+C11+C12 | D13: =D10+D11+D12 | E13: =E10+E11+E12 | F13: =F10+F11+F12 | G13: =G10+G11+G12 | H13: =F13+G13 | I13: =I10+I11+I12 | J13: =J10+J11+J12 | K13: =K10+K11+K12 | L13: =L10+L11+L12
A15: Training & research compute (R&D)
A16: Frontier training runs | B16: runs | G16: ='Assumptions'!G37 | H16: =F16+G16 | I16: ='Assumptions'!I37 | J16: ='Assumptions'!J37 | K16: ='Assumptions'!K37 | L16: ='Assumptions'!L37
A17: Compute cost per frontier run | B17: $M | G17: ='Assumptions'!G41 | I17: ='Assumptions'!I41 | J17: ='Assumptions'!J41 | K17: ='Assumptions'!K41 | L17: ='Assumptions'!L41
A18: Frontier pre-training compute | B18: $M | G18: =G16*G17 | H18: =F18+G18 | I18: =I16*I17 | J18: =J16*J17 | K18: =K16*K17 | L18: =L16*L17
A19: Research, experimentation & post-training compute | B19: $M | G19: =G18*'Assumptions'!G42 | H19: =F19+G19 | I19: =I18*'Assumptions'!I42 | J19: =J18*'Assumptions'!J42 | K19: =K18*'Assumptions'!K42 | L19: =L18*'Assumptions'!L42
A20: Total training & research compute | B20: $M | C20: ='Historical Data'!C11-C13 | D20: ='Historical Data'!D11-D13 | E20: ='Historical Data'!E11-E13 | F20: ='Historical Data'!F11-F13 | G20: =G18+G19 | H20: =F20+G20 | I20: =I18+I19 | J20: =J18+J19 | K20: =K18+K19 | L20: =L18+L19 | M20: Historical: residual of filed total compute less estimated inference.
A22: Contracted capacity and total compute expense
A23: Driver-based compute demand (inference + training) | B23: $M | C23: =C13+C20 | D23: =D13+D20 | E23: =E13+E20 | F23: =F13+F20 | G23: =G13+G20 | H23: =F23+G23 | I23: =I13+I20 | J23: =J13+J20 | K23: =K13+K20 | L23: =L13+L20
A24: Estimated non-cancellable contracted minimums coming on-line | B24: $M | G24: ='Compute Commitments'!G17 | H24: =F24+G24 | I24: ='Compute Commitments'!I17 | J24: ='Compute Commitments'!J17 | K24: ='Compute Commitments'!K17 | L24: ='Compute Commitments'!L17 | M24: From the Compute Commitments sheet (estimated phasing of S-1 deal terms).
A25: Take-or-pay shortfall: contracted capacity above modelled demand (expensed in R&D) | B25: $M | G25: =IF('Assumptions'!$C$43=1,MAX(0,G24-G23),0) | H25: =F25+G25 | I25: =IF('Assumptions'!$C$43=1,MAX(0,I24-I23),0) | J25: =IF('Assumptions'!$C$43=1,MAX(0,J24-J23),0) | K25: =IF('Assumptions'!$C$43=1,MAX(0,K24-K23),0) | L25: =IF('Assumptions'!$C$43=1,MAX(0,L24-L23),0) | M25: Zero when demand ≥ contracted minimums. Capacity is expensed when available, whether or not customers use it.
A26: Total compute & infrastructure expense | B26: $M | C26: ='Historical Data'!C11 | D26: ='Historical Data'!D11 | E26: ='Historical Data'!E11 | F26: ='Historical Data'!F11 | G26: =G23+G25 | H26: =F26+G26 | I26: =I23+I25 | J26: =J23+J25 | K26: =K23+K25 | L26: =L23+L25
A28: Ratios
A29: Compute & infrastructure as % of revenue | B29: % | C29: =C26/'Revenue Build'!C13 | D29: =D26/'Revenue Build'!D13 | E29: =E26/'Revenue Build'!E13 | F29: =F26/'Revenue Build'!F13 | G29: =G26/'Revenue Build'!G13 | H29: =H26/'Revenue Build'!H13 | I29: =I26/'Revenue Build'!I13 | J29: =J26/'Revenue Build'!J13 | ... L29: =L26/'Revenue Build'!L13 | M29: FY25 160%; H1'26 55%; Q2'26 48%; Q3'26 ~59% ($1.70 revenue per $1).
A30: Revenue per $1 of compute | B30: x | C30: ='Revenue Build'!C13/C26 | D30: ='Revenue Build'!D13/D26 | E30: ='Revenue Build'!E13/E26 | F30: ='Revenue Build'!F13/F26 | G30: ='Revenue Build'!G13/G26 | H30: ='Revenue Build'!H13/H26 | I30: ='Revenue Build'!I13/I26 | J30: ='Revenue Build'!J13/J26 | ... L30: ='Revenue Build'!L13/L26
A31: Paid inference compute as % of revenue (1 – serving gross margin) | B31: % | C31: =C10/'Revenue Build'!C13 | D31: =D10/'Revenue Build'!D13 | E31: =E10/'Revenue Build'!E13 | F31: =F10/'Revenue Build'!F13 | G31: =G10/'Revenue Build'!G13 | H31: =H10/'Revenue Build'!H13 | I31: =I10/'Revenue Build'!I13 | J31: =J10/'Revenue Build'!J13 | ... L31: =L10/'Revenue Build'!L13
A32: Training & research share of total compute | B32: % | C32: =C20/C26 | D32: =D20/D26 | E32: =E20/E26 | F32: =F20/F26 | G32: =(G20+G25)/G26 | H32: =(H20+H25)/H26 | I32: =(I20+I25)/I26 | J32: =(J20+J25)/J26 | K32: =(K20+K25)/K26 | L32: =(L20+L25)/L26
A33: Inference share of total compute | B33: % | C33: =C13/C26 | D33: =D13/D26 | E33: =E13/E26 | F33: =F13/F26 | G33: =G13/G26 | H33: =H13/H26 | I33: =I13/I26 | J33: =J13/J26 | ... L33: =L13/L26
A34: Training & research compute as % of revenue | B34: % | C34: =C20/'Revenue Build'!C13 | D34: =D20/'Revenue Build'!D13 | E34: =E20/'Revenue Build'!E13 | F34: =F20/'Revenue Build'!F13 | G34: =(G20+G25)/'Revenue Build'!G13 | H34: =(H20+H25)/'Revenue Build'!H13 | I34: =(I20+I25)/'Revenue Build'!I13 | J34: =(J20+J25)/'Revenue Build'!J13 | K34: =(K20+K25)/'Revenue Build'!K13 | L34: =(L20+L25)/'Revenue Build'!L13
A35: Total compute growth (YoY) | B35: % | D35: =D26/C26-1 | E35: =E26/D26-1 | H35: =H26/E26-1 | I35: =I26/H26-1 | J35: =J26/I26-1 | K35: =K26/J26-1 | L35: =L26/K26-1

Sheet Opex Build
A1: Operating Expense Build
A2: Personnel, channel-partner fees, marketing, other operating costs and D&A, then allocated to GAAP functional lines.
A4: $M unless noted | B4: Unit | C4: FY2023A | D4: FY2024A | E4: FY2025A | F4: H1'26A | G4: H2'26E | H4: FY2026E | I4: FY2027E | J4: FY2028E | K4: FY2029E | L4: FY2030E | M4: Notes / source
C5: Actual | D5: Actual | E5: Actual | F5: Actual | G5: Forecast | H5: H1A + H2E | I5: Forecast | J5: Forecast | K5: Forecast | L5: Forecast
A7: Personnel
A8: Year-end headcount | B8: FTE | D8: ='Assumptions'!D46 | E8: ='Assumptions'!E46 | F8: ='Assumptions'!F46 | G8: ='Assumptions'!G46 | H8: =G8 | I8: ='Assumptions'!I46 | J8: ='Assumptions'!J46 | K8: ='Assumptions'!K46 | L8: ='Assumptions'!L46
A9: Average headcount | B9: FTE | E9: =AVERAGE(D8,E8) | F9: =AVERAGE(E8,F8) | G9: =AVERAGE(F8,G8) | H9: =AVERAGE(E8,H8) | I9: =AVERAGE(H8,I8) | J9: =AVERAGE(I8,J8) | K9: =AVERAGE(J8,K8) | L9: =AVERAGE(K8,L8)
A10: Stock-based compensation | B10: $M | C10: ='Historical Data'!C34 | D10: ='Historical Data'!D34 | E10: ='Historical Data'!E34 | F10: ='Historical Data'!F34 | G10: ='Assumptions'!G48+'Assumptions'!G49 | H10: =F10+G10 | I10: ='Assumptions'!I48+'Assumptions'!I49 | J10: ='Assumptions'!J48+'Assumptions'!J49 | K10: ='Assumptions'!K48+'Assumptions'!K49 | L10: ='Assumptions'!L48+'Assumptions'!L49
A11: Cash personnel cost (salary, bonus, benefits, payroll tax) | B11: $M | C11: ='Historical Data'!C12-C10 | D11: ='Historical Data'!D12-D10 | E11: ='Historical Data'!E12-E10 | F11: ='Historical Data'!F12-F10 | G11: =G9*'Assumptions'!G47/1000*'Assumptions'!G10 | H11: =F11+G11 | I11: =I9*'Assumptions'!I47/1000*'Assumptions'!I10 | J11: =J9*'Assumptions'!J47/1000*'Assumptions'!J10 | K11: =K9*'Assumptions'!K47/1000*'Assumptions'!K10 | L11: =L9*'Assumptions'!L47/1000*'Assumptions'!L10
A12: Implied cash comp per average employee | B12: $K/yr | E12: =E11/E9*1000 | F12: =F11/F9*1000/'Assumptions'!F10 | G12: =G11/G9*1000/'Assumptions'!G10 | H12: =H11/H9*1000 | I12: =I11/I9*1000/'Assumptions'!I10 | J12: =J11/J9*1000/'Assumptions'!J10 | K12: =K11/K9*1000/'Assumptions'!K10 | L12: =L11/L9*1000/'Assumptions'!L10
A13: Total personnel expense | B13: $M | C13: ='Historical Data'!C12 | D13: ='Historical Data'!D12 | E13: ='Historical Data'!E12 | F13: ='Historical Data'!F12 | G13: =G11+G10 | H13: =F13+G13 | I13: =I11+I10 | J13: =J11+J10 | K13: =K11+K10 | L13: =L11+L10
A15: Sales, marketing & partnerships
A16: Channel-partner & partnership costs (marketplace fees) | B16: $M | G16: ='Revenue Build'!G25*'Assumptions'!G59 | H16: =F16+G16 | I16: ='Revenue Build'!I25*'Assumptions'!I59 | J16: ='Revenue Build'!J25*'Assumptions'!J59 | K16: ='Revenue Build'!K25*'Assumptions'!K59 | L16: ='Revenue Build'!L25*'Assumptions'!L59
A17: Advertising & marketing | B17: $M | G17: ='Revenue Build'!G13*'Assumptions'!G60 | H17: =F17+G17 | I17: ='Revenue Build'!I13*'Assumptions'!I60 | J17: ='Revenue Build'!J13*'Assumptions'!J60 | K17: ='Revenue Build'!K13*'Assumptions'!K60 | L17: ='Revenue Build'!L13*'Assumptions'!L60
A18: Total sales, marketing & partnerships | B18: $M | C18: ='Historical Data'!C14 | D18: ='Historical Data'!D14 | E18: ='Historical Data'!E14 | F18: ='Historical Data'!F14 | G18: =G16+G17 | H18: =F18+G18 | I18: =I16+I17 | J18: =J16+J17 | K18: =K16+K17 | L18: =L16+L17
A19: as % of revenue | B19: % | C19: =C18/'Revenue Build'!C13 | D19: =D18/'Revenue Build'!D13 | E19: =E18/'Revenue Build'!E13 | F19: =F18/'Revenue Build'!F13 | G19: =G18/'Revenue Build'!G13 | H19: =H18/'Revenue Build'!H13 | I19: =I18/'Revenue Build'!I13 | J19: =J18/'Revenue Build'!J13 | ... L19: =L18/'Revenue Build'!L13
A21: Other operating & administrative
A22: Other operating & administrative (ex-donation, ex-D&A) | B22: $M | C22: ='Historical Data'!C15-'Historical Data'!C36-'Historical Data'!C35 | D22: ='Historical Data'!D15-'Historical Data'!D36-'Historical Data'!D35 | E22: ='Historical Data'!E15-'Historical Data'!E36-'Historical Data'!E35 | F22: ='Historical Data'!F15-'Historical Data'!F36-'Historical Data'!F35 | G22: ='Revenue Build'!G13*'Assumptions'!G61 | H22: =F22+G22 | I22: ='Revenue Build'!I13*'Assumptions'!I61 | J22: ='Revenue Build'!J13*'Assumptions'!J61 | K22: ='Revenue Build'!K13*'Assumptions'!K61 | L22: ='Revenue Build'!L13*'Assumptions'!L61
A23: Donation-matching programme expense (non-cash) | B23: $M | C23: ='Historical Data'!C36 | D23: ='Historical Data'!D36 | E23: ='Historical Data'!E36 | F23: ='Historical Data'!F36 | G23: ='Assumptions'!G62 | H23: =F23+G23 | I23: ='Assumptions'!I62 | J23: ='Assumptions'!J62 | K23: ='Assumptions'!K62 | L23: ='Assumptions'!L62
A24: Capital expenditure (owned PP&E) | B24: $M | C24: =-'Historical Data'!C44 | D24: =-'Historical Data'!D44 | E24: =-'Historical Data'!E44 | F24: =-'Historical Data'!F44 | G24: ='Revenue Build'!G13*'Assumptions'!G69 | H24: =F24+G24 | I24: ='Revenue Build'!I13*'Assumptions'!I69 | J24: ='Revenue Build'!J13*'Assumptions'!J69 | K24: ='Revenue Build'!K13*'Assumptions'!K69 | L24: ='Revenue Build'!L13*'Assumptions'!L69
A25: Depreciation & amortisation | B25: $M | C25: ='Historical Data'!C35 | D25: ='Historical Data'!D35 | E25: ='Historical Data'!E35 | F25: ='Historical Data'!F35 | G25: =('Balance Sheet'!F13+0.5*G24)*'Assumptions'!$C$70*'Assumptions'!G10 | H25: =F25+G25 | I25: =('Balance Sheet'!H13+0.5*I24)*'Assumptions'!$C$70*'Assumptions'!I10 | J25: =('Balance Sheet'!I13+0.5*J24)*'Assumptions'!$C$70*'Assumptions'!J10 | K25: =('Balance Sheet'!J13+0.5*K24)*'Assumptions'!$C$70*'Assumptions'!K10 | L25: =('Balance Sheet'!K13+0.5*L24)*'Assumptions'!$C$70*'Assumptions'!L10
A26: Total other operating & administrative | B26: $M | C26: ='Historical Data'!C15 | D26: ='Historical Data'!D15 | E26: ='Historical Data'!E15 | F26: ='Historical Data'!F15 | G26: =G22+G23+G25 | H26: =F26+G26 | I26: =I22+I23+I25 | J26: =J22+J23+J25 | K26: =K22+K23+K25 | L26: =L22+L23+L25
A28: Functional allocation (forecast) – ties to total expenses by nature
A29: Cost of revenue | B29: $M | C29: ='Historical Data'!C26 | D29: ='Historical Data'!D26 | E29: ='Historical Data'!E26 | F29: ='Historical Data'!F26 | G29: ='Compute Build'!G10+'Assumptions'!$C$50*G13+'Assumptions'!$C$63*G22 | H29: =F29+G29 | I29: ='Compute Build'!I10+'Assumptions'!$C$50*I13+'Assumptions'!$C$63*I22 | J29: ='Compute Build'!J10+'Assumptions'!$C$50*J13+'Assumptions'!$C$63*J22 | K29: ='Compute Build'!K10+'Assumptions'!$C$50*K13+'Assumptions'!$C$63*K22 | L29: ='Compute Build'!L10+'Assumptions'!$C$50*L13+'Assumptions'!$C$63*L22 | M29: Paid inference compute + allocated personnel and other.
A30: Research & development | B30: $M | C30: ='Historical Data'!C27 | D30: ='Historical Data'!D27 | E30: ='Historical Data'!E27 | F30: ='Historical Data'!F27 | G30: ='Compute Build'!G20+'Compute Build'!G12+'Compute Build'!G25+'Assumptions'!$C$51*G13+'Assumptions'!$C$64*G22 | H30: =F30+G30 | I30: ='Compute Build'!I20+'Compute Build'!I12+'Compute Build'!I25+'Assumptions'!$C$51*I13+'Assumptions'!$C$64*I22 | J30: ='Compute Build'!J20+'Compute Build'!J12+'Compute Build'!J25+'Assumptions'!$C$51*J13+'Assumptions'!$C$64*J22 | K30: ='Compute Build'!K20+'Compute Build'!K12+'Compute Build'!K25+'Assumptions'!$C$51*K13+'Assumptions'!$C$64*K22 | L30: ='Compute Build'!L20+'Compute Build'!L12+'Compute Build'!L25+'Assumptions'!$C$51*L13+'Assumptions'!$C$64*L22 | M30: Training & research compute + internal inference + take-or-pay shortfall + allocated personnel/other.
A31: Sales & marketing | B31: $M | C31: ='Historical Data'!C28 | D31: ='Historical Data'!D28 | E31: ='Historical Data'!E28 | F31: ='Historical Data'!F28 | G31: ='Compute Build'!G11+G18+'Assumptions'!$C$52*G13+'Assumptions'!$C$65*G22 | H31: =F31+G31 | I31: ='Compute Build'!I11+I18+'Assumptions'!$C$52*I13+'Assumptions'!$C$65*I22 | J31: ='Compute Build'!J11+J18+'Assumptions'!$C$52*J13+'Assumptions'!$C$65*J22 | K31: ='Compute Build'!K11+K18+'Assumptions'!$C$52*K13+'Assumptions'!$C$65*K22 | L31: ='Compute Build'!L11+L18+'Assumptions'!$C$52*L13+'Assumptions'!$C$65*L22 | M31: Free-tier inference + channel & marketing + allocated personnel/other.
A32: General & administrative | B32: $M | C32: ='Historical Data'!C29 | D32: ='Historical Data'!D29 | E32: ='Historical Data'!E29 | F32: ='Historical Data'!F29 | G32: ='Assumptions'!$C$53*G13+'Assumptions'!$C$66*G22+G23+G25 | H32: =F32+G32 | I32: ='Assumptions'!$C$53*I13+'Assumptions'!$C$66*I22+I23+I25 | J32: ='Assumptions'!$C$53*J13+'Assumptions'!$C$66*J22+J23+J25 | K32: ='Assumptions'!$C$53*K13+'Assumptions'!$C$66*K22+K23+K25 | L32: ='Assumptions'!$C$53*L13+'Assumptions'!$C$66*L22+L23+L25 | M32: Allocated personnel/other + donation matching + D&A.
A33: Bartz settlement | B33: $M | C33: ='Historical Data'!C13 | D33: ='Historical Data'!D13 | E33: ='Historical Data'!E13 | F33: ='Historical Data'!F13 | G33: 0 | H33: =F33+G33 | I33: 0 | J33: 0 | K33: 0 | L33: 0
A34: Total operating expenses (functional) | B34: $M | C34: =C29+C30+C31+C32+C33 | D34: =D29+D30+D31+D32+D33 | E34: =E29+E30+E31+E32+E33 | F34: =F29+F30+F31+F32+F33 | G34: =G29+G30+G31+G32+G33 | H34: =F34+G34 | I34: =I29+I30+I31+I32+I33 | J34: =J29+J30+J31+J32+J33 | K34: =K29+K30+K31+K32+K33 | L34: =L29+L30+L31+L32+L33
A35: Total operating expenses (by nature: compute + personnel + S,M&P + other + Bartz) | B35: $M | C35: ='Compute Build'!C26+C13+C18+C26+C33 | D35: ='Compute Build'!D26+D13+D18+D26+D33 | E35: ='Compute Build'!E26+E13+E18+E26+E33 | F35: ='Compute Build'!F26+F13+F18+F26+F33 | G35: ='Compute Build'!G26+G13+G18+G26+G33 | H35: =F35+G35 | I35: ='Compute Build'!I26+I13+I18+I26+I33 | J35: ='Compute Build'!J26+J13+J18+J26+J33 | K35: ='Compute Build'!K26+K13+K18+K26+K33 | L35: ='Compute Build'!L26+L13+L18+L26+L33
A36: Check: functional – nature (should be 0) | B36: $M | C36: =C34-C35 | D36: =D34-D35 | E36: =E34-E35 | F36: =F34-F35 | G36: =G34-G35 | H36: =H34-H35 | I36: =I34-I35 | J36: =J34-J35 | ... L36: =L34-L35 | M36: Historical: the S-1's functional note ties to the nature presentation after adding the Bartz line.

Sheet Income Statement
A1: Income Statement
A2: GAAP functional presentation (as in the S-1 supplemental note) with memo by nature of expense and non-GAAP adjusted metrics.
A4: $M unless noted | B4: Unit | C4: FY2023A | D4: FY2024A | E4: FY2025A | F4: H1'26A | G4: H2'26E | H4: FY2026E | I4: FY2027E | J4: FY2028E | K4: FY2029E | L4: FY2030E | M4: Notes / source
C5: Actual | D5: Actual | E5: Actual | F5: Actual | G5: Forecast | H5: H1A + H2E | I5: Forecast | J5: Forecast | K5: Forecast | L5: Forecast
A7: GAAP income statement
A8: Revenue | B8: $M | C8: ='Revenue Build'!C13 | D8: ='Revenue Build'!D13 | E8: ='Revenue Build'!E13 | F8: ='Revenue Build'!F13 | G8: ='Revenue Build'!G13 | H8: =F8+G8 | I8: ='Revenue Build'!I13 | J8: ='Revenue Build'!J13 | K8: ='Revenue Build'!K13 | L8: ='Revenue Build'!L13
A9: YoY growth | B9: % | D9: ='Revenue Build'!D14 | E9: ='Revenue Build'!E14 | G9: ='Revenue Build'!G14 | H9: ='Revenue Build'!H14 | I9: ='Revenue Build'!I14 | J9: ='Revenue Build'!J14 | K9: ='Revenue Build'!K14 | L9: ='Revenue Build'!L14
A10: Cost of revenue | B10: $M | C10: ='Opex Build'!C29 | D10: ='Opex Build'!D29 | E10: ='Opex Build'!E29 | F10: ='Opex Build'!F29 | G10: ='Opex Build'!G29 | H10: =F10+G10 | I10: ='Opex Build'!I29 | J10: ='Opex Build'!J29 | K10: ='Opex Build'!K29 | L10: ='Opex Build'!L29
A11: Gross profit | B11: $M | C11: =C8-C10 | D11: =D8-D10 | E11: =E8-E10 | F11: =F8-F10 | G11: =G8-G10 | H11: =H8-H10 | I11: =I8-I10 | J11: =J8-J10 | ... L11: =L8-L10
A12: Gross margin | B12: % | C12: =C11/C8 | D12: =D11/D8 | E12: =E11/E8 | F12: =F11/F8 | G12: =G11/G8 | H12: =H11/H8 | I12: =I11/I8 | J12: =J11/J8 | ... L12: =L11/L8 | M12: Functional margin: excludes training, research, internal and free-tier compute (in R&D / S&M).
A13: Research & development | B13: $M | C13: ='Opex Build'!C30 | D13: ='Opex Build'!D30 | E13: ='Opex Build'!E30 | F13: ='Opex Build'!F30 | G13: ='Opex Build'!G30 | H13: =F13+G13 | I13: ='Opex Build'!I30 | J13: ='Opex Build'!J30 | K13: ='Opex Build'!K30 | L13: ='Opex Build'!L30
A14: Sales & marketing | B14: $M | C14: ='Opex Build'!C31 | D14: ='Opex Build'!D31 | E14: ='Opex Build'!E31 | F14: ='Opex Build'!F31 | G14: ='Opex Build'!G31 | H14: =F14+G14 | I14: ='Opex Build'!I31 | J14: ='Opex Build'!J31 | K14: ='Opex Build'!K31 | L14: ='Opex Build'!L31
A15: General & administrative | B15: $M | C15: ='Opex Build'!C32 | D15: ='Opex Build'!D32 | E15: ='Opex Build'!E32 | F15: ='Opex Build'!F32 | G15: ='Opex Build'!G32 | H15: =F15+G15 | I15: ='Opex Build'!I32 | J15: ='Opex Build'!J32 | K15: ='Opex Build'!K32 | L15: ='Opex Build'!L32
A16: Bartz copyright settlement | B16: $M | C16: ='Opex Build'!C33 | D16: ='Opex Build'!D33 | E16: ='Opex Build'!E33 | F16: ='Opex Build'!F33 | G16: ='Opex Build'!G33 | H16: =F16+G16 | I16: ='Opex Build'!I33 | J16: ='Opex Build'!J33 | K16: ='Opex Build'!K33 | L16: ='Opex Build'!L33
A17: Total operating expenses (incl. cost of revenue) | B17: $M | C17: =C10+C13+C14+C15+C16 | D17: =D10+D13+D14+D15+D16 | E17: =E10+E13+E14+E15+E16 | F17: =F10+F13+F14+F15+F16 | G17: =G10+G13+G14+G15+G16 | H17: =H10+H13+H14+H15+H16 | I17: =I10+I13+I14+I15+I16 | J17: =J10+J13+J14+J15+J16 | ... L17: =L10+L13+L14+L15+L16
A18: Operating income (loss) | B18: $M | C18: =C8-C17 | D18: =D8-D17 | E18: =E8-E17 | F18: =F8-F17 | G18: =G8-G17 | H18: =H8-H17 | I18: =I8-I17 | J18: =J8-J17 | ... L18: =L8-L17
A19: Operating margin | B19: % | C19: =C18/C8 | D19: =D18/D8 | E19: =E18/E8 | F19: =F18/F8 | G19: =G18/G8 | H19: =H18/H8 | I19: =I18/I8 | J19: =J18/J8 | ... L19: =L18/L8
A20: Interest income | B20: $M | C20: ='Historical Data'!C18 | D20: ='Historical Data'!D18 | E20: ='Historical Data'!E18 | F20: ='Historical Data'!F18 | G20: ='Balance Sheet'!F8*'Assumptions'!G84*'Assumptions'!G10 | H20: =F20+G20 | I20: ='Balance Sheet'!H8*'Assumptions'!I84*'Assumptions'!I10 | J20: ='Balance Sheet'!I8*'Assumptions'!J84*'Assumptions'!J10 | K20: ='Balance Sheet'!J8*'Assumptions'!K84*'Assumptions'!K10 | L20: ='Balance Sheet'!K8*'Assumptions'!L84*'Assumptions'!L10 | M20: Opening cash & STI × yield × period fraction.
A21: Interest expense | B21: $M | C21: 0 | D21: 0 | E21: 0 | F21: 0 | G21: =-'Balance Sheet'!F24*'Assumptions'!$C$83*'Assumptions'!G10 | H21: =F21+G21 | I21: =-'Balance Sheet'!H24*'Assumptions'!$C$83*'Assumptions'!I10 | J21: =-'Balance Sheet'!I24*'Assumptions'!$C$83*'Assumptions'!J10 | K21: =-'Balance Sheet'!J24*'Assumptions'!$C$83*'Assumptions'!K10 | L21: =-'Balance Sheet'!K24*'Assumptions'!$C$83*'Assumptions'!L10
A22: Change in FV of convertible notes, SAFEs & other financial instruments (non-cash) | B22: $M | C22: ='Historical Data'!C19 | D22: ='Historical Data'!D19 | E22: ='Historical Data'!E19 | F22: ='Historical Data'!F19 | G22: =-'Assumptions'!G80 | H22: =F22+G22 | I22: =-'Assumptions'!I80 | J22: =-'Assumptions'!J80 | K22: =-'Assumptions'!K80 | L22: =-'Assumptions'!L80 | M22: Mark-to-market of Amazon notes etc. as the private valuation rose; ends on conversion at IPO.
A23: Other income (expense), net | B23: $M | C23: ='Historical Data'!C20 | D23: ='Historical Data'!D20 | E23: ='Historical Data'!E20 | F23: ='Historical Data'!F20 | G23: 0 | H23: =F23+G23 | I23: 0 | J23: 0 | K23: 0 | L23: 0
A24: Income (loss) before income taxes | B24: $M | C24: =C18+C20+C21+C22+C23 | D24: =D18+D20+D21+D22+D23 | E24: =E18+E20+E21+E22+E23 | F24: =F18+F20+F21+F22+F23 | G24: =G18+G20+G21+G22+G23 | H24: =H18+H20+H21+H22+H23 | I24: =I18+I20+I21+I22+I23 | J24: =J18+J20+J21+J22+J23 | ... L24: =L18+L20+L21+L22+L23
A25: Provision for income taxes | B25: $M | C25: =-'Historical Data'!C22 | D25: =-'Historical Data'!D22 | E25: =-'Historical Data'!E22 | F25: =-'Historical Data'!F22 | G25: =-'Balance Sheet'!G47 | H25: =F25+G25 | I25: =-'Balance Sheet'!I47 | J25: =-'Balance Sheet'!J47 | K25: =-'Balance Sheet'!K47 | L25: =-'Balance Sheet'!L47 | M25: Forecast from the NOL schedule on the Balance Sheet sheet.
A26: Net income (loss) | B26: $M | C26: =C24+C25 | D26: =D24+D25 | E26: =E24+E25 | F26: =F24+F25 | G26: =G24+G25 | H26: =H24+H25 | I26: =I24+I25 | J26: =J24+J25 | ... L26: =L24+L25
A27: Net margin | B27: % | C27: =C26/C8 | D27: =D26/D8 | E27: =E26/E8 | F27: =F26/F8 | G27: =G26/G8 | H27: =H26/H8 | I27: =I26/I8 | J27: =J26/J8 | ... L27: =L26/L8
A28: Check vs. filed net loss (0 = ties) | B28: $M | C28: =C26-'Historical Data'!C23 | D28: =D26-'Historical Data'!D23 | E28: =E26-'Historical Data'!E23 | F28: =F26-'Historical Data'!F23
A30: Memo: operating expenses by nature
A31: Compute & infrastructure | B31: $M | C31: ='Compute Build'!C26 | D31: ='Compute Build'!D26 | E31: ='Compute Build'!E26 | F31: ='Compute Build'!F26 | G31: ='Compute Build'!G26 | H31: =F31+G31 | I31: ='Compute Build'!I26 | J31: ='Compute Build'!J26 | K31: ='Compute Build'!K26 | L31: ='Compute Build'!L26
A32: of which inference (paid + free-tier + internal) | B32: $M | C32: ='Compute Build'!C13 | D32: ='Compute Build'!D13 | E32: ='Compute Build'!E13 | F32: ='Compute Build'!F13 | G32: ='Compute Build'!G13 | H32: =F32+G32 | I32: ='Compute Build'!I13 | J32: ='Compute Build'!J13 | K32: ='Compute Build'!K13 | L32: ='Compute Build'!L13
A33: of which training & research (incl. take-or-pay shortfall) | B33: $M | C33: ='Compute Build'!C20 | D33: ='Compute Build'!D20 | E33: ='Compute Build'!E20 | F33: ='Compute Build'!F20 | G33: ='Compute Build'!G20+'Compute Build'!G25 | H33: =F33+G33 | I33: ='Compute Build'!I20+'Compute Build'!I25 | J33: ='Compute Build'!J20+'Compute Build'!J25 | K33: ='Compute Build'!K20+'Compute Build'!K25 | L33: ='Compute Build'!L20+'Compute Build'!L25
A34: Personnel | B34: $M | C34: ='Opex Build'!C13 | D34: ='Opex Build'!D13 | E34: ='Opex Build'!E13 | F34: ='Opex Build'!F13 | G34: ='Opex Build'!G13 | H34: =F34+G34 | I34: ='Opex Build'!I13 | J34: ='Opex Build'!J13 | K34: ='Opex Build'!K13 | L34: ='Opex Build'!L13
A35: of which stock-based compensation | B35: $M | C35: ='Opex Build'!C10 | D35: ='Opex Build'!D10 | E35: ='Opex Build'!E10 | F35: ='Opex Build'!F10 | G35: ='Opex Build'!G10 | H35: =F35+G35 | I35: ='Opex Build'!I10 | J35: ='Opex Build'!J10 | K35: ='Opex Build'!K10 | L35: ='Opex Build'!L10
A36: Sales, marketing & partnerships | B36: $M | C36: ='Opex Build'!C18 | D36: ='Opex Build'!D18 | E36: ='Opex Build'!E18 | F36: ='Opex Build'!F18 | G36: ='Opex Build'!G18 | H36: =F36+G36 | I36: ='Opex Build'!I18 | J36: ='Opex Build'!J18 | K36: ='Opex Build'!K18 | L36: ='Opex Build'!L18
A37: Other operating & administrative | B37: $M | C37: ='Opex Build'!C26 | D37: ='Opex Build'!D26 | E37: ='Opex Build'!E26 | F37: ='Opex Build'!F26 | G37: ='Opex Build'!G26 | H37: =F37+G37 | I37: ='Opex Build'!I26 | J37: ='Opex Build'!J26 | K37: ='Opex Build'!K26 | L37: ='Opex Build'!L26
A38: Bartz settlement | B38: $M | C38: =C16 | D38: =D16 | E38: =E16 | F38: =F16 | G38: =G16 | H38: =F38+G38 | I38: =I16 | J38: =J16 | K38: =K16 | L38: =L16
A39: Total operating expenses (by nature) | B39: $M | C39: =C31+C34+C36+C37+C38 | D39: =D31+D34+D36+D37+D38 | E39: =E31+E34+E36+E37+E38 | F39: =F31+F34+F36+F37+F38 | G39: =G31+G34+G36+G37+G38 | H39: =H31+H34+H36+H37+H38 | I39: =I31+I34+I36+I37+I38 | J39: =J31+J34+J36+J37+J38 | ... L39: =L31+L34+L36+L37+L38
A40: Check: nature – functional (0 = ties) | B40: $M | C40: =C39-C17 | D40: =D39-D17 | E40: =E39-E17 | F40: =F39-F17 | G40: =G39-G17 | H40: =H39-H17 | I40: =I39-I17 | J40: =J39-J17 | ... L40: =L39-L17
A41: Compute & infrastructure as % of revenue | B41: % | C41: =C31/C8 | D41: =D31/D8 | E41: =E31/E8 | F41: =F31/F8 | G41: =G31/G8 | H41: =H31/H8 | I41: =I31/I8 | J41: =J31/J8 | ... L41: =L31/L8
A43: Non-GAAP (company definitions)
A44: Adjusted operating income (op. income + SBC + non-cash donation matching + Bartz) | B44: $M | C44: =C18+'Opex Build'!C10+'Opex Build'!C23+C16 | D44: =D18+'Opex Build'!D10+'Opex Build'!D23+D16 | E44: =E18+'Opex Build'!E10+'Opex Build'!E23+E16 | F44: =F18+'Opex Build'!F10+'Opex Build'!F23+F16 | G44: =G18+'Opex Build'!G10+'Opex Build'!G23+G16 | H44: =H18+'Opex Build'!H10+'Opex Build'!H23+H16 | I44: =I18+'Opex Build'!I10+'Opex Build'!I23+I16 | J44: =J18+'Opex Build'!J10+'Opex Build'!J23+J16 | ... L44: =L18+'Opex Build'!L10+'Opex Build'!L23+L16 | M44: Filed: FY25 $(4,854)M; H1'26 $1,618M. Q3'26 margin ~11% per management.
A45: Adjusted operating margin | B45: % | C45: =C44/C8 | D45: =D44/D8 | E45: =E44/E8 | F45: =F44/F8 | G45: =G44/G8 | H45: =H44/H8 | I45: =I44/I8 | J45: =J44/J8 | ... L45: =L44/L8
A46: Adjusted EBITDA (adjusted operating income + D&A) | B46: $M | C46: =C44+'Opex Build'!C25 | D46: =D44+'Opex Build'!D25 | E46: =E44+'Opex Build'!E25 | F46: =F44+'Opex Build'!F25 | G46: =G44+'Opex Build'!G25 | H46: =H44+'Opex Build'!H25 | I46: =I44+'Opex Build'!I25 | J46: =J44+'Opex Build'!J25 | ... L46: =L44+'Opex Build'!L25
A47: Adjusted EBITDA margin | B47: % | C47: =C46/C8 | D47: =D46/D8 | E47: =E46/E8 | F47: =F46/F8 | G47: =G46/G8 | H47: =H46/H8 | I47: =I46/I8 | J47: =J46/J8 | ... L47: =L46/L8
A48: Adjusted net income (net income + SBC + donation + Bartz + FV changes) | B48: $M | C48: =C26+'Opex Build'!C10+'Opex Build'!C23+C16-C22 | D48: =D26+'Opex Build'!D10+'Opex Build'!D23+D16-D22 | E48: =E26+'Opex Build'!E10+'Opex Build'!E23+E16-E22 | F48: =F26+'Opex Build'!F10+'Opex Build'!F23+F16-F22 | G48: =G26+'Opex Build'!G10+'Opex Build'!G23+G16-G22 | H48: =H26+'Opex Build'!H10+'Opex Build'!H23+H16-H22 | I48: =I26+'Opex Build'!I10+'Opex Build'!I23+I16-I22 | J48: =J26+'Opex Build'!J10+'Opex Build'!J23+J16-J22 | ... L48: =L26+'Opex Build'!L10+'Opex Build'!L23+L16-L22 | M48: Filed: FY25 $(4,448)M; H1'26 $2,671M.

Sheet Balance Sheet
A1: Balance Sheet
A2: Rolls forward from the Jun-26A filed balance sheet. Convertible notes and preferred stock convert to common equity at the IPO in H2'26E.
A4: $M unless noted | B4: Unit | C4: Dec-23A | D4: Dec-24A | E4: Dec-25A | F4: Jun-26A | G4: Dec-26E | H4: Dec-26E | I4: Dec-27E | J4: Dec-28E | K4: Dec-29E | L4: Dec-30E | M4: Notes / source
C5: Actual | D5: Actual | E5: Actual | F5: Actual | G5: Forecast | H5: same as H2'26E | I5: Forecast | J5: Forecast | K5: Forecast | L5: Forecast
A7: Assets
A8: Cash, cash equivalents & short-term investments | B8: $M | D8: ='Historical Data'!D58+'Historical Data'!D59 | E8: ='Historical Data'!E58+'Historical Data'!E59 | F8: ='Historical Data'!F58+'Historical Data'!F59 | G8: ='Cash Flow'!G41 | H8: =G8 | I8: ='Cash Flow'!I41 | J8: ='Cash Flow'!J41 | K8: ='Cash Flow'!K41 | L8: ='Cash Flow'!L41 | M8: Forecast: one pool (STI treated as cash).
A9: Accounts receivable, net | B9: $M | D9: ='Historical Data'!D60 | E9: ='Historical Data'!E60 | F9: ='Historical Data'!F60 | G9: ='Assumptions'!G73*'Revenue Build'!G13/'Assumptions'!G10 | H9: =G9 | I9: ='Assumptions'!I73*'Revenue Build'!I13/'Assumptions'!I10 | J9: ='Assumptions'!J73*'Revenue Build'!J13/'Assumptions'!J10 | K9: ='Assumptions'!K73*'Revenue Build'!K13/'Assumptions'!K10 | L9: ='Assumptions'!L73*'Revenue Build'!L13/'Assumptions'!L10
A10: Prepaid expenses & other current assets | B10: $M | D10: ='Historical Data'!D61 | E10: ='Historical Data'!E61 | F10: ='Historical Data'!F61 | G10: ='Assumptions'!G74*'Compute Build'!G26/'Assumptions'!G10 | H10: =G10 | I10: ='Assumptions'!I74*'Compute Build'!I26/'Assumptions'!I10 | J10: ='Assumptions'!J74*'Compute Build'!J26/'Assumptions'!J10 | K10: ='Assumptions'!K74*'Compute Build'!K26/'Assumptions'!K10 | L10: ='Assumptions'!L74*'Compute Build'!L26/'Assumptions'!L10
A11: Total current assets | B11: $M | D11: =D8+D9+D10 | E11: =E8+E9+E10 | F11: =F8+F9+F10 | G11: =G8+G9+G10 | H11: =G11 | I11: =I8+I9+I10 | J11: =J8+J9+J10 | K11: =K8+K9+K10 | L11: =L8+L9+L10
A12: Restricted cash | B12: $M | D12: ='Historical Data'!D62 | E12: ='Historical Data'!E62 | F12: ='Historical Data'!F62 | G12: =F12 | H12: =G12 | I12: =H12 | J12: =I12 | K12: =J12 | L12: =K12 | M12: Held flat.
A13: Property & equipment, net (incl. finance-lease assets) | B13: $M | D13: ='Historical Data'!D63 | E13: ='Historical Data'!E63 | F13: ='Historical Data'!F63 | G13: =F13+'Opex Build'!G24-'Opex Build'!G25 | H13: =G13 | I13: =H13+'Opex Build'!I24-'Opex Build'!I25 | J13: =I13+'Opex Build'!J24-'Opex Build'!J25 | K13: =J13+'Opex Build'!K24-'Opex Build'!K25 | L13: =K13+'Opex Build'!L24-'Opex Build'!L25
A14: Operating lease right-of-use assets | B14: $M | D14: ='Historical Data'!D64 | E14: ='Historical Data'!E64 | F14: ='Historical Data'!F64 | G14: =F14 | H14: =G14 | I14: =H14 | J14: =I14 | K14: =J14 | L14: =K14 | M14: Held flat (offices); matched by lease liabilities below.
A15: Goodwill | B15: $M | D15: ='Historical Data'!D65 | E15: ='Historical Data'!E65 | F15: ='Historical Data'!F65 | G15: =F15 | H15: =G15 | I15: =H15 | J15: =I15 | K15: =J15 | L15: =K15
A16: Other assets, noncurrent | B16: $M | D16: ='Historical Data'!D66 | E16: ='Historical Data'!E66 | F16: ='Historical Data'!F66 | G16: =F16 | H16: =G16 | I16: =H16 | J16: =I16 | K16: =J16 | L16: =K16 | M16: Held flat (deposits / prepayments on compute capacity).
A17: Total assets | B17: $M | D17: =D11+D12+D13+D14+D15+D16 | E17: =E11+E12+E13+E14+E15+E16 | F17: =F11+F12+F13+F14+F15+F16 | G17: =G11+G12+G13+G14+G15+G16 | H17: =G17 | I17: =I11+I12+I13+I14+I15+I16 | J17: =J11+J12+J13+J14+J15+J16 | K17: =K11+K12+K13+K14+K15+K16 | L17: =L11+L12+L13+L14+L15+L16
A19: Liabilities
A20: Accounts payable, accrued expenses & other current liabilities | B20: $M | D20: ='Historical Data'!D68 | E20: ='Historical Data'!E68 | F20: ='Historical Data'!F68 | G20: ='Assumptions'!G75*('Income Statement'!G17-'Opex Build'!G10-'Opex Build'!G23-'Opex Build'!G25)/'Assumptions'!G10 | H20: =G20 | I20: ='Assumptions'!I75*('Income Statement'!I17-'Opex Build'!I10-'Opex Build'!I23-'Opex Build'!I25)/'Assumptions'!I10 | J20: ='Assumptions'!J75*('Income Statement'!J17-'Opex Build'!J10-'Opex Build'!J23-'Opex Build'!J25)/'Assumptions'!J10 | K20: ='Assumptions'!K75*('Income Statement'!K17-'Opex Build'!K10-'Opex Build'!K23-'Opex Build'!K25)/'Assumptions'!K10 | L20: ='Assumptions'!L75*('Income Statement'!L17-'Opex Build'!L10-'Opex Build'!L23-'Opex Build'!L25)/'Assumptions'!L10 | M20: % of annualised cash operating costs (total opex less SBC, donation matching and D&A).
A21: Operating lease liabilities (current + noncurrent) | B21: $M | D21: ='Historical Data'!D69 | E21: ='Historical Data'!E69 | F21: ='Historical Data'!F69 | G21: =F21 | H21: =G21 | I21: =H21 | J21: =I21 | K21: =J21 | L21: =K21
A22: Deferred revenue | B22: $M | D22: ='Historical Data'!D70 | E22: ='Historical Data'!E70 | F22: ='Historical Data'!F70 | G22: ='Assumptions'!G76*'Revenue Build'!G19/'Assumptions'!G10 | H22: =G22 | I22: ='Assumptions'!I76*'Revenue Build'!I19/'Assumptions'!I10 | J22: ='Assumptions'!J76*'Revenue Build'!J19/'Assumptions'!J10 | K22: ='Assumptions'!K76*'Revenue Build'!K19/'Assumptions'!K10 | L22: ='Assumptions'!L76*'Revenue Build'!L19/'Assumptions'!L10
A23: Convertible notes payable (at fair value) | B23: $M | D23: ='Historical Data'!D71 | E23: ='Historical Data'!E71 | F23: ='Historical Data'!F71 | G23: =F23+'Assumptions'!G80-G38 | H23: =G23 | I23: =H23+'Assumptions'!I80-I38 | J23: =I23+'Assumptions'!J80-J38 | K23: =J23+'Assumptions'!K80-K38 | L23: =K23+'Assumptions'!L80-L38 | M23: Amazon notes: $6.2B principal, $108.6B fair value at Jun-26; convert to Class N common at IPO.
A24: Debt / supplier financing | B24: $M | D24: 0 | E24: 0 | F24: 0 | G24: =F24+'Assumptions'!G82 | H24: =G24 | I24: =H24+'Assumptions'!I82 | J24: =I24+'Assumptions'!J82 | K24: =J24+'Assumptions'!K82 | L24: =K24+'Assumptions'!L82
A25: Other noncurrent liabilities | B25: $M | D25: ='Historical Data'!D72 | E25: ='Historical Data'!E72 | F25: ='Historical Data'!F72 | G25: =F25 | H25: =G25 | I25: =H25 | J25: =I25 | K25: =J25 | L25: =K25
A26: Total liabilities | B26: $M | D26: =D20+D21+D22+D23+D24+D25 | E26: =E20+E21+E22+E23+E24+E25 | F26: =F20+F21+F22+F23+F24+F25 | G26: =G20+G21+G22+G23+G24+G25 | H26: =G26 | I26: =I20+I21+I22+I23+I24+I25 | J26: =J20+J21+J22+J23+J24+J25 | K26: =K20+K21+K22+K23+K24+K25 | L26: =L20+L21+L22+L23+L24+L25
A28: Mezzanine & stockholders' equity
A29: Redeemable convertible preferred stock (mezzanine) | B29: $M | D29: ='Historical Data'!D74 | E29: ='Historical Data'!E74 | F29: ='Historical Data'!F74 | G29: =F29-G39 | H29: =G29 | I29: =H29-I39 | J29: =I29-J39 | K29: =J29-K39 | L29: =K29-L39 | M29: Series A–H; converts 1:1 into common at IPO.
A30: Common stock & additional paid-in capital | B30: $M | D30: ='Historical Data'!D75 | E30: ='Historical Data'!E75 | F30: ='Historical Data'!F75 | G30: =F30+'Opex Build'!G10+'Opex Build'!G23+'Assumptions'!G81+'Assumptions'!G79+G39+G38 | H30: =G30 | I30: =H30+'Opex Build'!I10+'Opex Build'!I23+'Assumptions'!I81+'Assumptions'!I79+I39+I38 | J30: =I30+'Opex Build'!J10+'Opex Build'!J23+'Assumptions'!J81+'Assumptions'!J79+J39+J38 | K30: =J30+'Opex Build'!K10+'Opex Build'!K23+'Assumptions'!K81+'Assumptions'!K79+K39+K38 | L30: =K30+'Opex Build'!L10+'Opex Build'!L23+'Assumptions'!L81+'Assumptions'!L79+L39+L38 | M30: + SBC, share-settled donation matching, option/ESPP proceeds, IPO proceeds, conversion of preferred and notes.
A31: Accumulated other comprehensive income (loss) | B31: $M | D31: ='Historical Data'!D76 | E31: ='Historical Data'!E76 | F31: ='Historical Data'!F76 | G31: =F31 | H31: =G31 | I31: =H31 | J31: =I31 | K31: =J31 | L31: =K31
A32: Accumulated deficit | B32: $M | D32: ='Historical Data'!D77 | E32: ='Historical Data'!E77 | F32: ='Historical Data'!F77 | G32: =F32+'Income Statement'!G26 | H32: =G32 | I32: =H32+'Income Statement'!I26 | J32: =I32+'Income Statement'!J26 | K32: =J32+'Income Statement'!K26 | L32: =K32+'Income Statement'!L26
A33: Total equity incl. mezzanine preferred | B33: $M | D33: =D29+D30+D31+D32 | E33: =E29+E30+E31+E32 | F33: =F29+F30+F31+F32 | G33: =G29+G30+G31+G32 | H33: =G33 | I33: =I29+I30+I31+I32 | J33: =J29+J30+J31+J32 | K33: =K29+K30+K31+K32 | L33: =L29+L30+L31+L32
A34: Total liabilities, mezzanine & equity | B34: $M | D34: =D26+D33 | E34: =E26+E33 | F34: =F26+F33 | G34: =G26+G33 | H34: =G34 | I34: =I26+I33 | J34: =J26+J33 | K34: =K26+K33 | L34: =L26+L33
A35: Check: assets – (liabilities + equity) (0 = balances) | B35: $M | D35: =ROUND(D17-D34,3) | E35: =ROUND(E17-E34,3) | F35: =ROUND(F17-F34,3) | G35: =ROUND(G17-G34,3) | H35: =G35 | I35: =ROUND(I17-I34,3) | J35: =ROUND(J17-J34,3) | K35: =ROUND(K17-K34,3) | L35: =ROUND(L17-L34,3)
A37: Supporting schedules
A38: Conversion of convertible notes into common equity at IPO (non-cash) | B38: $M | G38: =F23+'Assumptions'!G80 | H38: =G38 | I38: =0 | J38: =0 | K38: =0 | L38: =0 | M38: All outstanding notes (carrying value incl. the pre-IPO fair-value charge) convert in H2'26E.
A39: Conversion of preferred stock into common equity at IPO (non-cash) | B39: $M | G39: =F29 | H39: =G39 | I39: =0 | J39: =0 | K39: =0 | L39: =0
A40: Net working capital (AR + prepaid – AP – deferred revenue) | B40: $M | D40: =D9+D10-D20-D22 | E40: =E9+E10-E20-E22 | F40: =F9+F10-F20-F22 | G40: =G9+G10-G20-G22 | H40: =G40 | I40: =I9+I10-I20-I22 | J40: =J9+J10-J20-J22 | K40: =K9+K10-K20-K22 | L40: =L9+L10-L20-L22
A42: Tax schedule (simplified NOL)
A43: Taxable income proxy (pre-tax income + non-deductible FV charge + donation matching) | B43: $M | G43: ='Income Statement'!G24-'Income Statement'!G22+'Opex Build'!G23 | H43: =F43+G43 | I43: ='Income Statement'!I24-'Income Statement'!I22+'Opex Build'!I23 | J43: ='Income Statement'!J24-'Income Statement'!J22+'Opex Build'!J23 | K43: ='Income Statement'!K24-'Income Statement'!K22+'Opex Build'!K23 | L43: ='Income Statement'!L24-'Income Statement'!L22+'Opex Build'!L23
A44: NOL carryforward – opening | B44: $M | G44: ='Assumptions'!$C$86 | H44: =G44 | I44: =H46 | J44: =I46 | K44: =J46 | L44: =K46 | M44: Opening balance is an input on Assumptions; thereafter rolls from prior closing.
A45: NOL utilised | B45: $M | G45: =MIN(G44,MAX(0,G43)) | H45: =F45+G45 | I45: =MIN(I44,MAX(0,I43)) | J45: =MIN(J44,MAX(0,J43)) | K45: =MIN(K44,MAX(0,K43)) | L45: =MIN(L44,MAX(0,L43))
A46: NOL carryforward – closing | B46: $M | G46: =G44-G45+MAX(0,-G43) | H46: =G46 | I46: =I44-I45+MAX(0,-I43) | J46: =J44-J45+MAX(0,-J43) | K46: =K44-K45+MAX(0,-K43) | L46: =L44-L45+MAX(0,-L43)
A47: Income tax expense (cash & deferred, simplified) | B47: $M | G47: =MAX(0,G43-G45)*'Assumptions'!$C$85+'Assumptions'!$C$87*'Revenue Build'!G13 | H47: =F47+G47 | I47: =MAX(0,I43-I45)*'Assumptions'!$C$85+'Assumptions'!$C$87*'Revenue Build'!I13 | J47: =MAX(0,J43-J45)*'Assumptions'!$C$85+'Assumptions'!$C$87*'Revenue Build'!J13 | K47: =MAX(0,K43-K45)*'Assumptions'!$C$85+'Assumptions'!$C$87*'Revenue Build'!K13 | L47: =MAX(0,L43-L45)*'Assumptions'!$C$85+'Assumptions'!$C$87*'Revenue Build'!L13 | M47: Statutory rate on taxable income after NOLs, plus minimum/other taxes as % of revenue.

Sheet Cash Flow
A1: Cash Flow Statement
A2: Indirect method. Historical columns as filed (restated to this line structure); forecast treats cash and short-term investments as one pool.
A4: $M unless noted | B4: Unit | C4: FY2023A | D4: FY2024A | E4: FY2025A | F4: H1'26A | G4: H2'26E | H4: FY2026E | I4: FY2027E | J4: FY2028E | K4: FY2029E | L4: FY2030E | M4: Notes / source
C5: Actual | D5: Actual | E5: Actual | F5: Actual | G5: Forecast | H5: H1A + H2E | I5: Forecast | J5: Forecast | K5: Forecast | L5: Forecast
A7: Operating activities
A8: Net income (loss) | B8: $M | C8: ='Income Statement'!C26 | D8: ='Income Statement'!D26 | E8: ='Income Statement'!E26 | F8: ='Income Statement'!F26 | G8: ='Income Statement'!G26 | H8: =F8+G8 | I8: ='Income Statement'!I26 | J8: ='Income Statement'!J26 | K8: ='Income Statement'!K26 | L8: ='Income Statement'!L26
A9: Stock-based compensation | B9: $M | C9: ='Historical Data'!C33 | D9: ='Historical Data'!D33 | E9: ='Historical Data'!E33 | F9: ='Historical Data'!F33 | G9: ='Opex Build'!G10 | H9: =F9+G9 | I9: ='Opex Build'!I10 | J9: ='Opex Build'!J10 | K9: ='Opex Build'!K10 | L9: ='Opex Build'!L10 | M9: Historical: cash-flow add-back (differs slightly from IS SBC in FY25 due to capitalised amounts).
A10: Depreciation & amortisation | B10: $M | C10: ='Historical Data'!C35 | D10: ='Historical Data'!D35 | E10: ='Historical Data'!E35 | F10: ='Historical Data'!F35 | G10: ='Opex Build'!G25 | H10: =F10+G10 | I10: ='Opex Build'!I25 | J10: ='Opex Build'!J25 | K10: ='Opex Build'!K25 | L10: ='Opex Build'!L25
A11: Change in FV of convertible notes, SAFEs & other financial instruments (non-cash) | B11: $M | C11: =-'Historical Data'!C19 | D11: =-'Historical Data'!D19 | E11: =-'Historical Data'!E19 | F11: =-'Historical Data'!F19 | G11: =-'Income Statement'!G22 | H11: =F11+G11 | I11: =-'Income Statement'!I22 | J11: =-'Income Statement'!J22 | K11: =-'Income Statement'!K22 | L11: =-'Income Statement'!L22
A12: Donation-matching expense settled in shares (non-cash) | B12: $M | C12: ='Historical Data'!C36 | D12: ='Historical Data'!D36 | E12: ='Historical Data'!E36 | F12: ='Historical Data'!F36 | G12: ='Opex Build'!G23 | H12: =F12+G12 | I12: ='Opex Build'!I23 | J12: ='Opex Build'!J23 | K12: ='Opex Build'!K23 | L12: ='Opex Build'!L23
A13: Other non-cash items | B13: $M | C13: ='Historical Data'!C37 | D13: ='Historical Data'!D37 | E13: ='Historical Data'!E37 | F13: ='Historical Data'!F37 | G13: 0 | H13: =F13+G13 | I13: 0 | J13: 0 | K13: 0 | L13: 0
A14: (Increase) decrease in accounts receivable | B14: $M | C14: ='Historical Data'!C38 | D14: ='Historical Data'!D38 | E14: ='Historical Data'!E38 | F14: ='Historical Data'!F38 | G14: ='Balance Sheet'!F9-'Balance Sheet'!G9 | H14: =F14+G14 | I14: ='Balance Sheet'!H9-'Balance Sheet'!I9 | J14: ='Balance Sheet'!I9-'Balance Sheet'!J9 | K14: ='Balance Sheet'!J9-'Balance Sheet'!K9 | L14: ='Balance Sheet'!K9-'Balance Sheet'!L9
A15: (Increase) decrease in prepaid expenses & other assets | B15: $M | C15: ='Historical Data'!C39 | D15: ='Historical Data'!D39 | E15: ='Historical Data'!E39 | F15: ='Historical Data'!F39 | G15: ='Balance Sheet'!F10-'Balance Sheet'!G10 | H15: =F15+G15 | I15: ='Balance Sheet'!H10-'Balance Sheet'!I10 | J15: ='Balance Sheet'!I10-'Balance Sheet'!J10 | K15: ='Balance Sheet'!J10-'Balance Sheet'!K10 | L15: ='Balance Sheet'!K10-'Balance Sheet'!L10
A16: Increase (decrease) in accounts payable, accrued & other liabilities | B16: $M | C16: ='Historical Data'!C40 | D16: ='Historical Data'!D40 | E16: ='Historical Data'!E40 | F16: ='Historical Data'!F40 | G16: ='Balance Sheet'!G20-'Balance Sheet'!F20 | H16: =F16+G16 | I16: ='Balance Sheet'!I20-'Balance Sheet'!H20 | J16: ='Balance Sheet'!J20-'Balance Sheet'!I20 | K16: ='Balance Sheet'!K20-'Balance Sheet'!J20 | L16: ='Balance Sheet'!L20-'Balance Sheet'!K20
A17: Increase (decrease) in lease liabilities | B17: $M | C17: ='Historical Data'!C41 | D17: ='Historical Data'!D41 | E17: ='Historical Data'!E41 | F17: ='Historical Data'!F41 | G17: ='Balance Sheet'!G21-'Balance Sheet'!F21 | H17: =F17+G17 | I17: ='Balance Sheet'!I21-'Balance Sheet'!H21 | J17: ='Balance Sheet'!J21-'Balance Sheet'!I21 | K17: ='Balance Sheet'!K21-'Balance Sheet'!J21 | L17: ='Balance Sheet'!L21-'Balance Sheet'!K21
A18: Increase (decrease) in deferred revenue | B18: $M | C18: ='Historical Data'!C42 | D18: ='Historical Data'!D42 | E18: ='Historical Data'!E42 | F18: ='Historical Data'!F42 | G18: ='Balance Sheet'!G22-'Balance Sheet'!F22 | H18: =F18+G18 | I18: ='Balance Sheet'!I22-'Balance Sheet'!H22 | J18: ='Balance Sheet'!J22-'Balance Sheet'!I22 | K18: ='Balance Sheet'!K22-'Balance Sheet'!J22 | L18: ='Balance Sheet'!L22-'Balance Sheet'!K22
A19: Net cash from operating activities | B19: $M | C19: =C8+C9+C10+C11+C12+C13+C14+C15+C16+C17+C18 | D19: =D8+D9+D10+D11+D12+D13+D14+D15+D16+D17+D18 | E19: =E8+E9+E10+E11+E12+E13+E14+E15+E16+E17+E18 | F19: =F8+F9+F10+F11+F12+F13+F14+F15+F16+F17+F18 | G19: =G8+G9+G10+G11+G12+G13+G14+G15+G16+G17+G18 | H19: =F19+G19 | I19: =I8+I9+I10+I11+I12+I13+I14+I15+I16+I17+I18 | J19: =J8+J9+J10+J11+J12+J13+J14+J15+J16+J17+J18 | K19: =K8+K9+K10+K11+K12+K13+K14+K15+K16+K17+K18 | L19: =L8+L9+L10+L11+L12+L13+L14+L15+L16+L17+L18
A20: Check vs. filed operating cash flow (0 = ties) | B20: $M | C20: =C19-'Historical Data'!C43 | D20: =D19-'Historical Data'!D43 | E20: =E19-'Historical Data'!E43 | F20: =F19-'Historical Data'!F43
A22: Investing activities
A23: Purchases of property & equipment | B23: $M | C23: ='Historical Data'!C44 | D23: ='Historical Data'!D44 | E23: ='Historical Data'!E44 | F23: ='Historical Data'!F44 | G23: =-'Opex Build'!G24 | H23: =F23+G23 | I23: =-'Opex Build'!I24 | J23: =-'Opex Build'!J24 | K23: =-'Opex Build'!K24 | L23: =-'Opex Build'!L24
A24: Purchases of short-term investments, net | B24: $M | C24: ='Historical Data'!C45 | D24: ='Historical Data'!D45 | E24: ='Historical Data'!E45 | F24: ='Historical Data'!F45 | G24: 0 | H24: =F24+G24 | I24: 0 | J24: 0 | K24: 0 | L24: 0 | M24: Forecast: STI modelled within the cash pool, so no separate flow.
A25: Other investing activities | B25: $M | C25: ='Historical Data'!C46 | D25: ='Historical Data'!D46 | E25: ='Historical Data'!E46 | F25: ='Historical Data'!F46 | G25: 0 | H25: =F25+G25 | I25: 0 | J25: 0 | K25: 0 | L25: 0
A26: Net cash from investing activities | B26: $M | C26: =C23+C24+C25 | D26: =D23+D24+D25 | E26: =E23+E24+E25 | F26: =F23+F24+F25 | G26: =G23+G24+G25 | H26: =F26+G26 | I26: =I23+I24+I25 | J26: =J23+J24+J25 | K26: =K23+K24+K25 | L26: =L23+L24+L25
A28: Financing activities
A29: Proceeds from preferred stock, net | B29: $M | C29: ='Historical Data'!C48 | D29: ='Historical Data'!D48 | E29: ='Historical Data'!E48 | F29: ='Historical Data'!F48 | G29: 0 | H29: =F29+G29 | I29: 0 | J29: 0 | K29: 0 | L29: 0
A30: Issuance of convertible notes for cash | B30: $M | C30: ='Historical Data'!C49 | D30: ='Historical Data'!D49 | E30: ='Historical Data'!E49 | F30: ='Historical Data'!F49 | G30: 0 | H30: =F30+G30 | I30: 0 | J30: 0 | K30: 0 | L30: 0
A31: IPO primary proceeds, net | B31: $M | C31: 0 | D31: 0 | E31: 0 | F31: 0 | G31: ='Assumptions'!G79 | H31: =F31+G31 | I31: ='Assumptions'!I79 | J31: ='Assumptions'!J79 | K31: ='Assumptions'!K79 | L31: ='Assumptions'!L79
A32: Proceeds from common stock (options / ESPP) | B32: $M | C32: ='Historical Data'!C50 | D32: ='Historical Data'!D50 | E32: ='Historical Data'!E50 | F32: ='Historical Data'!F50 | G32: ='Assumptions'!G81 | H32: =F32+G32 | I32: ='Assumptions'!I81 | J32: ='Assumptions'!J81 | K32: ='Assumptions'!K81 | L32: ='Assumptions'!L81
A33: Debt / supplier financing drawdown (repayment) | B33: $M | C33: 0 | D33: 0 | E33: 0 | F33: 0 | G33: ='Assumptions'!G82 | H33: =F33+G33 | I33: ='Assumptions'!I82 | J33: ='Assumptions'!J82 | K33: ='Assumptions'!K82 | L33: ='Assumptions'!L82
A34: Other financing | B34: $M | C34: ='Historical Data'!C51 | D34: ='Historical Data'!D51 | E34: ='Historical Data'!E51 | F34: ='Historical Data'!F51 | G34: 0 | H34: =F34+G34 | I34: 0 | J34: 0 | K34: 0 | L34: 0
A35: Net cash from financing activities | B35: $M | C35: =C29+C30+C31+C32+C33+C34 | D35: =D29+D30+D31+D32+D33+D34 | E35: =E29+E30+E31+E32+E33+E34 | F35: =F29+F30+F31+F32+F33+F34 | G35: =G29+G30+G31+G32+G33+G34 | H35: =F35+G35 | I35: =I29+I30+I31+I32+I33+I34 | J35: =J29+J30+J31+J32+J33+J34 | K35: =K29+K30+K31+K32+K33+K34 | L35: =L29+L30+L31+L32+L33+L34
A37: Cash reconciliation
A38: Effect of exchange rates | B38: $M | C38: ='Historical Data'!C53 | D38: ='Historical Data'!D53 | E38: ='Historical Data'!E53 | F38: ='Historical Data'!F53 | G38: 0 | H38: =F38+G38 | I38: 0 | J38: 0 | K38: 0 | L38: 0
A39: Net change in cash (forecast: cash & STI; historical: cash & restricted cash as filed) | B39: $M | C39: =C19+C26+C35+C38 | D39: =D19+D26+D35+D38 | E39: =E19+E26+E35+E38 | F39: =F19+F26+F35+F38 | G39: =G19+G26+G35+G38 | H39: =F39+G39 | I39: =I19+I26+I35+I38 | J39: =J19+J26+J35+J38 | K39: =K19+K26+K35+K38 | L39: =L19+L26+L35+L38
A40: Cash & STI – beginning of period | B40: $M | G40: ='Balance Sheet'!F8 | H40: ='Balance Sheet'!E8 | I40: ='Balance Sheet'!H8 | J40: ='Balance Sheet'!I8 | K40: ='Balance Sheet'!J8 | L40: ='Balance Sheet'!K8
A41: Cash & STI – end of period | B41: $M | D41: ='Balance Sheet'!D8 | E41: ='Balance Sheet'!E8 | F41: ='Balance Sheet'!F8 | G41: =G40+G39 | H41: ='Balance Sheet'!G8 | I41: =I40+I39 | J41: =J40+J39 | K41: =K40+K39 | L41: =L40+L39 | M41: Forecast: beginning + net change (feeds the balance sheet). Historical: per balance sheet.
A42: Memo: cash, equivalents & restricted cash – end of period (as filed) | B42: $M | C42: ='Historical Data'!C55 | D42: ='Historical Data'!D55 | E42: ='Historical Data'!E55 | F42: ='Historical Data'!F55
A44: Free cash flow
A45: Free cash flow (CFO – capex) | B45: $M | C45: =C19+C23 | D45: =D19+D23 | E45: =E19+E23 | F45: =F19+F23 | G45: =G19+G23 | H45: =F45+G45 | I45: =I19+I23 | J45: =J19+J23 | K45: =K19+K23 | L45: =L19+L23
A46: FCF margin | B46: % | C46: =C45/'Income Statement'!C8 | D46: =D45/'Income Statement'!D8 | E46: =E45/'Income Statement'!E8 | F46: =F45/'Income Statement'!F8 | G46: =G45/'Income Statement'!G8 | H46: =H45/'Income Statement'!H8 | I46: =I45/'Income Statement'!I8 | J46: =J45/'Income Statement'!J8 | ... L46: =L45/'Income Statement'!L8 | M46: The Information: H1'26 FCF ≈ $3.5B.
A47: FCF less SBC (shareholder-adjusted) | B47: $M | C47: =C45-'Opex Build'!C10 | D47: =D45-'Opex Build'!D10 | E47: =E45-'Opex Build'!E10 | F47: =F45-'Opex Build'!F10 | G47: =G45-'Opex Build'!G10 | H47: =H45-'Opex Build'!H10 | I47: =I45-'Opex Build'!I10 | J47: =J45-'Opex Build'!J10 | ... L47: =L45-'Opex Build'!L10

Sheet Compute Commitments
A1: Compute Commitments – contracted capacity vs. modelled demand
A2: Estimated annual expense phasing of the agreements disclosed in the S-1 (deal values as extracted by multiple outlets). Phasing is the author's estimate; the S-1 gives deal totals and terms, not annual schedules. Column B: 1 = non-cancellable.
A4: $M unless noted | B4: Unit | C4: FY2023A | D4: FY2024A | E4: FY2025A | F4: H1'26A | G4: H2'26E | H4: FY2026E | I4: FY2027E | J4: FY2028E | K4: FY2029E | L4: FY2030E | M4: Notes / source
C5: Actual | D5: Actual | E5: Actual | F5: Actual | G5: Forecast | H5: H1A + H2E | I5: Forecast | J5: Forecast | K5: Forecast | L5: Forecast
A7: Estimated expense recognised as capacity comes on-line ($M)
A8: Google Cloud – TPUs / cloud (≥$114.5B, Apr-26 to Jul-33) | B8: 1 | G8: 4000 | H8: =F8+G8 | I8: 10000 | J8: 16000 | K8: 20000 | L8: 22000 | M8: Deal value ~$114.5B. True-up if spend falls short; non-cancellable except Google breach.
A9: Amazon / AWS – Trainium & other (≥$110B, May-26 to Apr-36) | B9: 1 | G9: 3000 | H9: =F9+G9 | I9: 7000 | J9: 10000 | K9: 13000 | L9: 15000 | M9: Deal value ~$110.0B. Up to 5 GW; non-cancellable except Amazon breach.
A10: Broadcom – TPU equipment finance leases (~$161.2B rent, 5-yr) | B10: 1 | G10: 0 | H10: =F10+G10 | I10: 12000 | J10: 28000 | K10: 36000 | L10: 38000 | M10: Deal value ~$161.2B. Finance leases (D&A + interest in GAAP); modeled here as compute expense for simplicity.
A11: SpaceXAI – NVIDIA GPU capacity (up to $120.5B, ~$3.1B/mo at full) | B11: 0 | G11: 3000 | H11: =F11+G11 | I11: 20000 | J11: 37000 | K11: 37000 | L11: 23000 | M11: Deal value ~$120.5B. Cancellable on 90 days' notice after Jan/Mar 2027 – the main pressure valve.
A12: Microsoft Azure – NVIDIA GPUs (≥$44.9B, Nov-26 to May-33) | B12: 1 | G12: 500 | H12: =F12+G12 | I12: 5000 | J12: 7000 | K12: 8000 | L12: 8000 | M12: Deal value ~$44.9B. Amended upward Oct-26 from ~$30B.
A13: Nscale – NVIDIA GPUs (up to ~$44.6B, into 2033) | B13: 1 | G13: 500 | H13: =F13+G13 | I13: 3000 | J13: 6000 | K13: 7000 | L13: 7000 | M13: Deal value ~$44.6B. Paid as delivered; limited cancellation.
A14: Lambda – NVIDIA GPUs (~$41.3B, into 2034) | B14: 1 | G14: 500 | H14: =F14+G14 | I14: 3000 | J14: 5000 | K14: 6000 | L14: 7000 | M14: Deal value ~$41.3B. Large tranche depends on a facility lease.
A15: AMD – Instinct MI450 / Helios (>$20B, first tranche 2027) | B15: 1 | G15: 0 | H15: =F15+G15 | I15: 2000 | J15: 4000 | K15: 5000 | L15: 5000 | M15: Deal value ~$20.0B. AMD to buy up to $5B of Anthropic stock as chips deliver.
A16: Total estimated contracted compute expense | B16: $M | G16: =SUM(G8:G15) | H16: =F16+G16 | I16: =SUM(I8:I15) | J16: =SUM(J8:J15) | K16: =SUM(K8:K15) | L16: =SUM(L8:L15)
A17: of which non-cancellable (flag = 1) | B17: $M | G17: =SUMPRODUCT($B$8:$B$15,G8:G15) | H17: =F17+G17 | I17: =SUMPRODUCT($B$8:$B$15,I8:I15) | J17: =SUMPRODUCT($B$8:$B$15,J8:J15) | K17: =SUMPRODUCT($B$8:$B$15,K8:K15) | L17: =SUMPRODUCT($B$8:$B$15,L8:L15) | M17: Feeds the take-or-pay floor on the Compute Build sheet.
A18: of which cancellable (SpaceXAI) | B18: $M | G18: =G16-G17 | H18: =F18+G18 | I18: =I16-I17 | J18: =J16-J17 | K18: =K16-K17 | L18: =L16-L17
A19: Cumulative contracted expense 2026–2030 (memo) | B19: $M | G19: =G16 | H19: =G19 | I19: =H19+I16 | J19: =I19+J16 | K19: =J19+K16 | L19: =K19+L16 | M19: Compare: $265.6B minimum purchase commitments + $321.4B uncommenced leases at Jun-26A (through ~2036), plus ~$245B signed after Jun-26.
A21: Comparison with modelled compute demand
A22: Driver-based compute demand (Compute Build) | B22: $M | G22: ='Compute Build'!G23 | H22: =F22+G22 | I22: ='Compute Build'!I23 | J22: ='Compute Build'!J23 | K22: ='Compute Build'!K23 | L22: ='Compute Build'!L23
A23: Total compute & infrastructure expense in model | B23: $M | G23: ='Compute Build'!G26 | H23: =F23+G23 | I23: ='Compute Build'!I26 | J23: ='Compute Build'!J26 | K23: ='Compute Build'!K26 | L23: ='Compute Build'!L26
A24: Modelled expense – total contracted (positive = legacy capacity / on-demand / spot purchases) | B24: $M | G24: =G23-G16 | H24: =F24+G24 | I24: =I23-I16 | J24: =J23-J16 | K24: =K23-K16 | L24: =L23-L16 | M24: Pre-2026 Amazon/Google capacity and short-term purchases are not in the schedule above, so a positive gap is expected in 2026–27.
A25: Take-or-pay shortfall expensed (from Compute Build) | B25: $M | G25: ='Compute Build'!G25 | H25: =F25+G25 | I25: ='Compute Build'!I25 | J25: ='Compute Build'!J25 | K25: ='Compute Build'!K25 | L25: ='Compute Build'!L25 | M25: Non-zero when non-cancellable minimums exceed driver-based demand (check the Bear case).
A26: Contracted capacity coverage of demand (total contracted / demand) | B26: x | G26: =G16/G22 | H26: =H16/H22 | I26: =I16/I22 | J26: =J16/J22 | K26: =K16/K22 | L26: =L16/L22

Sheet Historical Data
A1: Historical Data – as filed (Form S-1, 26 Oct 2026)
A2: USD millions. FY2023–FY2025 audited; six-month periods unaudited. Blue = filed figure or flagged estimate.
A4: $M unless noted | B4: Unit | C4: FY2023A | D4: FY2024A | E4: FY2025A | F4: H1'26A | G4: H2'26E | H4: FY2026E | I4: FY2027E | J4: FY2028E | K4: FY2029E | L4: FY2030E | M4: Notes / source
C5: Actual | D5: Actual | E5: Actual | F5: Actual | G5: Forecast | H5: H1A + H2E | I5: Forecast | J5: Forecast | K5: Forecast | L5: Forecast
A7: Statement of operations – by nature of expense (primary presentation in the S-1)
A8: Revenue | B8: $M | C8: 41 | D8: 386 | E8: 4585 | F8: 16286
A9: Consumption-based (pay-for-intelligence) | B9: $M | C9: 39 | D9: 288 | E9: 3796 | F9: 13064
A10: Subscription-based | B10: $M | C10: 2 | D10: 98 | E10: 789 | F10: 3222
A11: Compute and infrastructure | B11: $M | C11: 433 | D11: 2522 | E11: 7326 | F11: 8945 | M11: Single fungible pool across training, research, serving and internal use.
A12: Personnel (incl. SBC) | B12: $M | C12: 95 | D12: 454 | E12: 1839 | F12: 3152
A13: Bartz copyright settlement | B13: $M | C13: 0 | D13: 0 | E13: 1500 | F13: 0 | M13: $1.5B settled 2025; $300M paid in 2025, $1.2B payable through Sep-27.
A14: Sales, marketing and partnerships | B14: $M | C14: 2 | D14: 43 | E14: 568 | F14: 3168 | M14: Channel-partner costs (AWS/GCP/Azure marketplaces) + advertising.
A15: Other operating and administrative | B15: $M | C15: 62 | D15: 347 | E15: 1412 | F15: 1714 | M15: Incl. donation-matching expense (FY25 $541M; H1'26 $126M).
A16: Total operating expenses | B16: $M | C16: 592 | D16: 3366 | E16: 12645 | F16: 16979
A17: Operating income (loss) | B17: $M | C17: -551 | D17: -2980 | E17: -8060 | F17: -693
A18: Interest income | B18: $M | C18: 69 | D18: 106 | E18: 431 | F18: 1111
A19: Change in FV of convertible notes, derivatives, SAFEs & other financial instruments | B19: $M | C19: -1045 | D19: -5434 | E19: -34308 | F19: -81108 | M19: H1'26 = $(72,388)M on notes/SAFEs + $(8,720)M recognition of 2026 note purchase agreements (reported within 'other').
A20: Other income (expense), net | B20: $M | C20: -2 | D20: 0 | E20: -8 | F20: -37 | M20: H1'26 residual after moving the $8,720M to the FV line.
A21: Income (loss) before income taxes | B21: $M | C21: -1529 | D21: -8308 | E21: -41945 | F21: -80727
A22: Provision for income taxes | B22: $M | C22: 2 | D22: 1 | E22: 20 | F22: 21
A23: Net income (loss) | B23: $M | C23: -1531 | D23: -8309 | E23: -41965 | F23: -80748
A25: Statement of operations – by function (S-1 supplemental note)
A26: Cost of revenue | B26: $M | C26: 26 | D26: 752 | E26: 2773 | F26: 2380 | M26: 'Substantially all' compute for customer-serving workloads + some personnel/overhead.
A27: Research and development | B27: $M | C27: 422 | D27: 2275 | E27: 6338 | F27: 9741 | M27: Primarily compute for model development, research and internal usage.
A28: Sales and marketing | B28: $M | C28: 76 | D28: 163 | E28: 911 | F28: 3808 | M28: Channel-partner costs, marketing, personnel, free-tier compute.
A29: General and administrative | B29: $M | C29: 68 | D29: 176 | E29: 1123 | F29: 1050 | M29: Donation matching, personnel, facilities, legal, non-income taxes.
A30: Functional total + Bartz settlement | B30: $M | C30: =C26+C27+C28+C29+C13 | D30: =D26+D27+D28+D29+D13 | E30: =E26+E27+E28+E29+E13 | F30: =F26+F27+F28+F29+F13 | M30: Ties to total operating expenses above.
A32: Cash flow statement (as filed)
A33: Stock-based compensation (cash-flow add-back) | B33: $M | C33: 29 | D33: 192 | E33: 1158 | F33: 2185
A34: Stock-based compensation (income statement, per non-GAAP reconciliation) | B34: $M | C34: 29 | D34: 192 | E34: 1165 | F34: 2185 | M34: FY25 IS expense $1,165M vs. $1,158M cash-flow add-back (small capitalised amount).
A35: Depreciation and amortization | B35: $M | C35: 3 | D35: 21 | E35: 40 | F35: 97
A36: Donation matching programme liability (non-cash) | B36: $M | C36: 0 | D36: 0 | E36: 541 | F36: 126
A37: Other non-cash items | B37: $M | C37: 0 | D37: 7 | E37: 11 | F37: -7
A38: Change in accounts receivable | B38: $M | C38: -10 | D38: -90 | E38: -834 | F38: -4982
A39: Change in prepaid expenses and other assets | B39: $M | C39: -1253 | D39: -3190 | E39: 1771 | F39: 2094
A40: Change in accounts payable, accrued and other liabilities | B40: $M | C40: 84 | D40: 222 | E40: 2079 | F40: 2679
A41: Change in lease liabilities | B41: $M | C41: -1 | D41: 0 | E41: 13 | F41: -3
A42: Change in deferred revenue | B42: $M | C42: 7 | D42: 21 | E42: 241 | F42: 1380
A43: Net cash from operating activities | B43: $M | C43: -1627 | D43: -5692 | E43: -2637 | F43: 3929
A44: Purchases of property and equipment | B44: $M | C44: -2 | D44: -15 | E44: -131 | F44: -482
A45: Purchases of short-term investments, net of sales/maturities | B45: $M | C45: 0 | D45: 0 | E45: -2869 | F45: -16362
A46: Other investing activities | B46: $M | C46: 0 | D46: -7 | E46: -77 | F46: -337
... A55: Cash, cash equivalents and restricted cash – end of period | B55: $M | C55: 1620 | D55: 3154 | E55: 17401 | F55: 114918
A57: Balance sheet (as filed) – column aligns with period end
A58: Cash and cash equivalents | B58: $M | D58: 3141 | E58: 17388 | F58: 112389
A59: Short-term investments | B59: $M | D59: 0 | E59: 2889 | F59: 19262
A60: Accounts receivable, net | B60: $M | D60: 95 | E60: 909 | F60: 5833
A61: Prepaid expenses and other current assets | B61: $M | D61: 2076 | E61: 2560 | F61: 496
A62: Restricted cash | B62: $M | D62: 13 | E62: 13 | F62: 2529
A63: Property and equipment, net | B63: $M | D63: 19 | E63: 146 | F63: 1187
A64: Operating lease right-of-use assets | B64: $M | D64: 35 | E64: 126 | F64: 1157
A65: Goodwill | B65: $M | D65: 0 | E65: 154 | F65: 576
A66: Other assets, noncurrent | B66: $M | D66: 2373 | E66: 476 | F66: 3929
A67: Total assets | B67: $M | D67: 7752 | E67: 24661 | F67: 147358
A68: Accounts payable, accrued expenses and other current liabilities | B68: $M | D68: 333 | E68: 2511 | F68: 5422
A69: Operating lease liabilities (current + noncurrent) | B69: $M | D69: 52 | E69: 117 | F69: 1079
... A78: Total stockholders' equity (deficit) | B78: $M | D78: -9801 | E78: -50505 | F78: -127619
A79: Balance-sheet columns: D = Dec-24A, E = Dec-25A, F = Jun-26A. Dec-23 balance sheet not presented in the S-1 in full.
A81: Quarterly revenue and compute (S-1 narrative; Q3'26 from 14 Oct 2026 investor day)
A82: Quarter | C82: Q4'24A | D82: Q1'25A | E82: Q2'25A | F82: Q3'25A | G82: Q4'25A | H82: Q1'26A | I82: Q2'26A | J82: Q3'26
A83: Revenue | B83: $M | C83: 197 | D83: 376 | E83: 787 | F83: 1382 | G83: 2040 | H83: 4731 | I83: 11555 | J83: 16800 | M83: Q3'26 $16.8B disclosed to investors (S-1 states it as 86× Q4'24 revenue ≈ $16.9B).
A84: Compute and infrastructure | B84: $M | D84: 944 | E84: 1390 | F84: 2047 | G84: 2945 | H84: 3387 | I84: 5558 | J84: =J83/J85 | M84: Q3'26 compute derived from the disclosed $1.70 of revenue per $1 of compute.
A85: Revenue per $1 of compute | B85: x | D85: =D83/D84 | E85: =E83/E84 | F85: =F83/F84 | G85: =G83/G84 | H85: =H83/H84 | I85: =I83/I84 | J85: 1.7
A87: Other disclosed data points
A88: Revenue, six months ended 30 Jun 2025 (unaudited) | B88: $M | C88: 1163 | M88: Implies H2'25 revenue of $3,422M – the comparison base for H2'26E growth.
A89: Run-rate revenue, end-July 2026 (company to investors) | B89: $M | C89: 65000 | M89: Run-rate = trailing 28-day consumption fees × 13 + monthly subscription fees × 12.
A90: Run-rate revenue, end-2025 | B90: $M | C90: 9000
A91: Adjusted operating margin, Q3'26 (company to investors) | B91: % | C91: 0.11
A92: Fixed / minimum compute purchase commitments at Jun-26A | B92: $M | C92: 265600 | M92: Terms 1–20 years; up from $54.6B at Dec-25.
A93: Leases signed but not yet commenced (undiscounted) at Jun-26A | B93: $M | C93: 321400 | M93: Primarily compute; commencement 2026–2028.
A94: Aggregate capital raised through Jun-26A | B94: $M | C94: 141100
A95: Unrecognised SBC on unvested RSUs at Jun-26A | B95: $M | C95: 26600

Sheet Checks
A1: Model Integrity Checks
A2: All rows should read 0 (or TRUE). Overall status at the top.
A4: $M unless noted | B4: Unit | C4: FY2023A | D4: FY2024A | E4: FY2025A | F4: H1'26A | G4: H2'26E | H4: FY2026E | I4: FY2027E | J4: FY2028E | K4: FY2029E | L4: FY2030E | M4: Notes / source
C5: Actual | D5: Actual | E5: Actual | F5: Actual | G5: Forecast | H5: H1A + H2E | I5: Forecast | J5: Forecast | K5: Forecast | L5: Forecast
A6: Balance sheet balances (assets – liabilities – equity) | B6: $M | D6: ='Balance Sheet'!D35 | E6: ='Balance Sheet'!E35 | F6: ='Balance Sheet'!F35 | G6: ='Balance Sheet'!G35 | H6: ='Balance Sheet'!H35 | I6: ='Balance Sheet'!I35 | J6: ='Balance Sheet'!J35 | K6: ='Balance Sheet'!K35 | L6: ='Balance Sheet'!L35
A7: Cash flow ending cash ties to balance sheet | B7: $M | G7: =ROUND('Cash Flow'!G41-'Balance Sheet'!G8,3) | H7: =ROUND('Cash Flow'!H41-'Balance Sheet'!H8,3) | I7: =ROUND('Cash Flow'!I41-'Balance Sheet'!I8,3) | J7: =ROUND('Cash Flow'!J41-'Balance Sheet'!J8,3) | K7: =ROUND('Cash Flow'!K41-'Balance Sheet'!K8,3) | L7: =ROUND('Cash Flow'!L41-'Balance Sheet'!L8,3)
A8: Opex by nature ties to functional presentation | B8: $M | C8: =ROUND('Income Statement'!C40,3) | D8: =ROUND('Income Statement'!D40,3) | E8: =ROUND('Income Statement'!E40,3) | F8: =ROUND('Income Statement'!F40,3) | G8: =ROUND('Income Statement'!G40,3) | H8: =ROUND('Income Statement'!H40,3) | I8: =ROUND('Income Statement'!I40,3) | J8: =ROUND('Income Statement'!J40,3) | ... L8: =ROUND('Income Statement'!L40,3)
A9: Net income ties to filed figures (historical) | B9: $M | C9: =ROUND('Income Statement'!C28,3) | D9: =ROUND('Income Statement'!D28,3) | E9: =ROUND('Income Statement'!E28,3) | F9: =ROUND('Income Statement'!F28,3)
A10: Operating cash flow ties to filed figures (historical) | B10: $M | C10: =ROUND('Cash Flow'!C20,3) | D10: =ROUND('Cash Flow'!D20,3) | E10: =ROUND('Cash Flow'!E20,3) | F10: =ROUND('Cash Flow'!F20,3)
A11: Expense allocation percentages sum to 100% | B11: $M | G11: =ROUND('Assumptions'!$C$50+'Assumptions'!$C$51+'Assumptions'!$C$52+'Assumptions'!$C$53-1,6)+ROUND('Assumptions'!$C$63+'Assumptions'!$C$64+'Assumptions'!$C$65+'Assumptions'!$C$66-1,6)
A12: Accumulated deficit rolls with net income (Jun-26A → Dec-26E) | B12: $M | G12: =ROUND('Balance Sheet'!G32-'Balance Sheet'!F32-'Income Statement'!G26,3)
A14: OVERALL MODEL STATUS | C14: =IF(SUMPRODUCT(ABS(C6:L12))<0.01,"OK – all checks pass","ERROR – review checks")
